Workbook
Name ___mo1: #REF!
Name __mo1: #REF!
Name _mo1: #REF!
Name AsOf: #REF!
Name aum_fee: #REF!
Name Bath: #REF!
Name Bed: #REF!
Name bond_AV_rate: #REF!
Name broker_fee: #REF!
Name CU?: #REF!
Name CUpt2: #REF!
Name CurrentEmpOtherConc: #REF!
Name CurrentInPlaceRent: #REF!
Name CurrentIsMonthToMonth: #REF!
Name CurrentLeaseExpirationDate: #REF!
Name CurrentLeaseSignedDate: #REF!
Name CurrentLeaseTerm: #REF!
Name CurrentMoveInDate: #REF!
Name CurrentMoveOutDate: #REF!
Name CurrentNetEffectiveRent: #REF!
Name CurrentOtherIncome: #REF!
Name CurrentRecurringConc: #REF!
Name CurrentSuppRent: #REF!
Name CurrentUpfrontConc: #REF!
Name DealName: #REF!
Name DealUnits: #REF!
Name Equity_Share_GP: #REF!
Name Equity_Share_LP: #REF!
Name FC_IRR: #REF!
Name fee_lot: #REF!
Name FF_1: #REF!
Name FF_2: #REF!
Name FF_3: #REF!
Name FF_4: #REF!
Name fin_rate: #REF!
Name FloorPlan: #REF!
Name FutureEmpOtherConc: #REF!
Name FutureInPlaceRent: #REF!
Name FutureLeaseColumn: #REF!
Name FutureLeaseExpiration: #REF!
Name FutureLeaseSignedDate: #REF!
Name FutureLeaseTerm: #REF!
Name FutureMoveInDate: #REF!
Name FutureNetEffectiveRent: #REF!
Name FutureOtherIncome: #REF!
Name FutureRecurringConc: #REF!
Name FutureSuppRent: #REF!
Name FutureUpfrontConc: #REF!
Name hurd1_IRR: #REF!
Name hurd2_IRR: #REF!
Name inv_share_equity: #REF!
Name inv_share_hurd1: #REF!
Name inv_share_hurd2: #REF!
Name inv_share_hurd3: #REF!
Name IO_Period: #REF!
Name IsEdit: #REF!
Name IsNoticeToVacate: #REF!
Name land_acre: #REF!
Name land_plan_lot: #REF!
Name Lev_IRR: #REF!

Sheet I. LeaseUp Template
B1: Lease-Up / Inventory Report - March 2026
B3: # of Units | C3: 117
B4: =COUNT('Data Table'!P2:P118) -> 57 | E4: =COUNTIF('Data Table'!O2:O118,"Tenant Occupied*") -> 55 | H4: =F14 -> 52 | K4: =F19 -> 53 | N4: =F24 -> 6
B6: Executed Leases To Date | E6: Current Occupancy | H6: Ending Occupancy March Budget | K6: Ending Occupancy March Actual | N6: Net Absorption March 2026
B7: =B4/C3 -> 0.48717949 | E7: =E4/C3 -> 0.47008547 | H7: =H4/C3 -> 0.44444444 | K7: =K4/C3 -> 0.45299145 | N7: =N4/C3 -> 0.051282051
B9: OCCUPANCY BY MONTH
D10: 46023 | E10: 46054 | F10: 46082 | G10: 46113 | H10: 46143 | I10: 46174 | J10: 46204 | K10: 46235 | L10: 46266 | M10: 46296 | N10: 46327 | O10: 46357 | P10: Total / Avg
H11: 2026 Budget
B12: Beginning | D12: 33 | E12: =D14 -> 40 | F12: =E14 -> 47 | G12: =F14 -> 52 | H12: =G14 -> 58 | I12: =H14 -> 68 | J12: =I14 -> 77 | K12: =J14 -> 85 | L12: =K14 -> 91 | ... O12: =N14 -> 104
B13: Absorption (# Units) | D13: =D14-D12 -> 7 | E13: =E14-E12 -> 7 | F13: =F14-F12 -> 5 | G13: =G14-G12 -> 6 | H13: =H14-H12 -> 10 | I13: =I14-I12 -> 9 | J13: =J14-J12 -> 8 | K13: =K14-K12 -> 6 | ... O13: =O14-O12 -> 3
B14: Ending OCC | D14: 40 | E14: 47 | F14: 52 | G14: 58 | H14: 68 | I14: 77 | J14: 85 | K14: 91 | L14: 96 | M14: 100 | N14: 104 | O14: 107 | P14: =O14 -> 107
B15: OCC % | D15: =D14/117 -> 0.34188034 | E15: =E14/117 -> 0.4017094 | F15: =F14/117 -> 0.44444444 | G15: =G14/117 -> 0.4957265 | H15: =H14/117 -> 0.58119658 | I15: =I14/117 -> 0.65811966 | J15: =J14/117 -> 0.72649573 | K15: =K14/117 -> 0.77777778 | ... P15: =P14/117 -> 0.91452991
H17: Actual + Projected
B18: Beginning | D18: 33 | E18: =D19 -> 41 | F18: =E19 -> 47 | G18: =F19 -> 53 | H18: =G19 -> 56 | I18: =H19 -> 57 | J18: =I19 -> 57 | K18: =J19 -> 57 | L18: =K19 -> 57 | ... P18: =O19 -> 57
B19: Ending OCC | D19: 41 | E19: =E18+E24 -> 47 | F19: =F18+F24 -> 53 | G19: =G18+G24 -> 56 | H19: =H18+H24 -> 57 | I19: =I18+I24 -> 57 | J19: =J18+J24 -> 57 | K19: =K18+K24 -> 57 | L19: =L18+L24 -> 57 | ... O19: =O18+O24 -> 57 | P19: =O19 -> 57
B20: OCC % | D20: =D19/$C$3 -> 0.35042735 | E20: =E19/$C$3 -> 0.4017094 | F20: =F19/$C$3 -> 0.45299145 | G20: =G19/$C$3 -> 0.47863248 | H20: =H19/$C$3 -> 0.48717949 | I20: =I19/$C$3 -> 0.48717949 | J20: =J19/$C$3 -> 0.48717949 | K20: =K19/$C$3 -> 0.48717949 | ... P20: =P19/$C$3 -> 0.48717949
B22: Move-ins | D22: =D19-D18 -> 8 | E22: ='Lease Tracker'!M14 -> 7 | F22: ='Lease Tracker'!N14 -> 6 | G22: ='Lease Tracker'!O14 -> 3 | H22: ='Lease Tracker'!P14 -> 1 | I22: ='Lease Tracker'!Q14 -> 1 | J22: ='Lease Tracker'!R14 -> 0 | K22: ='Lease Tracker'!S14 -> 0 | L22: ='Lease Tracker'!T14 -> 0 | ... O22: ='Lease Tracker'!W14 -> 0 | P22: =SUM(D22:O22) -> 26
B23: Move-Outs | E23: ='Lease Tracker'!M15 -> -1 | F23: ='Lease Tracker'!N15 -> 0 | G23: ='Lease Tracker'!O15 -> 0 | H23: ='Lease Tracker'!P15 -> 0 | I23: ='Lease Tracker'!Q15 -> -1 | J23: ='Lease Tracker'!R15 -> 0 | K23: ='Lease Tracker'!S15 -> 0 | L23: ='Lease Tracker'!T15 -> 0 | ... O23: ='Lease Tracker'!W15 -> 0 | P23: =SUM(D23:O23) -> -2
B24: Net Absorption | D24: =D23+D22 -> 8 | E24: =E23+E22 -> 6 | F24: =F23+F22 -> 6 | G24: =G23+G22 -> 3 | H24: =H23+H22 -> 1 | I24: =I23+I22 -> 0 | J24: =J23+J22 -> 0 | K24: =K23+K22 -> 0 | ... O24: =O23+O22 -> 0
B26: # Units Leased, Actual | D26: ='Lease Tracker'!L13 -> 8 | E26: 5 | F26: ='Lease Tracker'!N13 -> 3 | G26: ='Lease Tracker'!O13 -> 3 | H26: ='Lease Tracker'!P13 -> 0 | I26: ='Lease Tracker'!Q13 -> 0 | J26: ='Lease Tracker'!R13 -> 0 | K26: ='Lease Tracker'!S13 -> 0 | L26: ='Lease Tracker'!T13 -> 0 | M26: ='Lease Tracker'!U13 -> 0 | ... O26: ='Lease Tracker'!W13 -> 0 | P26: =SUM(D26:O26) -> 19
B27: Lease Expirations | E27: 0
B28: Renewals | F28: 2
B29: Cumulative Leases | D29: 47 | E29: =D29+E26+E27 -> 52 | F29: =E29+F26+F27 -> 55 | G29: =F29+G26+G27 -> 58 | H29: =G29+H26+H27 -> 58 | I29: =H29+I26+I27 -> 58 | J29: =I29+J26+J27 -> 58 | K29: =J29+K26+K27 -> 58 | L29: =K29+L26+L27 -> 58 | ... O29: =N29+O26+O27 -> 58 | P29: =O29 -> 58
D30: =D29/$C$3 -> 0.4017094 | E30: =E29/$C$3 -> 0.44444444 | F30: =F29/$C$3 -> 0.47008547 | G30: =G29/$C$3 -> 0.4957265 | H30: =H29/$C$3 -> 0.4957265 | I30: =I29/$C$3 -> 0.4957265 | J30: =J29/$C$3 -> 0.4957265 | K30: =K29/$C$3 -> 0.4957265 | ... O30: =O29/$C$3 -> 0.4957265
B31: Internal Proforma Budget
B32: # of Occ Units | D32: 44 | E32: 52 | F32: 60 | G32: 68 | H32: 76 | I32: 84 | J32: 92 | K32: 100 | L32: 108 | M32: 116 | N32: 116 | O32: 116 | P32: 116
B33: Ending OCC % | D33: =D32/117 -> 0.37606838 | E33: =E32/117 -> 0.44444444 | F33: =F32/117 -> 0.51282051 | G33: =G32/117 -> 0.58119658 | H33: =H32/117 -> 0.64957265 | I33: =I32/117 -> 0.71794872 | J33: =J32/117 -> 0.78632479 | K33: =K32/117 -> 0.85470085 | ... P33: =P32/117 -> 0.99145299
B35: LEASING PACE
B48: TRAFFIC SUMMARY & CONVERSIONS
G49: Total Traffic | H49: Prospects | I49: Tours | J49: Applications | K49: Cancels | L49: Denials | M49: Net Leases
D50: Mar 2026 | G50: 179 | H50: 83 | I50: 30 | J50: 6 | K50: 2 | L50: 1 | M50: =J50-K50-L50 -> 3
D51: Feb 2026 | G51: 187 | H51: 108 | I51: 26 | J51: ='Weekly Traffic'!E18 -> 0 | K51: ='Weekly Traffic'!G18 -> 0 | L51: ='Weekly Traffic'!H18 -> 0 | M51: =J51-K51-L51 -> 0
F52: Current Month Conversion: | H52: =IFERROR(H50/G50,0) -> 0.46368715 | I52: =IFERROR(I50/H50,0) -> 0.36144578 | J52: =IFERROR(J50/I50,0) -> 0.2 | M52: =IFERROR(M50/J50,0) -> 0.5
F53: KPIs | H53: Lead>Prosp. | I53: Prosp.>Tours | J53: Tour >App. | K53: App.>Leases
H54: 60% + | I54: 25% + | J54: 35% + | K54: 60%+
B55: Comments:
B56: Traffic was down in the month of February; however the team's conversions exceeded KPIs.
B59: LEASING BY PHASE
D60: 1 | E60: 2 | F60: 3 | G60: 4 | H60: 5 | I60: 6 | J60: Total | K60: % | L60: Comments:
B61: Floorplan | D61: Complete | E61: T/O Date | F61: T/O Date | G61: 45961 | H61: 45991 | I61: 46022 | J61: Units / Plan | K61: Leased | L61: Our leasing strategy is focused on incentivizing residents to move in by mid-month for the month to drive revenues up & meet / exceed leasing goals for the month. For April, we are short on our goals for ending occupancy and have adjusted specials to encourage lease-up through April to meet budget.
B62: Canary | D62: {=_xlfn.LET(_xlpm.fp,TRIM($B62),_xlpm.ph,D$60,_xlpm.leased,SUMPRODUCT((TRIM('Data Table'!$J$2:$J$118)=_xlpm.fp)*(IFERROR(--'Data Table'!$M$2:$M$118,0)=_xlpm.ph)*('Data Table'!$P$2:$P$118<>"")),_xlpm.total,SUMPRODUCT((TRIM('Data Table'!$J$2:$J$118)=_xlpm.fp)*(IFERROR(--'Data Table'!$M$2:$M$118,0)=_xlpm.ph)),IF(_xlpm.total=0,"",_xlpm.leased&" / "&_xlpm.total))} -> 8 / 8 | E62: {=_xlfn.LET(_xlpm.fp,TRIM($B62),_xlpm.ph,E$60,_xlpm.leased,SUMPRODUCT((TRIM('Data Table'!$J$2:$J$118)=_xlpm.fp)*(IFERROR(--'Data Table'!$M$2:$M$118,0)=_xlpm.ph)*('Data Table'!$P$2:$P$118<>"")),_xlpm.total,SUMPRODUCT((TRIM('Data Table'!$J$2:$J$118)=_xlpm.fp)*(IFERROR(--'Data Table'!$M$2:$M$118,0)=_xlpm.ph)),IF(_xlpm.total=0,"",_xlpm.leased&" / "&_xlpm.total))} -> 2 / 2 | F62: {=_xlfn.LET(_xlpm.fp,TRIM($B62),_xlpm.ph,F$60,_xlpm.leased,SUMPRODUCT((TRIM('Data Table'!$J$2:$J$118)=_xlpm.fp)*(IFERROR(--'Data Table'!$M$2:$M$118,0)=_xlpm.ph)*('Data Table'!$P$2:$P$118<>"")),_xlpm.total,SUMPRODUCT((TRIM('Data Table'!$J$2:$J$118)=_xlpm.fp)*(IFERROR(--'Data Table'!$M$2:$M$118,0)=_xlpm.ph)),IF(_xlpm.total=0,"",_xlpm.leased&" / "&_xlpm.total))} -> 3 / 6 | G62: {=_xlfn.LET(_xlpm.fp,TRIM($B62),_xlpm.ph,G$60,_xlpm.leased,SUMPRODUCT((TRIM('Data Table'!$J$2:$J$118)=_xlpm.fp)*(IFERROR(--'Data Table'!$M$2:$M$118,0)=_xlpm.ph)*('Data Table'!$P$2:$P$118<>"")),_xlpm.total,SUMPRODUCT((TRIM('Data Table'!$J$2:$J$118)=_xlpm.fp)*(IFERROR(--'Data Table'!$M$2:$M$118,0)=_xlpm.ph)),IF(_xlpm.total=0,"",_xlpm.leased&" / "&_xlpm.total))} -> 1 / 5 | H62: {=_xlfn.LET(_xlpm.fp,TRIM($B62),_xlpm.ph,H$60,_xlpm.leased,SUMPRODUCT((TRIM('Data Table'!$J$2:$J$118)=_xlpm.fp)*(IFERROR(--'Data Table'!$M$2:$M$118,0)=_xlpm.ph)*('Data Table'!$P$2:$P$118<>"")),_xlpm.total,SUMPRODUCT((TRIM('Data Table'!$J$2:$J$118)=_xlpm.fp)*(IFERROR(--'Data Table'!$M$2:$M$118,0)=_xlpm.ph)),IF(_xlpm.total=0,"",_xlpm.leased&" / "&_xlpm.total))} -> 1 / 6 | I62: {=_xlfn.LET(_xlpm.fp,TRIM($B62),_xlpm.ph,I$60,_xlpm.leased,SUMPRODUCT((TRIM('Data Table'!$J$2:$J$118)=_xlpm.fp)*(IFERROR(--'Data Table'!$M$2:$M$118,0)=_xlpm.ph)*('Data Table'!$P$2:$P$118<>"")),_xlpm.total,SUMPRODUCT((TRIM('Data Table'!$J$2:$J$118)=_xlpm.fp)*(IFERROR(--'Data Table'!$M$2:$M$118,0)=_xlpm.ph)),IF(_xlpm.total=0,"",_xlpm.leased&" / "&_xlpm.total))} -> 1 / 4 | J62: {=_xlfn.LET(_xlpm.fp, SUBSTITUTE(SUBSTITUTE($B62,CHAR(160),"")," ",""),_xlpm.g, SUBSTITUTE(SUBSTITUTE('Data Table'!$J$2:$J$118,CHAR(160),"")," ",""),_xlpm.m, 'Data Table'!$P$2:$P$118,_xlpm.leased, SUMPRODUCT(--(_xlpm.g=_xlpm.fp), --ISNUMBER(_xlpm.m)),_xlpm.total, SUMPRODUCT(--(_xlpm.g=_xlpm.fp)),IF(_xlpm.total=0,"", _xlpm.leased & " / " & _xlpm.total))} -> 16 / 31 | K62: =16/31 -> 0.51612903
B63: Sparrow | D63: {=_xlfn.LET(_xlpm.fp,TRIM($B63),_xlpm.ph,D$60,_xlpm.leased,SUMPRODUCT((TRIM('Data Table'!$J$2:$J$118)=_xlpm.fp)*(IFERROR(--'Data Table'!$M$2:$M$118,0)=_xlpm.ph)*('Data Table'!$P$2:$P$118<>"")),_xlpm.total,SUMPRODUCT((TRIM('Data Table'!$J$2:$J$118)=_xlpm.fp)*(IFERROR(--'Data Table'!$M$2:$M$118,0)=_xlpm.ph)),IF(_xlpm.total=0,"",_xlpm.leased&" / "&_xlpm.total))} -> 2 / 3 | E63: {=_xlfn.LET(_xlpm.fp,TRIM($B63),_xlpm.ph,E$60,_xlpm.leased,SUMPRODUCT((TRIM('Data Table'!$J$2:$J$118)=_xlpm.fp)*(IFERROR(--'Data Table'!$M$2:$M$118,0)=_xlpm.ph)*('Data Table'!$P$2:$P$118<>"")),_xlpm.total,SUMPRODUCT((TRIM('Data Table'!$J$2:$J$118)=_xlpm.fp)*(IFERROR(--'Data Table'!$M$2:$M$118,0)=_xlpm.ph)),IF(_xlpm.total=0,"",_xlpm.leased&" / "&_xlpm.total))} -> 1 / 3 | F63: {=_xlfn.LET(_xlpm.fp,TRIM($B63),_xlpm.ph,F$60,_xlpm.leased,SUMPRODUCT((TRIM('Data Table'!$J$2:$J$118)=_xlpm.fp)*(IFERROR(--'Data Table'!$M$2:$M$118,0)=_xlpm.ph)*('Data Table'!$P$2:$P$118<>"")),_xlpm.total,SUMPRODUCT((TRIM('Data Table'!$J$2:$J$118)=_xlpm.fp)*(IFERROR(--'Data Table'!$M$2:$M$118,0)=_xlpm.ph)),IF(_xlpm.total=0,"",_xlpm.leased&" / "&_xlpm.total))} -> 2 / 3 | G63: {=_xlfn.LET(_xlpm.fp,TRIM($B63),_xlpm.ph,G$60,_xlpm.leased,SUMPRODUCT((TRIM('Data Table'!$J$2:$J$118)=_xlpm.fp)*(IFERROR(--'Data Table'!$M$2:$M$118,0)=_xlpm.ph)*('Data Table'!$P$2:$P$118<>"")),_xlpm.total,SUMPRODUCT((TRIM('Data Table'!$J$2:$J$118)=_xlpm.fp)*(IFERROR(--'Data Table'!$M$2:$M$118,0)=_xlpm.ph)),IF(_xlpm.total=0,"",_xlpm.leased&" / "&_xlpm.total))} -> 0 / 5 | H63: {=_xlfn.LET(_xlpm.fp,TRIM($B63),_xlpm.ph,H$60,_xlpm.leased,SUMPRODUCT((TRIM('Data Table'!$J$2:$J$118)=_xlpm.fp)*(IFERROR(--'Data Table'!$M$2:$M$118,0)=_xlpm.ph)*('Data Table'!$P$2:$P$118<>"")),_xlpm.total,SUMPRODUCT((TRIM('Data Table'!$J$2:$J$118)=_xlpm.fp)*(IFERROR(--'Data Table'!$M$2:$M$118,0)=_xlpm.ph)),IF(_xlpm.total=0,"",_xlpm.leased&" / "&_xlpm.total))} -> 1 / 2 | I63: {=_xlfn.LET(_xlpm.fp,TRIM($B63),_xlpm.ph,I$60,_xlpm.leased,SUMPRODUCT((TRIM('Data Table'!$J$2:$J$118)=_xlpm.fp)*(IFERROR(--'Data Table'!$M$2:$M$118,0)=_xlpm.ph)*('Data Table'!$P$2:$P$118<>"")),_xlpm.total,SUMPRODUCT((TRIM('Data Table'!$J$2:$J$118)=_xlpm.fp)*(IFERROR(--'Data Table'!$M$2:$M$118,0)=_xlpm.ph)),IF(_xlpm.total=0,"",_xlpm.leased&" / "&_xlpm.total))} -> 1 / 2 | J63: {=_xlfn.LET(_xlpm.fp, SUBSTITUTE(SUBSTITUTE($B63,CHAR(160),"")," ",""),_xlpm.g, SUBSTITUTE(SUBSTITUTE('Data Table'!$J$2:$J$118,CHAR(160),"")," ",""),_xlpm.m, 'Data Table'!$P$2:$P$118,_xlpm.leased, SUMPRODUCT(--(_xlpm.g=_xlpm.fp), --ISNUMBER(_xlpm.m)),_xlpm.total, SUMPRODUCT(--(_xlpm.g=_xlpm.fp)),IF(_xlpm.total=0,"", _xlpm.leased & " / " & _xlpm.total))} -> 7 / 18 | K63: =6/18 -> 0.33333333
B64: Mallard | D64: {=_xlfn.LET(_xlpm.fp,TRIM($B64),_xlpm.ph,D$60,_xlpm.leased,SUMPRODUCT((TRIM('Data Table'!$J$2:$J$118)=_xlpm.fp)*(IFERROR(--'Data Table'!$M$2:$M$118,0)=_xlpm.ph)*('Data Table'!$P$2:$P$118<>"")),_xlpm.total,SUMPRODUCT((TRIM('Data Table'!$J$2:$J$118)=_xlpm.fp)*(IFERROR(--'Data Table'!$M$2:$M$118,0)=_xlpm.ph)),IF(_xlpm.total=0,"",_xlpm.leased&" / "&_xlpm.total))} -> 5 / 6 | E64: {=_xlfn.LET(_xlpm.fp,TRIM($B64),_xlpm.ph,E$60,_xlpm.leased,SUMPRODUCT((TRIM('Data Table'!$J$2:$J$118)=_xlpm.fp)*(IFERROR(--'Data Table'!$M$2:$M$118,0)=_xlpm.ph)*('Data Table'!$P$2:$P$118<>"")),_xlpm.total,SUMPRODUCT((TRIM('Data Table'!$J$2:$J$118)=_xlpm.fp)*(IFERROR(--'Data Table'!$M$2:$M$118,0)=_xlpm.ph)),IF(_xlpm.total=0,"",_xlpm.leased&" / "&_xlpm.total))} -> 2 / 2 | F64: {=_xlfn.LET(_xlpm.fp,TRIM($B64),_xlpm.ph,F$60,_xlpm.leased,SUMPRODUCT((TRIM('Data Table'!$J$2:$J$118)=_xlpm.fp)*(IFERROR(--'Data Table'!$M$2:$M$118,0)=_xlpm.ph)*('Data Table'!$P$2:$P$118<>"")),_xlpm.total,SUMPRODUCT((TRIM('Data Table'!$J$2:$J$118)=_xlpm.fp)*(IFERROR(--'Data Table'!$M$2:$M$118,0)=_xlpm.ph)),IF(_xlpm.total=0,"",_xlpm.leased&" / "&_xlpm.total))} -> 5 / 6 | G64: {=_xlfn.LET(_xlpm.fp,TRIM($B64),_xlpm.ph,G$60,_xlpm.leased,SUMPRODUCT((TRIM('Data Table'!$J$2:$J$118)=_xlpm.fp)*(IFERROR(--'Data Table'!$M$2:$M$118,0)=_xlpm.ph)*('Data Table'!$P$2:$P$118<>"")),_xlpm.total,SUMPRODUCT((TRIM('Data Table'!$J$2:$J$118)=_xlpm.fp)*(IFERROR(--'Data Table'!$M$2:$M$118,0)=_xlpm.ph)),IF(_xlpm.total=0,"",_xlpm.leased&" / "&_xlpm.total))} -> 2 / 3 | H64: {=_xlfn.LET(_xlpm.fp,TRIM($B64),_xlpm.ph,H$60,_xlpm.leased,SUMPRODUCT((TRIM('Data Table'!$J$2:$J$118)=_xlpm.fp)*(IFERROR(--'Data Table'!$M$2:$M$118,0)=_xlpm.ph)*('Data Table'!$P$2:$P$118<>"")),_xlpm.total,SUMPRODUCT((TRIM('Data Table'!$J$2:$J$118)=_xlpm.fp)*(IFERROR(--'Data Table'!$M$2:$M$118,0)=_xlpm.ph)),IF(_xlpm.total=0,"",_xlpm.leased&" / "&_xlpm.total))} -> 4 / 4 | I64: {=_xlfn.LET(_xlpm.fp,TRIM($B64),_xlpm.ph,I$60,_xlpm.leased,SUMPRODUCT((TRIM('Data Table'!$J$2:$J$118)=_xlpm.fp)*(IFERROR(--'Data Table'!$M$2:$M$118,0)=_xlpm.ph)*('Data Table'!$P$2:$P$118<>"")),_xlpm.total,SUMPRODUCT((TRIM('Data Table'!$J$2:$J$118)=_xlpm.fp)*(IFERROR(--'Data Table'!$M$2:$M$118,0)=_xlpm.ph)),IF(_xlpm.total=0,"",_xlpm.leased&" / "&_xlpm.total))} -> 3 / 4 | J64: {=_xlfn.LET(_xlpm.fp, SUBSTITUTE(SUBSTITUTE($B64,CHAR(160),"")," ",""),_xlpm.g, SUBSTITUTE(SUBSTITUTE('Data Table'!$J$2:$J$118,CHAR(160),"")," ",""),_xlpm.m, 'Data Table'!$P$2:$P$118,_xlpm.leased, SUMPRODUCT(--(_xlpm.g=_xlpm.fp), --ISNUMBER(_xlpm.m)),_xlpm.total, SUMPRODUCT(--(_xlpm.g=_xlpm.fp)),IF(_xlpm.total=0,"", _xlpm.leased & " / " & _xlpm.total))} -> 21 / 25 | K64: =20/25 -> 0.8
B65: Raven | D65: {=_xlfn.LET(_xlpm.fp,TRIM($B65),_xlpm.ph,D$60,_xlpm.leased,SUMPRODUCT((TRIM('Data Table'!$J$2:$J$118)=_xlpm.fp)*(IFERROR(--'Data Table'!$M$2:$M$118,0)=_xlpm.ph)*('Data Table'!$P$2:$P$118<>"")),_xlpm.total,SUMPRODUCT((TRIM('Data Table'!$J$2:$J$118)=_xlpm.fp)*(IFERROR(--'Data Table'!$M$2:$M$118,0)=_xlpm.ph)),IF(_xlpm.total=0,"",_xlpm.leased&" / "&_xlpm.total))} -> 2 / 3 | E65: {=_xlfn.LET(_xlpm.fp,TRIM($B65),_xlpm.ph,E$60,_xlpm.leased,SUMPRODUCT((TRIM('Data Table'!$J$2:$J$118)=_xlpm.fp)*(IFERROR(--'Data Table'!$M$2:$M$118,0)=_xlpm.ph)*('Data Table'!$P$2:$P$118<>"")),_xlpm.total,SUMPRODUCT((TRIM('Data Table'!$J$2:$J$118)=_xlpm.fp)*(IFERROR(--'Data Table'!$M$2:$M$118,0)=_xlpm.ph)),IF(_xlpm.total=0,"",_xlpm.leased&" / "&_xlpm.total))} -> 1 / 3 | F65: {=_xlfn.LET(_xlpm.fp,TRIM($B65),_xlpm.ph,F$60,_xlpm.leased,SUMPRODUCT((TRIM('Data Table'!$J$2:$J$118)=_xlpm.fp)*(IFERROR(--'Data Table'!$M$2:$M$118,0)=_xlpm.ph)*('Data Table'!$P$2:$P$118<>"")),_xlpm.total,SUMPRODUCT((TRIM('Data Table'!$J$2:$J$118)=_xlpm.fp)*(IFERROR(--'Data Table'!$M$2:$M$118,0)=_xlpm.ph)),IF(_xlpm.total=0,"",_xlpm.leased&" / "&_xlpm.total))} -> 0 / 5 | G65: {=_xlfn.LET(_xlpm.fp,TRIM($B65),_xlpm.ph,G$60,_xlpm.leased,SUMPRODUCT((TRIM('Data Table'!$J$2:$J$118)=_xlpm.fp)*(IFERROR(--'Data Table'!$M$2:$M$118,0)=_xlpm.ph)*('Data Table'!$P$2:$P$118<>"")),_xlpm.total,SUMPRODUCT((TRIM('Data Table'!$J$2:$J$118)=_xlpm.fp)*(IFERROR(--'Data Table'!$M$2:$M$118,0)=_xlpm.ph)),IF(_xlpm.total=0,"",_xlpm.leased&" / "&_xlpm.total))} -> 1 / 2 | H65: {=_xlfn.LET(_xlpm.fp,TRIM($B65),_xlpm.ph,H$60,_xlpm.leased,SUMPRODUCT((TRIM('Data Table'!$J$2:$J$118)=_xlpm.fp)*(IFERROR(--'Data Table'!$M$2:$M$118,0)=_xlpm.ph)*('Data Table'!$P$2:$P$118<>"")),_xlpm.total,SUMPRODUCT((TRIM('Data Table'!$J$2:$J$118)=_xlpm.fp)*(IFERROR(--'Data Table'!$M$2:$M$118,0)=_xlpm.ph)),IF(_xlpm.total=0,"",_xlpm.leased&" / "&_xlpm.total))} -> 2 / 3 | I65: {=_xlfn.LET(_xlpm.fp,TRIM($B65),_xlpm.ph,I$60,_xlpm.leased,SUMPRODUCT((TRIM('Data Table'!$J$2:$J$118)=_xlpm.fp)*(IFERROR(--'Data Table'!$M$2:$M$118,0)=_xlpm.ph)*('Data Table'!$P$2:$P$118<>"")),_xlpm.total,SUMPRODUCT((TRIM('Data Table'!$J$2:$J$118)=_xlpm.fp)*(IFERROR(--'Data Table'!$M$2:$M$118,0)=_xlpm.ph)),IF(_xlpm.total=0,"",_xlpm.leased&" / "&_xlpm.total))} -> 2 / 5 | J65: {=_xlfn.LET(_xlpm.fp, SUBSTITUTE(SUBSTITUTE($B65,CHAR(160),"")," ",""),_xlpm.g, SUBSTITUTE(SUBSTITUTE('Data Table'!$J$2:$J$118,CHAR(160),"")," ",""),_xlpm.m, 'Data Table'!$P$2:$P$118,_xlpm.leased, SUMPRODUCT(--(_xlpm.g=_xlpm.fp), --ISNUMBER(_xlpm.m)),_xlpm.total, SUMPRODUCT(--(_xlpm.g=_xlpm.fp)),IF(_xlpm.total=0,"", _xlpm.leased & " / " & _xlpm.total))} -> 8 / 21 | K65: =7/21 -> 0.33333333
B66: Falcon | D66: {=_xlfn.LET(_xlpm.fp,TRIM($B66),_xlpm.ph,D$60,_xlpm.leased,SUMPRODUCT((TRIM('Data Table'!$J$2:$J$118)=_xlpm.fp)*(IFERROR(--'Data Table'!$M$2:$M$118,0)=_xlpm.ph)*('Data Table'!$P$2:$P$118<>"")),_xlpm.total,SUMPRODUCT((TRIM('Data Table'!$J$2:$J$118)=_xlpm.fp)*(IFERROR(--'Data Table'!$M$2:$M$118,0)=_xlpm.ph)),IF(_xlpm.total=0,"",_xlpm.leased&" / "&_xlpm.total))} | E66: {=_xlfn.LET(_xlpm.fp,TRIM($B66),_xlpm.ph,E$60,_xlpm.leased,SUMPRODUCT((TRIM('Data Table'!$J$2:$J$118)=_xlpm.fp)*(IFERROR(--'Data Table'!$M$2:$M$118,0)=_xlpm.ph)*('Data Table'!$P$2:$P$118<>"")),_xlpm.total,SUMPRODUCT((TRIM('Data Table'!$J$2:$J$118)=_xlpm.fp)*(IFERROR(--'Data Table'!$M$2:$M$118,0)=_xlpm.ph)),IF(_xlpm.total=0,"",_xlpm.leased&" / "&_xlpm.total))} -> 2 / 6 | F66: {=_xlfn.LET(_xlpm.fp,TRIM($B66),_xlpm.ph,F$60,_xlpm.leased,SUMPRODUCT((TRIM('Data Table'!$J$2:$J$118)=_xlpm.fp)*(IFERROR(--'Data Table'!$M$2:$M$118,0)=_xlpm.ph)*('Data Table'!$P$2:$P$118<>"")),_xlpm.total,SUMPRODUCT((TRIM('Data Table'!$J$2:$J$118)=_xlpm.fp)*(IFERROR(--'Data Table'!$M$2:$M$118,0)=_xlpm.ph)),IF(_xlpm.total=0,"",_xlpm.leased&" / "&_xlpm.total))} | G66: {=_xlfn.LET(_xlpm.fp,TRIM($B66),_xlpm.ph,G$60,_xlpm.leased,SUMPRODUCT((TRIM('Data Table'!$J$2:$J$118)=_xlpm.fp)*(IFERROR(--'Data Table'!$M$2:$M$118,0)=_xlpm.ph)*('Data Table'!$P$2:$P$118<>"")),_xlpm.total,SUMPRODUCT((TRIM('Data Table'!$J$2:$J$118)=_xlpm.fp)*(IFERROR(--'Data Table'!$M$2:$M$118,0)=_xlpm.ph)),IF(_xlpm.total=0,"",_xlpm.leased&" / "&_xlpm.total))} -> 0 / 1 | H66: {=_xlfn.LET(_xlpm.fp,TRIM($B66),_xlpm.ph,H$60,_xlpm.leased,SUMPRODUCT((TRIM('Data Table'!$J$2:$J$118)=_xlpm.fp)*(IFERROR(--'Data Table'!$M$2:$M$118,0)=_xlpm.ph)*('Data Table'!$P$2:$P$118<>"")),_xlpm.total,SUMPRODUCT((TRIM('Data Table'!$J$2:$J$118)=_xlpm.fp)*(IFERROR(--'Data Table'!$M$2:$M$118,0)=_xlpm.ph)),IF(_xlpm.total=0,"",_xlpm.leased&" / "&_xlpm.total))} -> 1 / 4 | I66: {=_xlfn.LET(_xlpm.fp,TRIM($B66),_xlpm.ph,I$60,_xlpm.leased,SUMPRODUCT((TRIM('Data Table'!$J$2:$J$118)=_xlpm.fp)*(IFERROR(--'Data Table'!$M$2:$M$118,0)=_xlpm.ph)*('Data Table'!$P$2:$P$118<>"")),_xlpm.total,SUMPRODUCT((TRIM('Data Table'!$J$2:$J$118)=_xlpm.fp)*(IFERROR(--'Data Table'!$M$2:$M$118,0)=_xlpm.ph)),IF(_xlpm.total=0,"",_xlpm.leased&" / "&_xlpm.total))} -> 0 / 5 | J66: {=_xlfn.LET(_xlpm.fp, SUBSTITUTE(SUBSTITUTE($B66,CHAR(160),"")," ",""),_xlpm.g, SUBSTITUTE(SUBSTITUTE('Data Table'!$J$2:$J$118,CHAR(160),"")," ",""),_xlpm.m, 'Data Table'!$P$2:$P$118,_xlpm.leased, SUMPRODUCT(--(_xlpm.g=_xlpm.fp), --ISNUMBER(_xlpm.m)),_xlpm.total, SUMPRODUCT(--(_xlpm.g=_xlpm.fp)),IF(_xlpm.total=0,"", _xlpm.leased & " / " & _xlpm.total))} -> 3 / 16 | K66: =3/16 -> 0.1875
B67: Phoenix | D67: {=_xlfn.LET(_xlpm.fp,TRIM($B67),_xlpm.ph,D$60,_xlpm.leased,SUMPRODUCT((TRIM('Data Table'!$J$2:$J$118)=_xlpm.fp)*(IFERROR(--'Data Table'!$M$2:$M$118,0)=_xlpm.ph)*('Data Table'!$P$2:$P$118<>"")),_xlpm.total,SUMPRODUCT((TRIM('Data Table'!$J$2:$J$118)=_xlpm.fp)*(IFERROR(--'Data Table'!$M$2:$M$118,0)=_xlpm.ph)),IF(_xlpm.total=0,"",_xlpm.leased&" / "&_xlpm.total))} | E67: {=_xlfn.LET(_xlpm.fp,TRIM($B67),_xlpm.ph,E$60,_xlpm.leased,SUMPRODUCT((TRIM('Data Table'!$J$2:$J$118)=_xlpm.fp)*(IFERROR(--'Data Table'!$M$2:$M$118,0)=_xlpm.ph)*('Data Table'!$P$2:$P$118<>"")),_xlpm.total,SUMPRODUCT((TRIM('Data Table'!$J$2:$J$118)=_xlpm.fp)*(IFERROR(--'Data Table'!$M$2:$M$118,0)=_xlpm.ph)),IF(_xlpm.total=0,"",_xlpm.leased&" / "&_xlpm.total))} -> 2 / 5 | F67: {=_xlfn.LET(_xlpm.fp,TRIM($B67),_xlpm.ph,F$60,_xlpm.leased,SUMPRODUCT((TRIM('Data Table'!$J$2:$J$118)=_xlpm.fp)*(IFERROR(--'Data Table'!$M$2:$M$118,0)=_xlpm.ph)*('Data Table'!$P$2:$P$118<>"")),_xlpm.total,SUMPRODUCT((TRIM('Data Table'!$J$2:$J$118)=_xlpm.fp)*(IFERROR(--'Data Table'!$M$2:$M$118,0)=_xlpm.ph)),IF(_xlpm.total=0,"",_xlpm.leased&" / "&_xlpm.total))} | G67: {=_xlfn.LET(_xlpm.fp,TRIM($B67),_xlpm.ph,G$60,_xlpm.leased,SUMPRODUCT((TRIM('Data Table'!$J$2:$J$118)=_xlpm.fp)*(IFERROR(--'Data Table'!$M$2:$M$118,0)=_xlpm.ph)*('Data Table'!$P$2:$P$118<>"")),_xlpm.total,SUMPRODUCT((TRIM('Data Table'!$J$2:$J$118)=_xlpm.fp)*(IFERROR(--'Data Table'!$M$2:$M$118,0)=_xlpm.ph)),IF(_xlpm.total=0,"",_xlpm.leased&" / "&_xlpm.total))} | H67: {=_xlfn.LET(_xlpm.fp,TRIM($B67),_xlpm.ph,H$60,_xlpm.leased,SUMPRODUCT((TRIM('Data Table'!$J$2:$J$118)=_xlpm.fp)*(IFERROR(--'Data Table'!$M$2:$M$118,0)=_xlpm.ph)*('Data Table'!$P$2:$P$118<>"")),_xlpm.total,SUMPRODUCT((TRIM('Data Table'!$J$2:$J$118)=_xlpm.fp)*(IFERROR(--'Data Table'!$M$2:$M$118,0)=_xlpm.ph)),IF(_xlpm.total=0,"",_xlpm.leased&" / "&_xlpm.total))} -> 0 / 1 | I67: {=_xlfn.LET(_xlpm.fp,TRIM($B67),_xlpm.ph,I$60,_xlpm.leased,SUMPRODUCT((TRIM('Data Table'!$J$2:$J$118)=_xlpm.fp)*(IFERROR(--'Data Table'!$M$2:$M$118,0)=_xlpm.ph)*('Data Table'!$P$2:$P$118<>"")),_xlpm.total,SUMPRODUCT((TRIM('Data Table'!$J$2:$J$118)=_xlpm.fp)*(IFERROR(--'Data Table'!$M$2:$M$118,0)=_xlpm.ph)),IF(_xlpm.total=0,"",_xlpm.leased&" / "&_xlpm.total))} | J67: {=_xlfn.LET(_xlpm.fp, SUBSTITUTE(SUBSTITUTE($B67,CHAR(160),"")," ",""),_xlpm.g, SUBSTITUTE(SUBSTITUTE('Data Table'!$J$2:$J$118,CHAR(160),"")," ",""),_xlpm.m, 'Data Table'!$P$2:$P$118,_xlpm.leased, SUMPRODUCT(--(_xlpm.g=_xlpm.fp), --ISNUMBER(_xlpm.m)),_xlpm.total, SUMPRODUCT(--(_xlpm.g=_xlpm.fp)),IF(_xlpm.total=0,"", _xlpm.leased & " / " & _xlpm.total))} -> 2 / 6 | K67: =2/6 -> 0.33333333
B68: Total Units / Phase | D68: {=_xlfn.LET(_xlpm.ph,D$60,_xlpm.j,'Data Table'!$M$2:$M$118,_xlpm.m,'Data Table'!$P$2:$P$118,_xlpm.isPh,--(IFERROR(--_xlpm.j,0)=_xlpm.ph),_xlpm.leased,SUMPRODUCT(_xlpm.isPh, --ISNUMBER(_xlpm.m)),_xlpm.total, SUMPRODUCT(_xlpm.isPh),IF(_xlpm.total=0,"", _xlpm.leased & " / " & _xlpm.total))} -> 17 / 20 | E68: {=_xlfn.LET(_xlpm.ph,E$60,_xlpm.j,'Data Table'!$M$2:$M$118,_xlpm.m,'Data Table'!$P$2:$P$118,_xlpm.isPh,--(IFERROR(--_xlpm.j,0)=_xlpm.ph),_xlpm.leased,SUMPRODUCT(_xlpm.isPh, --ISNUMBER(_xlpm.m)),_xlpm.total, SUMPRODUCT(_xlpm.isPh),IF(_xlpm.total=0,"", _xlpm.leased & " / " & _xlpm.total))} -> 10 / 21 | F68: {=_xlfn.LET(_xlpm.ph,F$60,_xlpm.j,'Data Table'!$M$2:$M$118,_xlpm.m,'Data Table'!$P$2:$P$118,_xlpm.isPh,--(IFERROR(--_xlpm.j,0)=_xlpm.ph),_xlpm.leased,SUMPRODUCT(_xlpm.isPh, --ISNUMBER(_xlpm.m)),_xlpm.total, SUMPRODUCT(_xlpm.isPh),IF(_xlpm.total=0,"", _xlpm.leased & " / " & _xlpm.total))} -> 10 / 20 | G68: {=_xlfn.LET(_xlpm.ph,G$60,_xlpm.j,'Data Table'!$M$2:$M$118,_xlpm.m,'Data Table'!$P$2:$P$118,_xlpm.isPh,--(IFERROR(--_xlpm.j,0)=_xlpm.ph),_xlpm.leased,SUMPRODUCT(_xlpm.isPh, --ISNUMBER(_xlpm.m)),_xlpm.total, SUMPRODUCT(_xlpm.isPh),IF(_xlpm.total=0,"", _xlpm.leased & " / " & _xlpm.total))} -> 4 / 16 | H68: {=_xlfn.LET(_xlpm.ph,H$60,_xlpm.j,'Data Table'!$M$2:$M$118,_xlpm.m,'Data Table'!$P$2:$P$118,_xlpm.isPh,--(IFERROR(--_xlpm.j,0)=_xlpm.ph),_xlpm.leased,SUMPRODUCT(_xlpm.isPh, --ISNUMBER(_xlpm.m)),_xlpm.total, SUMPRODUCT(_xlpm.isPh),IF(_xlpm.total=0,"", _xlpm.leased & " / " & _xlpm.total))} -> 9 / 20 | I68: {=_xlfn.LET(_xlpm.ph,I$60,_xlpm.j,'Data Table'!$M$2:$M$118,_xlpm.m,'Data Table'!$P$2:$P$118,_xlpm.isPh,--(IFERROR(--_xlpm.j,0)=_xlpm.ph),_xlpm.leased,SUMPRODUCT(_xlpm.isPh, --ISNUMBER(_xlpm.m)),_xlpm.total, SUMPRODUCT(_xlpm.isPh),IF(_xlpm.total=0,"", _xlpm.leased & " / " & _xlpm.total))} -> 7 / 20 | J68: {=_xlfn.LET(_xlpm.m,'Data Table'!$P$2:$P$118,_xlpm.leased,SUMPRODUCT(--ISNUMBER(_xlpm.m)),_xlpm.total,COUNTA('Data Table'!$J$2:$J$118),IF(_xlpm.total=0,"", _xlpm.leased & " / " & _xlpm.total))} -> 57 / 117 | K68: =54/117 -> 0.46153846
B70: SUMMARY BY FLOORPLAN
B71: Floorplan | D71: Bedrooms | E71: Unit Count | F71: Unit SF | G71: # Leased | H71: % Leased | I71: Units Occupied | J71: % Occupied | K71: # Avail | L71: Market Rent | M71: Market $/ SF | N71: Effective Rent | O71: Effective $/ SF
B72: Canary | C72: TH-A | D72: 2/2.5 | E72: 31 | F72: 1425 | G72: =COUNTIFS('Data Table'!$J$2:$J$118,$B72,'Data Table'!$P$2:$P$118, ">0") -> 16 | H72: =G72/E72 -> 0.51612903 | I72: =COUNTIFS('Data Table'!$J$2:$J$118,$B72,'Data Table'!$O$2:$O$118,'Data Table'!$Y$5) -> 16 | J72: =I72/E72 -> 0.51612903 | K72: =E72-G72 -> 15 | L72: 2450 | M72: =L72/F72 -> 1.7192982 | N72: 2240 | O72: =N72/F72 -> 1.5719298 | R72: Update this table from Month end Roscoe report
B73: Sparrow | C73: TH-E | D73: 2/2.5 | E73: 18 | F73: 1635 | G73: =COUNTIFS('Data Table'!$J$2:$J$118,$B73,'Data Table'!$P$2:$P$118, ">0") -> 7 | H73: =G73/E73 -> 0.38888889 | I73: =COUNTIFS('Data Table'!$J$2:$J$118,$B73,'Data Table'!$O$2:$O$118,'Data Table'!$Y$5) -> 7 | J73: =I73/E73 -> 0.38888889 | K73: =E73-G73 -> 11 | L73: 2650 | M73: =L73/F73 -> 1.6207951 | N73: 2405 | O73: =N73/F73 -> 1.470948
B74: Mallard | C74: TH-B | D74: 3/2.5 | E74: 25 | F74: 1685 | G74: =COUNTIFS('Data Table'!$J$2:$J$118,$B74,'Data Table'!$P$2:$P$118, ">0") -> 21 | H74: =G74/E74 -> 0.84 | I74: =COUNTIFS('Data Table'!$J$2:$J$118,$B74,'Data Table'!$O$2:$O$118,'Data Table'!$Y$5) -> 20 | J74: =I74/E74 -> 0.8 | K74: =E74-G74 -> 4 | L74: 2733 | M74: =L74/F74 -> 1.6219585 | N74: 2472 | O74: =N74/F74 -> 1.4670623
B75: Raven | C75: TH-F | D75: 3/2.5 | E75: 21 | F75: 1854 | G75: =COUNTIFS('Data Table'!$J$2:$J$118,$B75,'Data Table'!$P$2:$P$118, ">0") -> 8 | H75: =G75/E75 -> 0.38095238 | I75: =COUNTIFS('Data Table'!$J$2:$J$118,$B75,'Data Table'!$O$2:$O$118,'Data Table'!$Y$5) -> 7 | J75: =I75/E75 -> 0.33333333 | K75: =E75-G75 -> 13 | L75: 2928 | M75: =L75/F75 -> 1.579288 | N75: 2636 | O75: =N75/F75 -> 1.4217907
B76: Falcon | C76: TH-C | D76: 3/2.5 | E76: 16 | F76: 1909 | G76: =COUNTIFS('Data Table'!$J$2:$J$118,$B76,'Data Table'!$P$2:$P$118, ">0") -> 3 | H76: =G76/E76 -> 0.1875 | I76: =COUNTIFS('Data Table'!$J$2:$J$118,$B76,'Data Table'!$O$2:$O$118,'Data Table'!$Y$5) -> 3 | J76: =I76/E76 -> 0.1875 | K76: =E76-G76 -> 13 | L76: 3150 | M76: =L76/F76 -> 1.6500786 | N76: 2839 | O76: =N76/F76 -> 1.4871661
B77: Phoenix | C77: TH-D | D77: 4/2.5 | E77: 6 | F77: 2431 | G77: =COUNTIFS('Data Table'!$J$2:$J$118,$B77,'Data Table'!$P$2:$P$118, ">0") -> 2 | H77: =G77/E77 -> 0.33333333 | I77: =COUNTIFS('Data Table'!$J$2:$J$118,$B77,'Data Table'!$O$2:$O$118,'Data Table'!$Y$5) -> 2 | J77: =I77/E77 -> 0.33333333 | K77: =E77-G77 -> 4 | L77: 3600 | M77: =L77/F77 -> 1.4808721 | N77: 3270 | O77: =N77/F77 -> 1.3451255
B78: TOTAL / AVERAGE | E78: =SUM(E72:E77) -> 117 | F78: =SUMPRODUCT(F72:F77,E72:E77)/E78 -> 1707.641 | G78: =SUM(G72:G77) -> 57 | H78: =G78/E78 -> 0.48717949 | I78: =SUM(I72:I77) -> 55 | J78: =I78/E78 -> 0.47008547 | K78: =E78-G78 -> 60 | L78: =SUMPRODUCT(L72:L77,E72:E77)/E78 -> 2781.735 | M78: =L78/F78 -> 1.6289929 | N78: =SUMPRODUCT(N72:N77,G72:G77)/G78 -> 2468.9825 | O78: =N78/F78 -> 1.445844
B79: RENT REVIEW | Q79: =K79/E79 -> #DIV/0!
D80: 46023 | E80: 46054 | F80: 46082 | G80: 46113 | H80: 46143 | I80: 46174 | J80: 46204 | K80: 46235 | L80: 46266 | M80: 46296 | N80: 46327 | O80: 46357 | P80: 46357 | Q80: =K80/E80 -> 1.0039302
B81: Proforma | Q81: =K81/E81 -> #DIV/0!
B82: Budget | Q82: =K82/E82 -> #DIV/0!
B83: Market | Q83: =K83/E83 -> #DIV/0!
B84: Effective (Actual) | Q84: =K84/E84 -> #DIV/0!
B86: TRAFFIC
B87: Top Lead Sources
D88: 46023 | E88: 46054 | F88: 46082 | G88: 46113 | H88: 46143 | I88: 46174 | J88: 46204 | K88: 46235 | L88: 46266 | M88: 46296 | N88: 46327 | O88: 46357
B89: Property Website | D89: 43 | E89: 26 | F89: 36
B90: Locator/Realtor | D90: 6 | E90: 4 | F90: 0
B91: Drive By | D91: 13 | E91: 0 | F91: 17
B92: Google Business | D92: 50 | E92: 27 | F92: 29
B93: Zillow | D93: 8 | E93: 6 | F93: 10
B94: Google Paid Search | D94: 77 | E94: 89 | F94: 62
B95: Comments:
B96: ▪ Google Paid Search generated the highest volume of leads (62), followed by the Property Website (36) and Google Business Profile (29), making these the primary drivers of traffic. ▪ The Property Website was the top lease-driving source, highlighting its effectiveness in converting traffic into signed leases. ▪ Resident/Referral traffic, while low in volume, contributed to lease activity, demonstrating strong conversion from a smaller pool of leads. ▪ Zillow and Drive-by met lead-to-prospect benchmarks and showed strong progression to tours (with Zillow nearing the prospect-to-tour benchmark), but did not result in applications or leases, indicating a drop-off in the later stages of the funnel.
B100: CURRENT LEASING INCENTIVES
B101: Current Leasing Incentives, on a 13+ month lease: | H101: Renewals
B102: 4 Weeks Free – Canary (Must move in by 04/30), plus $250. Mkt Rent incr to $2550 | H102: March: 0 Expirations April: 1 Lease Expiration - 1 Renewal Pending Decision May: 2 Lease Expirations - 1 Renewal, 1 On-site Transfer June: 2 Lease Expirations - 2 Pending Decision
B103: 6 Weeks Free – Sparrow (Must move in by 04/30), plus $250. Mkt rent decr to $2600
B104: 2 Weeks Free – Mallard (Must move in by 04/30), plus $250. Mkt Rent incr. to $2850
B105: 2 months Free with 15+ month lease – Raven, Falcon (Must move in by 04/30), plus $500*
B106: 6 weeks Free - Phoenix (Must move in by 04/30), plus $250
B107: *Market rent reduced on Raven from $2950 to $2900 and reduce Falcon to $3100 from $3150.
B109: Additional Leasing Incentives:
B110: *Ember approved a $500 quarterly bonus to Leasing Team if Qtrly budget metrics are met*
B111: *Stopped automatically waiving the App Fee($85) and Admin Fee ($200) unless necessary. * We do offer the L&L App/Admin Fee of $99 if leased in 24 hours.
B112: *5% Preferred Employer discount for 1st responders, medical and educational personnel discontinued in April
B116: In Q4, most leases were driven by Google channels, include GBP, Google Search and the property website, reinforcing the importance of maintaining a strong presence across Google's channels. We continue to see this trend continue into 2026 with the website being the top lead generator. When looking into the website sources/mediums, Google organic search, paid search and direct traffic were the strongest.

Sheet II. Operational Template
B1: Operational Performance Report -March 2026
B7: 2026 BUDGET
C8: 46023 | D8: 46054 | E8: 46082 | F8: 46113 | G8: 46143 | H8: 46174 | I8: 46204 | J8: 46235 | K8: 46266 | L8: 46296 | M8: 46327 | N8: 46357 | O8: Total
C9: Budget | D9: Budget | E9: Budget | F9: Budget | G9: Budget | H9: Budget | I9: Budget | J9: Budget | K9: Budget | L9: Budget | M9: Budget | N9: Budget | O9: Budget
B11: NET RENTAL INCOME | C11: 89547 | D11: 109020 | E11: 122894 | F11: 138055 | G11: 154866 | H11: 181029 | I11: 203852 | J11: 220987 | K11: 233397 | L11: 256543 | M11: 274671 | N11: 283349 | O11: 2268210 | Q11: 2268210
B12: UTILITY INCOME | C12: 2535 | D12: 3052 | E12: 3446 | F12: 3949 | G12: 4662 | H12: 5465 | I12: 6129 | J12: 6530 | K12: 6924 | L12: 7305 | M12: 7752 | N12: 7920 | O12: =SUM(C12:N12) -> 65669 | Q12: 70922
B13: OTHER INCOME | C13: 7497 | D13: 8277 | E13: 9493 | F13: 10453 | G13: 12978 | H13: 13483 | I13: 14699 | J13: 15304 | K13: 14179 | L13: 13852 | M13: 15043 | N13: 15109 | O13: =SUM(C13:N13) -> 150367 | Q13: 150367
B14: TOTAL INCOME | C14: =SUM(C11:C13) -> 99579 | D14: =SUM(D11:D13) -> 120349 | E14: =SUM(E11:E13) -> 135833 | F14: =SUM(F11:F13) -> 152457 | G14: =SUM(G11:G13) -> 172506 | H14: =SUM(H11:H13) -> 199977 | I14: =SUM(I11:I13) -> 224680 | J14: =SUM(J11:J13) -> 242821 | ... O14: =SUM(O11:O13) -> 2484246
B15: OPERATING EXPENSES | C15: -59578 | D15: -57242 | E15: -60885 | F15: -65666 | G15: -57912 | H15: -71094 | I15: -72040 | J15: -59844 | K15: -59452 | L15: -60779 | M15: -48389 | N15: -51827 | O15: =SUM(C15:N15) -> -724708 | Q15: -721994
B16: FIXED EXPENSES | C16: -7500 | D16: -7500 | E16: -7500 | F16: -7500 | G16: -7500 | H16: -7500 | I16: -83930 | J16: -83930 | K16: -83930 | L16: -83930 | M16: -83930 | N16: -83930 | O16: =SUM(C16:N16) -> -548580 | Q16: -1007160
B17: NOI | C17: =C14+C15+C16 -> 32501 | D17: =D14+D15+D16 -> 55607 | E17: =E14+E15+E16 -> 67448 | F17: =F14+F15+F16 -> 79291 | G17: =G14+G15+G16 -> 107094 | H17: =H14+H15+H16 -> 121383 | I17: =I14+I15+I16 -> 68710 | J17: =J14+J15+J16 -> 99047 | ... O17: =O14+O15+O16 -> 1210958 | Q17: 760345
B19: CAPITAL IMPVMTS | C19: 0 | D19: 0 | E19: -1200 | F19: 0 | G19: 0 | H19: -7700 | I19: 0 | J19: 0 | K19: -1200 | L19: 0 | M19: 0 | N19: -1200 | O19: =SUM(C19:N19) -> -11300
B21: NOI / CASH FLOW | C21: =C17+C19 -> 32501 | D21: =D17+D19 -> 55607 | E21: =E17+E19 -> 66248 | F21: =F17+F19 -> 79291 | G21: =G17+G19 -> 107094 | H21: =H17+H19 -> 113683 | I21: =I17+I19 -> 68710 | J21: =J17+J19 -> 99047 | ... O21: =O17+O19 -> 1199658
B23: 2026 FORECAST
C24: 46023 | D24: 46054 | E24: 46082 | F24: 46113 | G24: 46143 | H24: 46174 | I24: 46204 | J24: 46235 | K24: 46266 | L24: 46296 | M24: 46327 | N24: 46357 | O24: Total
C25: Actual | D25: Actual | E25: Actual | F25: Budget | G25: Budget | H25: Budget | I25: Budget | J25: Budget | K25: Budget | L25: Budget | M25: Budget | N25: Budget | O25: Budget
B27: NET RENTAL INCOME | C27: 80971.03 | D27: 72170.14 | E27: 112999.88 | F27: 138055 | G27: 154866 | H27: 181029 | I27: 203852 | J27: 220987 | K27: 233397 | L27: 256543 | M27: 274671 | N27: 283349 | O27: =SUM(C27:N27) -> 2212890
B28: UTILITY INCOME | C28: 2705.74 | D28: 2806.38 | E28: 3592.85 | F28: 3949 | G28: 4662 | H28: 5465 | I28: 6129 | J28: 6530 | K28: 6924 | L28: 7305 | M28: 7752 | N28: 7920 | O28: =SUM(C28:N28) -> 65740.97
B29: OTHER INCOME | C29: 9037.36 | D29: 6086.37 | E29: 8200.39 | F29: 10453 | G29: 12978 | H29: 13483 | I29: 14699 | J29: 15304 | K29: 14179 | L29: 13852 | M29: 15043 | N29: 15109 | O29: =SUM(C29:N29) -> 148424.12
B30: TOTAL INCOME | C30: =SUM(C27:C29) -> 92714.13 | D30: =SUM(D27:D29) -> 81062.89 | E30: =SUM(E27:E29) -> 124793.12 | F30: =SUM(F27:F29) -> 152457 | G30: =SUM(G27:G29) -> 172506 | H30: =SUM(H27:H29) -> 199977 | I30: =SUM(I27:I29) -> 224680 | J30: =SUM(J27:J29) -> 242821 | ... N30: =SUM(N27:N29) -> 306378 | O30: =SUM(C30:N30) -> 2427055.1
B31: OPERATING EXPENSES | C31: -60895.72 | D31: =-73990.88+7500 -> -66490.88 | E31: =-55480.17+7500 -> -47980.17 | F31: -65666 | G31: -57912 | H31: -71094 | I31: -72040 | J31: -59844 | K31: -59452 | L31: -60779 | M31: -48389 | N31: -51827 | O31: =SUM(C31:N31) -> -722369.77
B32: FIXED EXPENSES | C32: =-7500 -> -7500 | D32: -7500 | E32: -7500 | F32: -7500 | G32: -7500 | H32: -7500 | I32: -83930 | J32: -83930 | K32: -83930 | L32: -83930 | M32: -83930 | N32: -83930 | O32: =SUM(C32:N32) -> -548580
B33: NOI | C33: =C30+C31+C32 -> 24318.41 | D33: =D30+D31+D32 -> 7072.01 | E33: =E30+E31+E32 -> 69312.95 | F33: =F30+F31+F32 -> 79291 | G33: =G30+G31+G32 -> 107094 | H33: =H30+H31+H32 -> 121383 | I33: =I30+I31+I32 -> 68710 | J33: =J30+J31+J32 -> 99047 | ... O33: =O30+O31+O32 -> 1156105.4
B35: CAPITAL IMPVMTS/PY EXP | C35: -2245 | D35: =-477.74-1894.38 -> -2372.12 | E35: =-3721.38-8660-2000 -> -14381.38 | F35: 0 | G35: 0 | H35: -7700 | I35: 0 | J35: 0 | K35: -1200 | L35: 0 | M35: 0 | N35: -1200 | O35: =SUM(C35:N35) -> -29098.5
B37: FORECASTED NOI / CASH FLOW | C37: =C33+C35 -> 22073.41 | D37: =D33+D35 -> 4699.89 | E37: =E33+E35 -> 54931.57 | F37: =F33+F35 -> 79291 | G37: =G33+G35 -> 107094 | H37: =H33+H35 -> 113683 | I37: =I33+I35 -> 68710 | J37: =J33+J35 -> 99047 | ... O37: =O33+O35 -> 1127006.9
B38: Variance Forcast to Budget | C38: =C37-C21 -> -10427.59 | D38: =D37-D21 -> -50907.11 | E38: =E37-E21 -> -11316.43 | F38: =F37-F21 -> 0 | G38: =G37-G21 -> 0 | H38: =H37-H21 -> 0 | I38: =I37-I21 -> 0 | J38: =J37-J21 -> 0 | ... O38: =O37-O21 -> -72651.13
B39: D2/ LENDER PROFORMA
B40: NET RENTAL INCOME | C40: 96017.212 | D40: 108835.5 | E40: 123078.05 | F40: 137320.6 | G40: 153476.7 | H40: 176886.1 | I40: 204678.29 | J40: 229680.65 | K40: 250461.59 | L40: 266999.11 | M40: 280746.79 | N40: 293070.22 | O40: =SUM(C40:N40) -> 2321250.8
B41: TOTAL OTHER INCOME, INCL. UTILITY | C41: 7034.2746 | D41: 7871.6882 | E41: 8709.1019 | F41: 9713.9982 | G41: 11418.152 | H41: 12962.585 | I41: 14346.005 | J41: 15397.91 | K41: 16285.351 | L41: 17007.034 | M41: 17732.167 | N41: 18289.817 | O41: =SUM(C41:N41) -> 156768.08 | P41: =O41+O40 -> 2478018.9
B42: OPERATING EXPENSES | C42: -60694 | D42: -62104 | E42: -60692 | F42: -64973 | G42: -63188 | H42: -70856 | I42: -71302 | J42: -65703 | K42: -59750 | L42: -60077 | M42: -53765 | N42: -51625 | O42: =SUM(C42:N42) -> -744729
B43: FIXED EXPENSES | C43: -7500 | D43: -7500 | E43: -7500 | F43: -7500 | G43: -7500 | H43: -7500 | I43: -83930 | J43: -83930 | K43: -83930 | L43: -83930 | M43: -83930 | N43: -86416 | O43: =SUM(C43:N43) -> -551066
B44: TOTAL PROJECTED CASH FLOW - D2 | C44: =SUM(C40:C43) -> 34857.486 | D44: =SUM(D40:D43) -> 47103.193 | E44: =SUM(E40:E43) -> 63595.155 | F44: =SUM(F40:F43) -> 74561.599 | G44: =SUM(G40:G43) -> 94206.852 | H44: =SUM(H40:H43) -> 111492.69 | I44: =SUM(I40:I43) -> 63792.297 | J44: =SUM(J40:J43) -> 95445.561 | ... N44: =SUM(N40:N43) -> 173319.04 | O44: =SUM(C44:N44) -> 1182223.9
B45: Variance Budget to Proforma | C45: =C37-C44 -> -12784.076 | D45: =D37-D44 -> -42403.303 | E45: =E37-E44 -> -8663.5847 | F45: =F37-F44 -> 4729.4008 | G45: =G37-G44 -> 12887.148 | H45: =H37-H44 -> 2190.3126 | I45: =I37-I44 -> 4917.7029 | J45: =J37-J44 -> 3601.4387 | ... O45: =O37-O44 -> -55217.036
B47: BUDGET TO ACTUAL & CASH FLOW
C48: 46082 | D48: 46082 | E48: Act v Bud
C49: Actual | D49: Budget | E49: Variance | F49: Comments
B50: NET RENTAL INCOME | C50: 112999.88 | D50: =E11 -> 122894 | E50: =C50-D50 -> -9894.12 | F50: Actual monthly weighted average occupancy was lower than budget, due to half of the move-ins occuring on the last 3 days of the month
B51: UTILITY INCOME | C51: 3592.85 | D51: =E12 -> 3446 | E51: =C51-D51 -> 146.85 | R51: $85 app fee per applicant | U51: Concessions hit the books 30 days following a resident's move-in.
B52: OTHER INCOME | C52: 8200.39 | D52: =E13 -> 9493 | E52: =C52-D52 -> -1292.61 | F52: Came in lower on application & lease admin fees, but double on pet fees. | R52: $200 admin fee | U52: E.G. if a resident moves in on Jan 30, they pay 2 days of rent in Jan, all of Feb and then March gets hit with the full concession
B53: OPERATING EXPENSES | C53: -47980.17 | D53: =E15 -> -60885 | E53: =C53-D53 -> 12904.83 | F53: Under budget in payroll due to no svc mgr; mar | R53: $99 App / Admin Fee for L&L
B54: FIXED EXPENSES | C54: -7500 | D54: -7500 | E54: =C54-D54 -> 0
B55: NOI | C55: =SUM(C50:C54) -> 69312.95 | D55: =SUM(D50:D54) -> 67448 | E55: =SUM(E50:E54) -> 1864.95 | F55: Operationally, the property was in budget.
B56: CAPITAL IMPVMTS | C56: =E35 -> -14381.38 | D56: =E19 -> -1200 | E56: =C56-D56 -> -13181.38 | F56: The property was hit with $8,660 to cover the meditation park, which should have been a project cost, $2K for pool gate repairs, & $3K PY expenses.
B57: NET CASH FLOW | C57: =C56+C55 -> 54931.57 | D57: =D56+D55 -> 66248 | E57: =C57-D57 -> -11316.43 | F57: Going forward, any non-operational invoices will be sent to Ownership for review & pmt.
B59: RENTS
F60: D2 Proforma Rents | I60: Current Market Rents | L60: Occupied Rent | O60: Mkt - Eff Rents
B61: Floorplan | C61: SF | D61: # Units | E61: # Leased | F61: Rents | G61: Rents PSF | H61: Occupied Rents | I61: Market Rents | J61: Market Rents PSF | K61: Occupied Market Rent | L61: Current Occupied Rents | M61: Current Occupied Rents PSF | N61: Occupied Effective Rents | O61: Loss/Gain to Lease* | Q61: <--Taken from previous month's financial statement | Y61: Annual Mkt
B62: Canary (THA) | C62: 1425 | D62: 31 | E62: ='I. LeaseUp Template'!G72 -> 16 | F62: 2468 | G62: =F62/C62 -> 1.7319298 | H62: =F62*E62 -> 39488 | I62: 2450 | J62: =I62/$C62 -> 1.7192982 | K62: =I62*E62 -> 39200 | L62: 2450 | M62: =L62/$C62 -> 1.7192982 | N62: =L62*E62 -> 39200 | O62: =N62-K62 -> 0 | V62: =2450*13 -> 31850 | W62: =V62/365 -> 87.260274 | Y62: =2450*12 -> 29400 | Z62: =Y62/52 -> 565.38462
B63: Sparrow (THE) | C63: 1635 | D63: 18 | E63: ='I. LeaseUp Template'!G73 -> 7 | F63: 2678 | G63: =F63/C63 -> 1.6379205 | H63: =F63*E63 -> 18746 | I63: 2650 | J63: =I63/$C63 -> 1.6207951 | K63: =I63*E63 -> 18550 | L63: 2650 | M63: =L63/$C63 -> 1.6207951 | N63: =L63*E63 -> 18550 | O63: =N63-K63 -> 0 | W63: =6*W62*7 -> 3664.9315 | Z63: =Z62*6 -> 3392.3077 | AA63: concession value
B64: Mallard (THB) | C64: 1685 | D64: 25 | E64: ='I. LeaseUp Template'!G74 -> 21 | F64: 2788 | G64: =F64/C64 -> 1.6545994 | H64: =F64*E64 -> 58548 | I64: 2733 | J64: =I64/$C64 -> 1.6219585 | K64: =I64*E64 -> 57393 | L64: 2748.48 | M64: =L64/$C64 -> 1.6311454 | N64: =L64*E64 -> 57718.08 | O64: -400 | P64: <--loss leaders | V64: =I62-W64 -> 2168.0822 | W64: =W63/13 -> 281.91781 | Z64: =2450*13 -> 31850 | AA64: based on 13-month lease
B65: Raven (THF) | C65: 1852 | D65: 21 | E65: ='I. LeaseUp Template'!G75 -> 8 | F65: 2971 | G65: =F65/C65 -> 1.6042117 | H65: =F65*E65 -> 23768 | I65: =C125 -> 2928.4286 | J65: =I65/$C65 -> 1.5812249 | K65: =I65*E65 -> 23427.429 | L65: 2874.5 | M65: =L65/$C65 -> 1.5521058 | N65: =L65*E65 -> 22996 | O65: 0 | P65: <--loss leaders | V65: =V64*12 -> 26016.986 | W65: =W64*12 -> 3383.0137 | Z65: =Z64-Z63 -> 28457.692
B66: Falcon (THC) | C66: 1909 | D66: 16 | E66: ='I. LeaseUp Template'!G76 -> 3 | F66: 3150 | G66: =F66/C66 -> 1.6500786 | H66: =F66*E66 -> 9450 | I66: 3150 | J66: =I66/$C66 -> 1.6500786 | K66: =I66*E66 -> 9450 | L66: 3150 | M66: =L66/$C66 -> 1.6500786 | N66: =L66*E66 -> 9450 | O66: =N66-K66 -> 0 | Z66: =Z65/13 -> 2189.0533 | AA66: Net Effective Rent | AD66: =(2450-Z66)*12 -> 3131.3609
B67: Phoenix (THD) | C67: 2431 | D67: 6 | E67: ='I. LeaseUp Template'!G77 -> 2 | F67: 3600 | G67: =F67/C67 -> 1.4808721 | H67: =F67*E67 -> 7200 | I67: 3600 | J67: =I67/$C67 -> 1.4808721 | K67: =I67*E67 -> 7200 | L67: 3600 | M67: =L67/$C67 -> 1.4808721 | N67: =L67*E67 -> 7200 | O67: =N67-K67 -> 0
B68: TOTAL | C68: =((C62*D62)+(C63*D63)+(C64*D64)+(C65*D65)+(C66*D66)+(C67*D67))/D68 -> 1707.2821 | D68: =SUM(D62:D67) -> 117 | E68: =SUM(E62:E67) -> 57 | F68: =SUMPRODUCT(F62:F67,$D$62:$D$67)/$D$68 -> 2810.2821 | G68: =SUMPRODUCT(G62:G67,$D$62:$D$67)/$D$68 -> 1.6539514 | H68: =SUM(H62:H67) -> 157200 | I68: =SUMPRODUCT(I62:I67,$D$62:$D$67)/$D$68 -> 2781.812 | J68: =SUMPRODUCT(J62:J67,$D$62:$D$67)/$D$68 -> 1.6368695 | K68: =SUM(K62:K67) -> 155220.43 | L68: =SUMPRODUCT(L62:L67,$D$62:$D$67)/$D$68 -> 2775.4402 | M68: =SUMPRODUCT(M62:M67,$D$62:$D$67)/$D$68 -> 1.633606 | N68: =SUM(N62:N67) -> 155114.08 | O68: =SUM(O62:O67) -> -400 | Y68: Mkt -8% discount
B69: *Loss Leaders are not factored as a loss to lease since an adjustment is made to market rents. | Y69: =2450*1 -> 2450 | Z69: =Y69*12/52 -> 565.38462 | AA69: 6-week concession
V70: =2450*0.9 -> 2205 | Z70: =Z69*6 -> 3392.3077
B71: Comments | V71: 100 | W71: amenity fee disct | Z71: =Y69*13 -> 31850
B72: Mallard market rent is lower because of one loss leader. Mkt assumes $2,750 rent taken over all units; occ avg rent assumes actual rent which includes two residents at $2950. | V72: =V70-V71 -> 2105 | Z72: =Z71-Z70 -> 28457.692
B73: The $400 gain to lease reflects that premium for the two residents who rented at $2950, before downward adj. | V73: =V72/2450 -> 0.85918367 | Z73: =Z72/13 -> 2189.0533 | AA73: net eff rent with 6-weeks + 8%
Z75: =Z73/2450-1 -> -0.10650888
Z77: =2450-Z73 -> 260.94675
B79: DISCUSSION ITEMS
B80: Item | C80: Description | L80: Status
B81: MUD Reimbursement | C81: Bond app was submitted last Thursday. It was submitted expedited so TCEQ has 60 days to review, but sometimes it can take them a little longer depending on how many applications they have and the number of reviewers. Then typically another 60-90 days to fund. | L81: Bond App submitted on 04/02/26. Anticipate approval June / July 2026.
B84: Capital Builder's C/O | C84: Pelican met with attorney to push Capital Builders to an agreement on final change order amount. Letter being drafted to CB. | L84: Waiting to hear back from Pelican on updates as they come.
B85: Funding Request
B87: Project Costs - Repairs | C87: There have been several project / development costs that are funneling through to be paid (eg. Utility, | L87: Montioring costs but unfortunately, OPS is taking | Q87: =229852.75-60000 -> 169852.75 | R87: =229852.75 -> 229852.75
C88: repairs, meditation park, etc) Those invoices were negatively impacting the operations budget, therefore, | L88: a hit on some construction / unforeseen costs
C89: it was decided that ownership would retain $8K of the $60K from D2 to help absorb those costs. | L89: that weren't covered by project budget. | Q89: =Q87/2 -> 84926.375 | R89: =R87/2 -> 114926.38
R90: =R89-30000 -> 84926.375 | S90: Balance after $60K split is reimbursed.
B91: Maintenance Supervisor | C91: Ownership interviewed two candidates for maint. Supervisor. Offer extended | L91: New Supervisor is Tony, started 03/31.
B92: Replacement
K101: `
C102: THF | H102: THB
C103: Mkt rent | D103: Occ rent | H103: 2750 | I103: =H103 -> 2750
B104: 1 | C104: 2950 | D104: =C104 -> 2950 | H104: 2750 | I104: =H104 -> 2750
B105: 2 | C105: 2950 | D105: =C105 -> 2950 | H105: 2750 | I105: =H105 -> 2750
B106: =B105+1 -> 3 | C106: 2950 | D106: 2950 | H106: 2750 | I106: =H106 -> 2750
B107: =B106+1 -> 4 | C107: 2950 | D107: 2950 | H107: 2750 | I107: =H107 -> 2750
B108: =B107+1 -> 5 | C108: 2950 | D108: 2950 | H108: 2750 | I108: =H108 -> 2750
B109: =B108+1 -> 6 | C109: 2950 | H109: 2750 | I109: =H109 -> 2750
B110: =B109+1 -> 7 | C110: 2950 | H110: 2750 | I110: =H110 -> 2750
B111: =B110+1 -> 8 | C111: 2950 | H111: 2750 | I111: =H111 -> 2750
B112: =B111+1 -> 9 | C112: 2950 | H112: 2750 | I112: =H112 -> 2750
B113: =B112+1 -> 10 | C113: 2950 | H113: 2750 | I113: =H113 -> 2750
B114: =B113+1 -> 11 | C114: 2950 | H114: 2750 | I114: =H114 -> 2750
B115: =B114+1 -> 12 | C115: 2950 | H115: 2750 | I115: =H115 -> 2750
B116: =B115+1 -> 13 | C116: 2950 | H116: 2750 | I116: =H116 -> 2750
B117: =B116+1 -> 14 | C117: 2950 | H117: 2750 | I117: =H117 -> 2750
B118: =B117+1 -> 15 | C118: 2950 | H118: 2750 | I118: =H118 -> 2750
B119: =B118+1 -> 16 | C119: 2950 | H119: 2750 | I119: =H119 -> 2750
B120: =B119+1 -> 17 | C120: 2950 | H120: 2750 | I120: =H120 -> 2750
B121: =B120+1 -> 18 | C121: 2950 | H121: 2750
B122: =B121+1 -> 19 | C122: 2950 | H122: 2750
B123: =B122+1 -> 20 | C123: 2950 | H123: 2750
B124: loss leader | C124: 2497 | D124: =C124 -> 2497 | H124: 2750
B125: Avg | C125: =AVERAGE(C104:C124) -> 2928.4286 | D125: =SUM(D104:D124)/6 -> 2874.5 | E125: 6 leases | H125: 2750
D126: =D125-C125 -> -53.928571 | H126: 2750
G127: #22027F | H127: 2327 | I127: =H127 -> 2327
G128: AVG | H128: =AVERAGE(H103:H127) -> 2733.08 | I128: =SUM(I103:I127)/19 -> 2727.7368 | J128: assumes 19 leases
...

Sheet Data Table
A1: Block | B1: Lot | C1: House # | D1: Rent Roll | E1: Match | F1: Address | G1: Tenant | H1: Inventory | I1: House Type | J1: Floorplan | K1: Bedrooms | L1: SQFT | M1: Phase | N1: Turnover Date | O1: Status | P1: Lease Executed Date | Q1: Tenant Move-In Date | R1: Tenant Move Out Date | S1: Average Rent | T1: $/SQFT | W1: No Match | X1: =COUNTIF(E2:E118,W1) -> 61
A2: 1 | B2: 38 | C2: 47 | D2: =IF(ISNUMBER(SEARCH("Bobby Meadow",F2)),LEFT(F2,FIND(" ",F2)-1)&"M",IF(ISNUMBER(SEARCH("Bruce Rushing",F2)),LEFT(F2,FIND(" ",F2)-1)&"R",LEFT(F2,FIND(" ",F2)-1)&MID(F2,FIND(" ",F2)+1,1))) -> 21901R | E2: =IFERROR(IF(_xlfn.XMATCH(D2,'Rent Roll - RPM'!$B$3:$B$60,0,1)>0,"Match","No Match"),"No Match") -> No Match | F2: 21901 Bruce Rushing Lane | G2: =_xlfn.XLOOKUP(D2,'Rent Roll - RPM'!$B$3:$B$60,'Rent Roll - RPM'!$D$3:$D$60,0) -> 0 | H2: 1 | I2: F3 | J2: Raven | K2: 3 Bed | L2: 1852 | M2: 3 | N2: Complete | O2: Turned | P2: =_xlfn.XLOOKUP(D2,'Rent Roll - RPM'!$B$3:$B$60,'Rent Roll - RPM'!$Q$3:$Q$60,"") | Q2: =_xlfn.XLOOKUP($D2,'Rent Roll - RPM'!$B$3:$B$60,'Rent Roll - RPM'!$R$3:$R$60,"") | R2: =_xlfn.XLOOKUP(D2,'Rent Roll - RPM'!$B$3:$B$60,'Rent Roll - RPM'!$S$3:$S$60,"") | S2: 2950 | T2: =S2/L2 -> 1.5928726 | W2: Match | X2: =COUNTIF(E2:E119,W2) -> 56 | Y2: Leased
A3: 1 | B3: 39 | C3: 46 | D3: =IF(ISNUMBER(SEARCH("Bobby Meadow",F3)),LEFT(F3,FIND(" ",F3)-1)&"M",IF(ISNUMBER(SEARCH("Bruce Rushing",F3)),LEFT(F3,FIND(" ",F3)-1)&"R",LEFT(F3,FIND(" ",F3)-1)&MID(F3,FIND(" ",F3)+1,1))) -> 21905R | E3: =IFERROR(IF(_xlfn.XMATCH(D3,'Rent Roll - RPM'!$B$3:$B$60,0,1)>0,"Match","No Match"),"No Match") -> No Match | F3: 21905 Bruce Rushing Lane | G3: =_xlfn.XLOOKUP(D3,'Rent Roll - RPM'!$B$3:$B$60,'Rent Roll - RPM'!$D$3:$D$60,0) -> 0 | H3: 1 | I3: F2 | J3: Raven | K3: 3 Bed | L3: 1852 | M3: 3 | N3: Complete | O3: Turned | P3: =_xlfn.XLOOKUP(D3,'Rent Roll - RPM'!$B$3:$B$60,'Rent Roll - RPM'!$Q$3:$Q$60,"") | Q3: =_xlfn.XLOOKUP($D3,'Rent Roll - RPM'!$B$3:$B$60,'Rent Roll - RPM'!$R$3:$R$60,"") | R3: =_xlfn.XLOOKUP(D3,'Rent Roll - RPM'!$B$3:$B$60,'Rent Roll - RPM'!$S$3:$S$60,"") | S3: 2950 | T3: =S3/L3 -> 1.5928726 | Y3: Under Construction
A4: 1 | B4: 25 | C4: 80 | D4: =IF(ISNUMBER(SEARCH("Bobby Meadow",F4)),LEFT(F4,FIND(" ",F4)-1)&"M",LEFT(F4,FIND(" ",F4)-1)&MID(F4,FIND(" ",F4)+1,1)) -> 21907M | E4: =IFERROR(IF(_xlfn.XMATCH(D4,'Rent Roll - RPM'!$B$3:$B$60,0,1)>0,"Match","No Match"),"No Match") -> No Match | F4: 21907 Bobby Meadow Lane | G4: =_xlfn.XLOOKUP(D4,'Rent Roll - RPM'!$B$3:$B$60,'Rent Roll - RPM'!$D$3:$D$60,0) -> 0 | H4: 1 | I4: D1 | J4: Phoenix | K4: 4 Bed | L4: 2431 | M4: 5 | N4: 45991 | O4: Turned | P4: =_xlfn.XLOOKUP(D4,'Rent Roll - RPM'!$B$3:$B$60,'Rent Roll - RPM'!$Q$3:$Q$60,"") | Q4: =_xlfn.XLOOKUP($D4,'Rent Roll - RPM'!$B$3:$B$60,'Rent Roll - RPM'!$R$3:$R$60,"") | R4: =_xlfn.XLOOKUP(D4,'Rent Roll - RPM'!$B$3:$B$60,'Rent Roll - RPM'!$S$3:$S$60,"") | S4: 3600 | T4: =S4/L4 -> 1.4808721 | Y4: Turned
A5: 1 | B5: 40 | C5: 45 | D5: =IF(ISNUMBER(SEARCH("Bobby Meadow",F5)),LEFT(F5,FIND(" ",F5)-1)&"M",IF(ISNUMBER(SEARCH("Bruce Rushing",F5)),LEFT(F5,FIND(" ",F5)-1)&"R",LEFT(F5,FIND(" ",F5)-1)&MID(F5,FIND(" ",F5)+1,1))) -> 21909R | E5: =IFERROR(IF(_xlfn.XMATCH(D5,'Rent Roll - RPM'!$B$3:$B$60,0,1)>0,"Match","No Match"),"No Match") -> No Match | F5: 21909 Bruce Rushing Lane | G5: =_xlfn.XLOOKUP(D5,'Rent Roll - RPM'!$B$3:$B$60,'Rent Roll - RPM'!$D$3:$D$60,0) -> 0 | H5: 1 | I5: A1 | J5: Canary | K5: 2 Bed | L5: 1425 | M5: 3 | N5: Complete | O5: Turned | P5: =_xlfn.XLOOKUP(D5,'Rent Roll - RPM'!$B$3:$B$60,'Rent Roll - RPM'!$Q$3:$Q$60,"") | Q5: =_xlfn.XLOOKUP($D5,'Rent Roll - RPM'!$B$3:$B$60,'Rent Roll - RPM'!$R$3:$R$60,"") | R5: =_xlfn.XLOOKUP(D5,'Rent Roll - RPM'!$B$3:$B$60,'Rent Roll - RPM'!$S$3:$S$60,"") | S5: 2450 | T5: =S5/L5 -> 1.7192982 | Y5: Tenant Occupied
A6: 1 | B6: 41 | C6: 44 | D6: =IF(ISNUMBER(SEARCH("Bobby Meadow",F6)),LEFT(F6,FIND(" ",F6)-1)&"M",IF(ISNUMBER(SEARCH("Bruce Rushing",F6)),LEFT(F6,FIND(" ",F6)-1)&"R",LEFT(F6,FIND(" ",F6)-1)&MID(F6,FIND(" ",F6)+1,1))) -> 21913R | E6: =IFERROR(IF(_xlfn.XMATCH(D6,'Rent Roll - RPM'!$B$3:$B$60,0,1)>0,"Match","No Match"),"No Match") -> No Match | F6: 21913 Bruce Rushing Lane | G6: =_xlfn.XLOOKUP(D6,'Rent Roll - RPM'!$B$3:$B$60,'Rent Roll - RPM'!$D$3:$D$60,0) -> 0 | H6: 1 | I6: A3 | J6: Canary | K6: 2 Bed | L6: 1425 | M6: 3 | N6: Complete | O6: Turned | P6: =_xlfn.XLOOKUP(D6,'Rent Roll - RPM'!$B$3:$B$60,'Rent Roll - RPM'!$Q$3:$Q$60,"") | Q6: =_xlfn.XLOOKUP($D6,'Rent Roll - RPM'!$B$3:$B$60,'Rent Roll - RPM'!$R$3:$R$60,"") | R6: =_xlfn.XLOOKUP(D6,'Rent Roll - RPM'!$B$3:$B$60,'Rent Roll - RPM'!$S$3:$S$60,"") | S6: 2450 | T6: =S6/L6 -> 1.7192982 | Y6: Renewal
A7: 1 | B7: 27 | C7: 78 | D7: =IF(ISNUMBER(SEARCH("Bobby Meadow",F7)),LEFT(F7,FIND(" ",F7)-1)&"M",LEFT(F7,FIND(" ",F7)-1)&MID(F7,FIND(" ",F7)+1,1)) -> 21919M | E7: =IFERROR(IF(_xlfn.XMATCH(D7,'Rent Roll - RPM'!$B$3:$B$60,0,1)>0,"Match","No Match"),"No Match") -> No Match | F7: 21919 Bobby Meadow Lane | G7: =_xlfn.XLOOKUP(D7,'Rent Roll - RPM'!$B$3:$B$60,'Rent Roll - RPM'!$D$3:$D$60,0) -> 0 | H7: 1 | I7: A2 | J7: Canary | K7: 2 Bed | L7: 1425 | M7: 5 | N7: 45991 | O7: Turned | P7: =_xlfn.XLOOKUP(D7,'Rent Roll - RPM'!$B$3:$B$60,'Rent Roll - RPM'!$Q$3:$Q$60,"") | Q7: =_xlfn.XLOOKUP($D7,'Rent Roll - RPM'!$B$3:$B$60,'Rent Roll - RPM'!$R$3:$R$60,"") | R7: =_xlfn.XLOOKUP(D7,'Rent Roll - RPM'!$B$3:$B$60,'Rent Roll - RPM'!$S$3:$S$60,"") | S7: 2450 | T7: =S7/L7 -> 1.7192982
A8: 1 | B8: 43 | C8: 42 | D8: =IF(ISNUMBER(SEARCH("Bobby Meadow",F8)),LEFT(F8,FIND(" ",F8)-1)&"M",IF(ISNUMBER(SEARCH("Bruce Rushing",F8)),LEFT(F8,FIND(" ",F8)-1)&"R",LEFT(F8,FIND(" ",F8)-1)&MID(F8,FIND(" ",F8)+1,1))) -> 21921R | E8: =IFERROR(IF(_xlfn.XMATCH(D8,'Rent Roll - RPM'!$B$3:$B$60,0,1)>0,"Match","No Match"),"No Match") -> No Match | F8: 21921 Bruce Rushing Lane | G8: =_xlfn.XLOOKUP(D8,'Rent Roll - RPM'!$B$3:$B$60,'Rent Roll - RPM'!$D$3:$D$60,0) -> 0 | H8: 1 | I8: F2 | J8: Raven | K8: 3 Bed | L8: 1852 | M8: 3 | N8: Complete | O8: Turned | P8: =_xlfn.XLOOKUP(D8,'Rent Roll - RPM'!$B$3:$B$60,'Rent Roll - RPM'!$Q$3:$Q$60,"") | Q8: =_xlfn.XLOOKUP($D8,'Rent Roll - RPM'!$B$3:$B$60,'Rent Roll - RPM'!$R$3:$R$60,"") | R8: =_xlfn.XLOOKUP(D8,'Rent Roll - RPM'!$B$3:$B$60,'Rent Roll - RPM'!$S$3:$S$60,"") | S8: 2950 | T8: =S8/L8 -> 1.5928726
A9: 1 | B9: 29 | C9: 56 | D9: =IF(ISNUMBER(SEARCH("Bobby Meadow",F9)),LEFT(F9,FIND(" ",F9)-1)&"M",LEFT(F9,FIND(" ",F9)-1)&MID(F9,FIND(" ",F9)+1,1)) -> 21927M | E9: =IFERROR(IF(_xlfn.XMATCH(D9,'Rent Roll - RPM'!$B$3:$B$60,0,1)>0,"Match","No Match"),"No Match") -> No Match | F9: 21927 Bobby Meadow Lane | G9: =_xlfn.XLOOKUP(D9,'Rent Roll - RPM'!$B$3:$B$60,'Rent Roll - RPM'!$D$3:$D$60,0) -> 0 | H9: 1 | I9: B3 | J9: Mallard | K9: 3 Bed | L9: 1685 | M9: 3 | N9: Complete | O9: Turned | P9: =_xlfn.XLOOKUP(D9,'Rent Roll - RPM'!$B$3:$B$60,'Rent Roll - RPM'!$Q$3:$Q$60,"") | Q9: =_xlfn.XLOOKUP($D9,'Rent Roll - RPM'!$B$3:$B$60,'Rent Roll - RPM'!$R$3:$R$60,"") | R9: =_xlfn.XLOOKUP(D9,'Rent Roll - RPM'!$B$3:$B$60,'Rent Roll - RPM'!$S$3:$S$60,"") | S9: 2750 | T9: =S9/L9 -> 1.6320475
A10: 1 | B10: 30 | C10: 55 | D10: =IF(ISNUMBER(SEARCH("Bobby Meadow",F10)),LEFT(F10,FIND(" ",F10)-1)&"M",LEFT(F10,FIND(" ",F10)-1)&MID(F10,FIND(" ",F10)+1,1)) -> 21931M | E10: =IFERROR(IF(_xlfn.XMATCH(D10,'Rent Roll - RPM'!$B$3:$B$60,0,1)>0,"Match","No Match"),"No Match") -> No Match | F10: 21931 Bobby Meadow Lane | G10: =_xlfn.XLOOKUP(D10,'Rent Roll - RPM'!$B$3:$B$60,'Rent Roll - RPM'!$D$3:$D$60,0) -> 0 | H10: 1 | I10: B2 | J10: Raven | K10: 3 Bed | L10: 1852 | M10: 3 | N10: Complete | O10: Turned | P10: =_xlfn.XLOOKUP(D10,'Rent Roll - RPM'!$B$3:$B$60,'Rent Roll - RPM'!$Q$3:$Q$60,"") | Q10: =_xlfn.XLOOKUP($D10,'Rent Roll - RPM'!$B$3:$B$60,'Rent Roll - RPM'!$R$3:$R$60,"") | R10: =_xlfn.XLOOKUP(D10,'Rent Roll - RPM'!$B$3:$B$60,'Rent Roll - RPM'!$S$3:$S$60,"") | S10: 2950 | T10: =S10/L10 -> 1.5928726
A11: 1 | B11: 36 | C11: 49 | D11: =IF(ISNUMBER(SEARCH("Bobby Meadow",F11)),LEFT(F11,FIND(" ",F11)-1)&"M",LEFT(F11,FIND(" ",F11)-1)&MID(F11,FIND(" ",F11)+1,1)) -> 21942M | E11: =IFERROR(IF(_xlfn.XMATCH(D11,'Rent Roll - RPM'!$B$3:$B$60,0,1)>0,"Match","No Match"),"No Match") -> No Match | F11: 21942 Bobby Meadow Lane | G11: =_xlfn.XLOOKUP(D11,'Rent Roll - RPM'!$B$3:$B$60,'Rent Roll - RPM'!$D$3:$D$60,0) -> 0 | H11: 1 | I11: A3 | J11: Canary | K11: 2 Bed | L11: 1425 | M11: 3 | N11: Complete | O11: Turned | P11: =_xlfn.XLOOKUP(D11,'Rent Roll - RPM'!$B$3:$B$60,'Rent Roll - RPM'!$Q$3:$Q$60,"") | Q11: =_xlfn.XLOOKUP($D11,'Rent Roll - RPM'!$B$3:$B$60,'Rent Roll - RPM'!$R$3:$R$60,"") | R11: =_xlfn.XLOOKUP(D11,'Rent Roll - RPM'!$B$3:$B$60,'Rent Roll - RPM'!$S$3:$S$60,"") | S11: 2450 | T11: =S11/L11 -> 1.7192982
A12: 1 | B12: 44 | C12: 31 | D12: =IF(ISNUMBER(SEARCH("Bobby Meadow",F12)),LEFT(F12,FIND(" ",F12)-1)&"M",LEFT(F12,FIND(" ",F12)-1)&MID(F12,FIND(" ",F12)+1,1)) -> 22001L | E12: =IFERROR(IF(_xlfn.XMATCH(D12,'Rent Roll - RPM'!$B$3:$B$60,0,1)>0,"Match","No Match"),"No Match") -> No Match | F12: 22001 Lesley Grove Lane | G12: =_xlfn.XLOOKUP(D12,'Rent Roll - RPM'!$B$3:$B$60,'Rent Roll - RPM'!$D$3:$D$60,0) -> 0 | H12: 1 | I12: D1 | J12: Phoenix | K12: 4 Bed | L12: 2431 | M12: 2 | N12: Complete | O12: Turned | P12: =_xlfn.XLOOKUP(D12,'Rent Roll - RPM'!$B$3:$B$60,'Rent Roll - RPM'!$Q$3:$Q$60,"") | Q12: =_xlfn.XLOOKUP($D12,'Rent Roll - RPM'!$B$3:$B$60,'Rent Roll - RPM'!$R$3:$R$60,"") | R12: =_xlfn.XLOOKUP(D12,'Rent Roll - RPM'!$B$3:$B$60,'Rent Roll - RPM'!$S$3:$S$60,"") | S12: 3600 | T12: =S12/L12 -> 1.4808721
A13: 1 | B13: 66 | C13: 2 | D13: =IF(ISNUMBER(SEARCH("Bobby Meadow",F13)),LEFT(F13,FIND(" ",F13)-1)&"M",LEFT(F13,FIND(" ",F13)-1)&MID(F13,FIND(" ",F13)+1,1)) -> 22006F | E13: =IFERROR(IF(_xlfn.XMATCH(D13,'Rent Roll - RPM'!$B$3:$B$60,0,1)>0,"Match","No Match"),"No Match") -> No Match | F13: 22006 Ferguson Meadow Lane | G13: =_xlfn.XLOOKUP(D13,'Rent Roll - RPM'!$B$3:$B$60,'Rent Roll - RPM'!$D$3:$D$60,0) -> 0 | I13: E3 | J13: Sparrow | K13: 2 Bed | L13: 1635 | M13: 1 | N13: Complete | O13: Turned | P13: =_xlfn.XLOOKUP(D13,'Rent Roll - RPM'!$B$3:$B$60,'Rent Roll - RPM'!$Q$3:$Q$60,"") | Q13: =_xlfn.XLOOKUP($D13,'Rent Roll - RPM'!$B$3:$B$60,'Rent Roll - RPM'!$R$3:$R$60,"") | R13: =_xlfn.XLOOKUP(D13,'Rent Roll - RPM'!$B$3:$B$60,'Rent Roll - RPM'!$S$3:$S$60,"") | S13: 2650 | T13: =S13/L13 -> 1.6207951
A14: 1 | B14: 46 | C14: 29 | D14: =IF(ISNUMBER(SEARCH("Bobby Meadow",F14)),LEFT(F14,FIND(" ",F14)-1)&"M",LEFT(F14,FIND(" ",F14)-1)&MID(F14,FIND(" ",F14)+1,1)) -> 22009L | E14: =IFERROR(IF(_xlfn.XMATCH(D14,'Rent Roll - RPM'!$B$3:$B$60,0,1)>0,"Match","No Match"),"No Match") -> No Match | F14: 22009 Lesley Grove Lane | G14: =_xlfn.XLOOKUP(D14,'Rent Roll - RPM'!$B$3:$B$60,'Rent Roll - RPM'!$D$3:$D$60,0) -> 0 | H14: 1 | I14: C2 | J14: Falcon | K14: 3 Bed | L14: 1909 | M14: 2 | N14: Complete | O14: Turned | P14: =_xlfn.XLOOKUP(D14,'Rent Roll - RPM'!$B$3:$B$60,'Rent Roll - RPM'!$Q$3:$Q$60,"") | Q14: =_xlfn.XLOOKUP($D14,'Rent Roll - RPM'!$B$3:$B$60,'Rent Roll - RPM'!$R$3:$R$60,"") | R14: =_xlfn.XLOOKUP(D14,'Rent Roll - RPM'!$B$3:$B$60,'Rent Roll - RPM'!$S$3:$S$60,"") | S14: 3150 | T14: =S14/L14 -> 1.6500786
A15: 1 | B15: 65 | C15: 3 | D15: =IF(ISNUMBER(SEARCH("Bobby Meadow",F15)),LEFT(F15,FIND(" ",F15)-1)&"M",LEFT(F15,FIND(" ",F15)-1)&MID(F15,FIND(" ",F15)+1,1)) -> 22010F | E15: =IFERROR(IF(_xlfn.XMATCH(D15,'Rent Roll - RPM'!$B$3:$B$60,0,1)>0,"Match","No Match"),"No Match") -> No Match | F15: 22010 Ferguson Meadow Lane | G15: =_xlfn.XLOOKUP(D15,'Rent Roll - RPM'!$B$3:$B$60,'Rent Roll - RPM'!$D$3:$D$60,0) -> 0 | H15: 1 | I15: B3 | J15: Mallard | K15: 3 Bed | L15: 1685 | M15: 1 | N15: Complete | O15: Turned | P15: =_xlfn.XLOOKUP(D15,'Rent Roll - RPM'!$B$3:$B$60,'Rent Roll - RPM'!$Q$3:$Q$60,"") | Q15: =_xlfn.XLOOKUP($D15,'Rent Roll - RPM'!$B$3:$B$60,'Rent Roll - RPM'!$R$3:$R$60,"") | R15: =_xlfn.XLOOKUP(D15,'Rent Roll - RPM'!$B$3:$B$60,'Rent Roll - RPM'!$S$3:$S$60,"") | S15: 2750 | T15: =S15/L15 -> 1.6320475
A16: 3 | B16: 11 | C16: 35 | D16: =IF(ISNUMBER(SEARCH("Bobby Meadow",F16)),LEFT(F16,FIND(" ",F16)-1)&"M",LEFT(F16,FIND(" ",F16)-1)&MID(F16,FIND(" ",F16)+1,1)) -> 22014L | E16: =IFERROR(IF(_xlfn.XMATCH(D16,'Rent Roll - RPM'!$B$3:$B$60,0,1)>0,"Match","No Match"),"No Match") -> No Match | F16: 22014 Lesley Grove Lane | G16: =_xlfn.XLOOKUP(D16,'Rent Roll - RPM'!$B$3:$B$60,'Rent Roll - RPM'!$D$3:$D$60,0) -> 0 | H16: 1 | I16: D2 | J16: Phoenix | K16: 4 Bed | L16: 2431 | M16: 2 | N16: Complete | O16: Turned | P16: =_xlfn.XLOOKUP(D16,'Rent Roll - RPM'!$B$3:$B$60,'Rent Roll - RPM'!$Q$3:$Q$60,"") | Q16: =_xlfn.XLOOKUP($D16,'Rent Roll - RPM'!$B$3:$B$60,'Rent Roll - RPM'!$R$3:$R$60,"") | R16: =_xlfn.XLOOKUP(D16,'Rent Roll - RPM'!$B$3:$B$60,'Rent Roll - RPM'!$S$3:$S$60,"") | S16: 3600 | T16: =S16/L16 -> 1.4808721
A17: 1 | B17: 48 | C17: 27 | D17: =IF(ISNUMBER(SEARCH("Bobby Meadow",F17)),LEFT(F17,FIND(" ",F17)-1)&"M",LEFT(F17,FIND(" ",F17)-1)&MID(F17,FIND(" ",F17)+1,1)) -> 22017L | E17: =IFERROR(IF(_xlfn.XMATCH(D17,'Rent Roll - RPM'!$B$3:$B$60,0,1)>0,"Match","No Match"),"No Match") -> No Match | F17: 22017 Lesley Grove Lane | G17: =_xlfn.XLOOKUP(D17,'Rent Roll - RPM'!$B$3:$B$60,'Rent Roll - RPM'!$D$3:$D$60,0) -> 0 | H17: 1 | I17: F3 | J17: Raven | K17: 3 Bed | L17: 1852 | M17: 2 | N17: Complete | O17: Turned | P17: =_xlfn.XLOOKUP(D17,'Rent Roll - RPM'!$B$3:$B$60,'Rent Roll - RPM'!$Q$3:$Q$60,"") | Q17: =_xlfn.XLOOKUP($D17,'Rent Roll - RPM'!$B$3:$B$60,'Rent Roll - RPM'!$R$3:$R$60,"") | R17: =_xlfn.XLOOKUP(D17,'Rent Roll - RPM'!$B$3:$B$60,'Rent Roll - RPM'!$S$3:$S$60,"") | S17: 2950 | T17: =S17/L17 -> 1.5928726
A18: 3 | B18: 10 | C18: 34 | D18: =IF(ISNUMBER(SEARCH("Bobby Meadow",F18)),LEFT(F18,FIND(" ",F18)-1)&"M",LEFT(F18,FIND(" ",F18)-1)&MID(F18,FIND(" ",F18)+1,1)) -> 22018L | E18: =IFERROR(IF(_xlfn.XMATCH(D18,'Rent Roll - RPM'!$B$3:$B$60,0,1)>0,"Match","No Match"),"No Match") -> No Match | F18: 22018 Lesley Grove Lane | G18: =_xlfn.XLOOKUP(D18,'Rent Roll - RPM'!$B$3:$B$60,'Rent Roll - RPM'!$D$3:$D$60,0) -> 0 | H18: 1 | I18: C1 | J18: Falcon | K18: 3 Bed | L18: 1909 | M18: 2 | N18: Complete | O18: Turned | P18: =_xlfn.XLOOKUP(D18,'Rent Roll - RPM'!$B$3:$B$60,'Rent Roll - RPM'!$Q$3:$Q$60,"") | Q18: =_xlfn.XLOOKUP($D18,'Rent Roll - RPM'!$B$3:$B$60,'Rent Roll - RPM'!$R$3:$R$60,"") | R18: =_xlfn.XLOOKUP(D18,'Rent Roll - RPM'!$B$3:$B$60,'Rent Roll - RPM'!$S$3:$S$60,"") | S18: 3150 | T18: =S18/L18 -> 1.6500786
A19: 1 | B19: 49 | C19: 26 | D19: =IF(ISNUMBER(SEARCH("Bobby Meadow",F19)),LEFT(F19,FIND(" ",F19)-1)&"M",LEFT(F19,FIND(" ",F19)-1)&MID(F19,FIND(" ",F19)+1,1)) -> 22021L | E19: =IFERROR(IF(_xlfn.XMATCH(D19,'Rent Roll - RPM'!$B$3:$B$60,0,1)>0,"Match","No Match"),"No Match") -> No Match | F19: 22021 Lesley Grove Lane | G19: =_xlfn.XLOOKUP(D19,'Rent Roll - RPM'!$B$3:$B$60,'Rent Roll - RPM'!$D$3:$D$60,0) -> 0 | H19: 1 | I19: C3 | J19: Falcon | K19: 3 Bed | L19: 1909 | M19: 2 | N19: Complete | O19: Turned | P19: =_xlfn.XLOOKUP(D19,'Rent Roll - RPM'!$B$3:$B$60,'Rent Roll - RPM'!$Q$3:$Q$60,"") | Q19: =_xlfn.XLOOKUP($D19,'Rent Roll - RPM'!$B$3:$B$60,'Rent Roll - RPM'!$R$3:$R$60,"") | R19: =_xlfn.XLOOKUP(D19,'Rent Roll - RPM'!$B$3:$B$60,'Rent Roll - RPM'!$S$3:$S$60,"") | S19: 3150 | T19: =S19/L19 -> 1.6500786
A20: 1 | B20: 62 | C20: 6 | D20: =IF(ISNUMBER(SEARCH("Bobby Meadow",F20)),LEFT(F20,FIND(" ",F20)-1)&"M",LEFT(F20,FIND(" ",F20)-1)&MID(F20,FIND(" ",F20)+1,1)) -> 22022F | E20: =IFERROR(IF(_xlfn.XMATCH(D20,'Rent Roll - RPM'!$B$3:$B$60,0,1)>0,"Match","No Match"),"No Match") -> No Match | F20: 22022 Ferguson Meadow Lane | G20: =_xlfn.XLOOKUP(D20,'Rent Roll - RPM'!$B$3:$B$60,'Rent Roll - RPM'!$D$3:$D$60,0) -> 0 | H20: 1 | I20: F3 | J20: Raven | K20: 3 Bed | L20: 1852 | M20: 1 | N20: Complete | O20: Turned | P20: =_xlfn.XLOOKUP(D20,'Rent Roll - RPM'!$B$3:$B$60,'Rent Roll - RPM'!$Q$3:$Q$60,"") | Q20: =_xlfn.XLOOKUP($D20,'Rent Roll - RPM'!$B$3:$B$60,'Rent Roll - RPM'!$R$3:$R$60,"") | R20: =_xlfn.XLOOKUP(D20,'Rent Roll - RPM'!$B$3:$B$60,'Rent Roll - RPM'!$S$3:$S$60,"") | S20: 2950 | T20: =S20/L20 -> 1.5928726
A21: 3 | B21: 9 | C21: 33 | D21: =IF(ISNUMBER(SEARCH("Bobby Meadow",F21)),LEFT(F21,FIND(" ",F21)-1)&"M",LEFT(F21,FIND(" ",F21)-1)&MID(F21,FIND(" ",F21)+1,1)) -> 22022L | E21: =IFERROR(IF(_xlfn.XMATCH(D21,'Rent Roll - RPM'!$B$3:$B$60,0,1)>0,"Match","No Match"),"No Match") -> No Match | F21: 22022 Lesley Grove Lane | G21: =_xlfn.XLOOKUP(D21,'Rent Roll - RPM'!$B$3:$B$60,'Rent Roll - RPM'!$D$3:$D$60,0) -> 0 | H21: 1 | I21: F2 | J21: Raven | K21: 3 Bed | L21: 1852 | M21: 2 | N21: Complete | O21: Turned | P21: =_xlfn.XLOOKUP(D21,'Rent Roll - RPM'!$B$3:$B$60,'Rent Roll - RPM'!$Q$3:$Q$60,"") | Q21: =_xlfn.XLOOKUP($D21,'Rent Roll - RPM'!$B$3:$B$60,'Rent Roll - RPM'!$R$3:$R$60,"") | R21: =_xlfn.XLOOKUP(D21,'Rent Roll - RPM'!$B$3:$B$60,'Rent Roll - RPM'!$S$3:$S$60,"") | S21: 2950 | T21: =S21/L21 -> 1.5928726
A22: 2 | B22: 1 | C22: 68 | D22: =IF(ISNUMBER(SEARCH("Bobby Meadow",F22)),LEFT(F22,FIND(" ",F22)-1)&"M",LEFT(F22,FIND(" ",F22)-1)&MID(F22,FIND(" ",F22)+1,1)) -> 7303L | E22: =IFERROR(IF(_xlfn.XMATCH(D22,'Rent Roll - RPM'!$B$3:$B$60,0,1)>0,"Match","No Match"),"No Match") -> No Match | F22: 7303 Leighton Meadow Lane | G22: =_xlfn.XLOOKUP(D22,'Rent Roll - RPM'!$B$3:$B$60,'Rent Roll - RPM'!$D$3:$D$60,0) -> 0 | H22: 1 | I22: F1 | J22: Raven | K22: 3 Bed | L22: 1852 | M22: 4 | N22: 45961 | O22: Leased | P22: 46127 | Q22: =_xlfn.XLOOKUP($D22,'Rent Roll - RPM'!$B$3:$B$60,'Rent Roll - RPM'!$R$3:$R$60,"") | R22: =_xlfn.XLOOKUP(D22,'Rent Roll - RPM'!$B$3:$B$60,'Rent Roll - RPM'!$S$3:$S$60,"") | S22: 2950 | T22: =S22/L22 -> 1.5928726
A23: 1 | B23: 6 | C23: 106 | D23: =IF(ISNUMBER(SEARCH("Bobby Meadow",F23)),LEFT(F23,FIND(" ",F23)-1)&"M",LEFT(F23,FIND(" ",F23)-1)&MID(F23,FIND(" ",F23)+1,1)) -> 7307H | E23: =IFERROR(IF(_xlfn.XMATCH(D23,'Rent Roll - RPM'!$B$3:$B$60,0,1)>0,"Match","No Match"),"No Match") -> No Match | F23: 7307 Hadley Meadow Lane | G23: =_xlfn.XLOOKUP(D23,'Rent Roll - RPM'!$B$3:$B$60,'Rent Roll - RPM'!$D$3:$D$60,0) -> 0 | H23: 1 | I23: C3 | J23: Falcon | K23: 3 Bed | L23: 1909 | M23: 6 | N23: 46006 | O23: Turned | P23: =_xlfn.XLOOKUP(D23,'Rent Roll - RPM'!$B$3:$B$60,'Rent Roll - RPM'!$Q$3:$Q$60,"") | Q23: =_xlfn.XLOOKUP($D23,'Rent Roll - RPM'!$B$3:$B$60,'Rent Roll - RPM'!$R$3:$R$60,"") | R23: =_xlfn.XLOOKUP(D23,'Rent Roll - RPM'!$B$3:$B$60,'Rent Roll - RPM'!$S$3:$S$60,"") | S23: 3150 | T23: =S23/L23 -> 1.6500786
A24: 3 | B24: 15 | C24: 39 | D24: =IF(ISNUMBER(SEARCH("Bobby Meadow",F24)),LEFT(F24,FIND(" ",F24)-1)&"M",LEFT(F24,FIND(" ",F24)-1)&MID(F24,FIND(" ",F24)+1,1)) -> 7310C | E24: =IFERROR(IF(_xlfn.XMATCH(D24,'Rent Roll - RPM'!$B$3:$B$60,0,1)>0,"Match","No Match"),"No Match") -> No Match | F24: 7310 Corey Rushing Lane | G24: =_xlfn.XLOOKUP(D24,'Rent Roll - RPM'!$B$3:$B$60,'Rent Roll - RPM'!$D$3:$D$60,0) -> 0 | H24: 1 | I24: E2 | J24: Sparrow | K24: 2 Bed | L24: 1635 | M24: 2 | N24: Complete | O24: Turned | P24: =_xlfn.XLOOKUP(D24,'Rent Roll - RPM'!$B$3:$B$60,'Rent Roll - RPM'!$Q$3:$Q$60,"") | Q24: =_xlfn.XLOOKUP($D24,'Rent Roll - RPM'!$B$3:$B$60,'Rent Roll - RPM'!$R$3:$R$60,"") | R24: =_xlfn.XLOOKUP(D24,'Rent Roll - RPM'!$B$3:$B$60,'Rent Roll - RPM'!$S$3:$S$60,"") | S24: 2650 | T24: =S24/L24 -> 1.6207951
A25: 1 | B25: 7 | C25: 105 | D25: =IF(ISNUMBER(SEARCH("Bobby Meadow",F25)),LEFT(F25,FIND(" ",F25)-1)&"M",LEFT(F25,FIND(" ",F25)-1)&MID(F25,FIND(" ",F25)+1,1)) -> 7311H | E25: =IFERROR(IF(_xlfn.XMATCH(D25,'Rent Roll - RPM'!$B$3:$B$60,0,1)>0,"Match","No Match"),"No Match") -> No Match | F25: 7311 Hadley Meadow Lane | G25: =_xlfn.XLOOKUP(D25,'Rent Roll - RPM'!$B$3:$B$60,'Rent Roll - RPM'!$D$3:$D$60,0) -> 0 | H25: 1 | I25: C2 | J25: Falcon | K25: 3 Bed | L25: 1909 | M25: 6 | N25: 46006 | O25: Turned | P25: =_xlfn.XLOOKUP(D25,'Rent Roll - RPM'!$B$3:$B$60,'Rent Roll - RPM'!$Q$3:$Q$60,"") | Q25: =_xlfn.XLOOKUP($D25,'Rent Roll - RPM'!$B$3:$B$60,'Rent Roll - RPM'!$R$3:$R$60,"") | R25: =_xlfn.XLOOKUP(D25,'Rent Roll - RPM'!$B$3:$B$60,'Rent Roll - RPM'!$S$3:$S$60,"") | S25: 3150 | T25: =S25/L25 -> 1.6500786
A26: 2 | B26: 3 | C26: 70 | D26: =IF(ISNUMBER(SEARCH("Bobby Meadow",F26)),LEFT(F26,FIND(" ",F26)-1)&"M",LEFT(F26,FIND(" ",F26)-1)&MID(F26,FIND(" ",F26)+1,1)) -> 7311L | E26: =IFERROR(IF(_xlfn.XMATCH(D26,'Rent Roll - RPM'!$B$3:$B$60,0,1)>0,"Match","No Match"),"No Match") -> No Match | F26: 7311 Leighton Meadow Lane | G26: =_xlfn.XLOOKUP(D26,'Rent Roll - RPM'!$B$3:$B$60,'Rent Roll - RPM'!$D$3:$D$60,0) -> 0 | H26: 1 | I26: E2 | J26: Sparrow | K26: 2 Bed | L26: 1635 | M26: 4 | N26: 45961 | O26: Turned | P26: =_xlfn.XLOOKUP(D26,'Rent Roll - RPM'!$B$3:$B$60,'Rent Roll - RPM'!$Q$3:$Q$60,"") | Q26: =_xlfn.XLOOKUP($D26,'Rent Roll - RPM'!$B$3:$B$60,'Rent Roll - RPM'!$R$3:$R$60,"") | R26: =_xlfn.XLOOKUP(D26,'Rent Roll - RPM'!$B$3:$B$60,'Rent Roll - RPM'!$S$3:$S$60,"") | S26: 2650 | T26: =S26/L26 -> 1.6207951
A27: 3 | B27: 14 | C27: 38 | D27: =IF(ISNUMBER(SEARCH("Bobby Meadow",F27)),LEFT(F27,FIND(" ",F27)-1)&"M",LEFT(F27,FIND(" ",F27)-1)&MID(F27,FIND(" ",F27)+1,1)) -> 7314C | E27: =IFERROR(IF(_xlfn.XMATCH(D27,'Rent Roll - RPM'!$B$3:$B$60,0,1)>0,"Match","No Match"),"No Match") -> No Match | F27: 7314 Corey Rushing Lane | G27: =_xlfn.XLOOKUP(D27,'Rent Roll - RPM'!$B$3:$B$60,'Rent Roll - RPM'!$D$3:$D$60,0) -> 0 | H27: 1 | I27: E3 | J27: Sparrow | K27: 2 Bed | L27: 1635 | M27: 2 | N27: Complete | O27: Turned | P27: =_xlfn.XLOOKUP(D27,'Rent Roll - RPM'!$B$3:$B$60,'Rent Roll - RPM'!$Q$3:$Q$60,"") | Q27: =_xlfn.XLOOKUP($D27,'Rent Roll - RPM'!$B$3:$B$60,'Rent Roll - RPM'!$R$3:$R$60,"") | R27: =_xlfn.XLOOKUP(D27,'Rent Roll - RPM'!$B$3:$B$60,'Rent Roll - RPM'!$S$3:$S$60,"") | S27: 2650 | T27: =S27/L27 -> 1.6207951
A28: 3 | B28: 18 | C28: 62 | D28: =IF(ISNUMBER(SEARCH("Bobby Meadow",F28)),LEFT(F28,FIND(" ",F28)-1)&"M",LEFT(F28,FIND(" ",F28)-1)&MID(F28,FIND(" ",F28)+1,1)) -> 7314L | E28: =IFERROR(IF(_xlfn.XMATCH(D28,'Rent Roll - RPM'!$B$3:$B$60,0,1)>0,"Match","No Match"),"No Match") -> No Match | F28: 7314 Leighton Meadow Lane | G28: =_xlfn.XLOOKUP(D28,'Rent Roll - RPM'!$B$3:$B$60,'Rent Roll - RPM'!$D$3:$D$60,0) -> 0 | H28: 1 | I28: E3 | J28: Sparrow | K28: 2 Bed | L28: 1635 | M28: 4 | N28: 45961 | O28: Turned | P28: =_xlfn.XLOOKUP(D28,'Rent Roll - RPM'!$B$3:$B$60,'Rent Roll - RPM'!$Q$3:$Q$60,"") | Q28: =_xlfn.XLOOKUP($D28,'Rent Roll - RPM'!$B$3:$B$60,'Rent Roll - RPM'!$R$3:$R$60,"") | R28: =_xlfn.XLOOKUP(D28,'Rent Roll - RPM'!$B$3:$B$60,'Rent Roll - RPM'!$S$3:$S$60,"") | S28: 2650 | T28: =S28/L28 -> 1.6207951
A29: 1 | B29: 8 | C29: 104 | D29: =IF(ISNUMBER(SEARCH("Bobby Meadow",F29)),LEFT(F29,FIND(" ",F29)-1)&"M",LEFT(F29,FIND(" ",F29)-1)&MID(F29,FIND(" ",F29)+1,1)) -> 7315H | E29: =IFERROR(IF(_xlfn.XMATCH(D29,'Rent Roll - RPM'!$B$3:$B$60,0,1)>0,"Match","No Match"),"No Match") -> No Match | F29: 7315 Hadley Meadow Lane | G29: =_xlfn.XLOOKUP(D29,'Rent Roll - RPM'!$B$3:$B$60,'Rent Roll - RPM'!$D$3:$D$60,0) -> 0 | H29: 1 | I29: F1 | J29: Raven | K29: 3 Bed | L29: 1852 | M29: 6 | N29: 46006 | O29: Turned | P29: =_xlfn.XLOOKUP(D29,'Rent Roll - RPM'!$B$3:$B$60,'Rent Roll - RPM'!$Q$3:$Q$60,"") | Q29: =_xlfn.XLOOKUP($D29,'Rent Roll - RPM'!$B$3:$B$60,'Rent Roll - RPM'!$R$3:$R$60,"") | R29: =_xlfn.XLOOKUP(D29,'Rent Roll - RPM'!$B$3:$B$60,'Rent Roll - RPM'!$S$3:$S$60,"") | S29: 2950 | T29: =S29/L29 -> 1.5928726
A30: 2 | B30: 4 | C30: 71 | D30: =IF(ISNUMBER(SEARCH("Bobby Meadow",F30)),LEFT(F30,FIND(" ",F30)-1)&"M",LEFT(F30,FIND(" ",F30)-1)&MID(F30,FIND(" ",F30)+1,1)) -> 7315L | E30: =IFERROR(IF(_xlfn.XMATCH(D30,'Rent Roll - RPM'!$B$3:$B$60,0,1)>0,"Match","No Match"),"No Match") -> No Match | F30: 7315 Leighton Meadow Lane | G30: =_xlfn.XLOOKUP(D30,'Rent Roll - RPM'!$B$3:$B$60,'Rent Roll - RPM'!$D$3:$D$60,0) -> 0 | H30: 1 | I30: E1 | J30: Sparrow | K30: 2 Bed | L30: 1635 | M30: 4 | N30: 45961 | O30: Turned | P30: =_xlfn.XLOOKUP(D30,'Rent Roll - RPM'!$B$3:$B$60,'Rent Roll - RPM'!$Q$3:$Q$60,"") | Q30: =_xlfn.XLOOKUP($D30,'Rent Roll - RPM'!$B$3:$B$60,'Rent Roll - RPM'!$R$3:$R$60,"") | R30: =_xlfn.XLOOKUP(D30,'Rent Roll - RPM'!$B$3:$B$60,'Rent Roll - RPM'!$S$3:$S$60,"") | S30: 2650 | T30: =S30/L30 -> 1.6207951
A31: 3 | B31: 13 | C31: 37 | D31: =IF(ISNUMBER(SEARCH("Bobby Meadow",F31)),LEFT(F31,FIND(" ",F31)-1)&"M",LEFT(F31,FIND(" ",F31)-1)&MID(F31,FIND(" ",F31)+1,1)) -> 7318C | E31: =IFERROR(IF(_xlfn.XMATCH(D31,'Rent Roll - RPM'!$B$3:$B$60,0,1)>0,"Match","No Match"),"No Match") -> No Match | F31: 7318 Corey Rushing Lane | G31: =_xlfn.XLOOKUP(D31,'Rent Roll - RPM'!$B$3:$B$60,'Rent Roll - RPM'!$D$3:$D$60,0) -> 0 | H31: 1 | I31: C1 | J31: Falcon | K31: 3 Bed | L31: 1909 | M31: 2 | N31: Complete | O31: Turned | P31: =_xlfn.XLOOKUP(D31,'Rent Roll - RPM'!$B$3:$B$60,'Rent Roll - RPM'!$Q$3:$Q$60,"") | Q31: =_xlfn.XLOOKUP($D31,'Rent Roll - RPM'!$B$3:$B$60,'Rent Roll - RPM'!$R$3:$R$60,"") | R31: =_xlfn.XLOOKUP(D31,'Rent Roll - RPM'!$B$3:$B$60,'Rent Roll - RPM'!$S$3:$S$60,"") | S31: 3150 | T31: =S31/L31 -> 1.6500786
A32: 2 | B32: 27 | C32: 117 | D32: =IF(ISNUMBER(SEARCH("Bobby Meadow",F32)),LEFT(F32,FIND(" ",F32)-1)&"M",LEFT(F32,FIND(" ",F32)-1)&MID(F32,FIND(" ",F32)+1,1)) -> 7318H | E32: =IFERROR(IF(_xlfn.XMATCH(D32,'Rent Roll - RPM'!$B$3:$B$60,0,1)>0,"Match","No Match"),"No Match") -> No Match | F32: 7318 Hadley Meadow Lane | G32: =_xlfn.XLOOKUP(D32,'Rent Roll - RPM'!$B$3:$B$60,'Rent Roll - RPM'!$D$3:$D$60,0) -> 0 | H32: 1 | I32: E1 | J32: Sparrow | K32: 2 Bed | L32: 1635 | M32: 6 | N32: 46006 | O32: Turned | P32: =_xlfn.XLOOKUP(D32,'Rent Roll - RPM'!$B$3:$B$60,'Rent Roll - RPM'!$Q$3:$Q$60,"") | Q32: =_xlfn.XLOOKUP($D32,'Rent Roll - RPM'!$B$3:$B$60,'Rent Roll - RPM'!$R$3:$R$60,"") | R32: =_xlfn.XLOOKUP(D32,'Rent Roll - RPM'!$B$3:$B$60,'Rent Roll - RPM'!$S$3:$S$60,"") | S32: 2650 | T32: =S32/L32 -> 1.6207951
A33: 3 | B33: 19 | C33: 63 | D33: =IF(ISNUMBER(SEARCH("Bobby Meadow",F33)),LEFT(F33,FIND(" ",F33)-1)&"M",LEFT(F33,FIND(" ",F33)-1)&MID(F33,FIND(" ",F33)+1,1)) -> 7318L | E33: =IFERROR(IF(_xlfn.XMATCH(D33,'Rent Roll - RPM'!$B$3:$B$60,0,1)>0,"Match","No Match"),"No Match") -> No Match | F33: 7318 Leighton Meadow Lane | G33: =_xlfn.XLOOKUP(D33,'Rent Roll - RPM'!$B$3:$B$60,'Rent Roll - RPM'!$D$3:$D$60,0) -> 0 | H33: 1 | I33: A1 | J33: Canary | K33: 2 Bed | L33: 1425 | M33: 4 | N33: 45961 | O33: Turned | P33: =_xlfn.XLOOKUP(D33,'Rent Roll - RPM'!$B$3:$B$60,'Rent Roll - RPM'!$Q$3:$Q$60,"") | Q33: =_xlfn.XLOOKUP($D33,'Rent Roll - RPM'!$B$3:$B$60,'Rent Roll - RPM'!$R$3:$R$60,"") | R33: =_xlfn.XLOOKUP(D33,'Rent Roll - RPM'!$B$3:$B$60,'Rent Roll - RPM'!$S$3:$S$60,"") | S33: 2450 | T33: =S33/L33 -> 1.7192982
A34: 1 | B34: 9 | C34: 103 | D34: =IF(ISNUMBER(SEARCH("Bobby Meadow",F34)),LEFT(F34,FIND(" ",F34)-1)&"M",LEFT(F34,FIND(" ",F34)-1)&MID(F34,FIND(" ",F34)+1,1)) -> 7319H | E34: =IFERROR(IF(_xlfn.XMATCH(D34,'Rent Roll - RPM'!$B$3:$B$60,0,1)>0,"Match","No Match"),"No Match") -> No Match | F34: 7319 Hadley Meadow Lane | G34: =_xlfn.XLOOKUP(D34,'Rent Roll - RPM'!$B$3:$B$60,'Rent Roll - RPM'!$D$3:$D$60,0) -> 0 | H34: 1 | I34: F3 | J34: Raven | K34: 3 Bed | L34: 1852 | M34: 6 | N34: 46006 | O34: Turned | P34: =_xlfn.XLOOKUP(D34,'Rent Roll - RPM'!$B$3:$B$60,'Rent Roll - RPM'!$Q$3:$Q$60,"") | Q34: =_xlfn.XLOOKUP($D34,'Rent Roll - RPM'!$B$3:$B$60,'Rent Roll - RPM'!$R$3:$R$60,"") | R34: =_xlfn.XLOOKUP(D34,'Rent Roll - RPM'!$B$3:$B$60,'Rent Roll - RPM'!$S$3:$S$60,"") | S34: 2950 | T34: =S34/L34 -> 1.5928726
A35: 2 | B35: 5 | C35: 72 | D35: =IF(ISNUMBER(SEARCH("Bobby Meadow",F35)),LEFT(F35,FIND(" ",F35)-1)&"M",LEFT(F35,FIND(" ",F35)-1)&MID(F35,FIND(" ",F35)+1,1)) -> 7319L | E35: =IFERROR(IF(_xlfn.XMATCH(D35,'Rent Roll - RPM'!$B$3:$B$60,0,1)>0,"Match","No Match"),"No Match") -> No Match | F35: 7319 Leighton Meadow Lane | G35: =_xlfn.XLOOKUP(D35,'Rent Roll - RPM'!$B$3:$B$60,'Rent Roll - RPM'!$D$3:$D$60,0) -> 0 | H35: 1 | I35: A2 | J35: Canary | K35: 2 Bed | L35: 1425 | M35: 4 | N35: 45961 | O35: Turned | P35: =_xlfn.XLOOKUP(D35,'Rent Roll - RPM'!$B$3:$B$60,'Rent Roll - RPM'!$Q$3:$Q$60,"") | Q35: =_xlfn.XLOOKUP($D35,'Rent Roll - RPM'!$B$3:$B$60,'Rent Roll - RPM'!$R$3:$R$60,"") | R35: =_xlfn.XLOOKUP(D35,'Rent Roll - RPM'!$B$3:$B$60,'Rent Roll - RPM'!$S$3:$S$60,"") | S35: 2450 | T35: =S35/L35 -> 1.7192982
A36: 2 | B36: 26 | C36: 116 | D36: =IF(ISNUMBER(SEARCH("Bobby Meadow",F36)),LEFT(F36,FIND(" ",F36)-1)&"M",LEFT(F36,FIND(" ",F36)-1)&MID(F36,FIND(" ",F36)+1,1)) -> 7322H | E36: =IFERROR(IF(_xlfn.XMATCH(D36,'Rent Roll - RPM'!$B$3:$B$60,0,1)>0,"Match","No Match"),"No Match") -> No Match | F36: 7322 Hadley Meadow Lane | G36: =_xlfn.XLOOKUP(D36,'Rent Roll - RPM'!$B$3:$B$60,'Rent Roll - RPM'!$D$3:$D$60,0) -> 0 | H36: 1 | I36: A3 | J36: Canary | K36: 2 Bed | L36: 1425 | M36: 6 | N36: 46006 | O36: Turned | P36: =_xlfn.XLOOKUP(D36,'Rent Roll - RPM'!$B$3:$B$60,'Rent Roll - RPM'!$Q$3:$Q$60,"") | Q36: =_xlfn.XLOOKUP($D36,'Rent Roll - RPM'!$B$3:$B$60,'Rent Roll - RPM'!$R$3:$R$60,"") | R36: =_xlfn.XLOOKUP(D36,'Rent Roll - RPM'!$B$3:$B$60,'Rent Roll - RPM'!$S$3:$S$60,"") | S36: 2450 | T36: =S36/L36 -> 1.7192982
A37: 3 | B37: 20 | C37: 64 | D37: =IF(ISNUMBER(SEARCH("Bobby Meadow",F37)),LEFT(F37,FIND(" ",F37)-1)&"M",LEFT(F37,FIND(" ",F37)-1)&MID(F37,FIND(" ",F37)+1,1)) -> 7322L | E37: =IFERROR(IF(_xlfn.XMATCH(D37,'Rent Roll - RPM'!$B$3:$B$60,0,1)>0,"Match","No Match"),"No Match") -> No Match | F37: 7322 Leighton Meadow Lane | G37: =_xlfn.XLOOKUP(D37,'Rent Roll - RPM'!$B$3:$B$60,'Rent Roll - RPM'!$D$3:$D$60,0) -> 0 | H37: 1 | I37: B2 | J37: Mallard | K37: 3 Bed | L37: 1685 | M37: 4 | N37: 45961 | O37: Turned | P37: =_xlfn.XLOOKUP(D37,'Rent Roll - RPM'!$B$3:$B$60,'Rent Roll - RPM'!$Q$3:$Q$60,"") | Q37: =_xlfn.XLOOKUP($D37,'Rent Roll - RPM'!$B$3:$B$60,'Rent Roll - RPM'!$R$3:$R$60,"") | R37: =_xlfn.XLOOKUP(D37,'Rent Roll - RPM'!$B$3:$B$60,'Rent Roll - RPM'!$S$3:$S$60,"") | S37: 2750 | T37: =S37/L37 -> 1.6320475
A38: 2 | B38: 6 | C38: 73 | D38: =IF(ISNUMBER(SEARCH("Bobby Meadow",F38)),LEFT(F38,FIND(" ",F38)-1)&"M",LEFT(F38,FIND(" ",F38)-1)&MID(F38,FIND(" ",F38)+1,1)) -> 7323L | E38: =IFERROR(IF(_xlfn.XMATCH(D38,'Rent Roll - RPM'!$B$3:$B$60,0,1)>0,"Match","No Match"),"No Match") -> No Match | F38: 7323 Leighton Meadow Lane | G38: =_xlfn.XLOOKUP(D38,'Rent Roll - RPM'!$B$3:$B$60,'Rent Roll - RPM'!$D$3:$D$60,0) -> 0 | H38: 1 | I38: E2 | J38: Sparrow | K38: 2 Bed | L38: 1635 | M38: 4 | N38: 45961 | O38: Turned | P38: =_xlfn.XLOOKUP(D38,'Rent Roll - RPM'!$B$3:$B$60,'Rent Roll - RPM'!$Q$3:$Q$60,"") | Q38: =_xlfn.XLOOKUP($D38,'Rent Roll - RPM'!$B$3:$B$60,'Rent Roll - RPM'!$R$3:$R$60,"") | R38: =_xlfn.XLOOKUP(D38,'Rent Roll - RPM'!$B$3:$B$60,'Rent Roll - RPM'!$S$3:$S$60,"") | S38: 2650 | T38: =S38/L38 -> 1.6207951
A39: 2 | B39: 25 | C39: 115 | D39: =IF(ISNUMBER(SEARCH("Bobby Meadow",F39)),LEFT(F39,FIND(" ",F39)-1)&"M",LEFT(F39,FIND(" ",F39)-1)&MID(F39,FIND(" ",F39)+1,1)) -> 7326H | E39: =IFERROR(IF(_xlfn.XMATCH(D39,'Rent Roll - RPM'!$B$3:$B$60,0,1)>0,"Match","No Match"),"No Match") -> No Match | F39: 7326 Hadley Meadow Lane | G39: =_xlfn.XLOOKUP(D39,'Rent Roll - RPM'!$B$3:$B$60,'Rent Roll - RPM'!$D$3:$D$60,0) -> 0 | H39: 1 | I39: A1 | J39: Canary | K39: 2 Bed | L39: 1425 | M39: 6 | N39: 46006 | O39: Turned | P39: =_xlfn.XLOOKUP(D39,'Rent Roll - RPM'!$B$3:$B$60,'Rent Roll - RPM'!$Q$3:$Q$60,"") | Q39: =_xlfn.XLOOKUP($D39,'Rent Roll - RPM'!$B$3:$B$60,'Rent Roll - RPM'!$R$3:$R$60,"") | R39: =_xlfn.XLOOKUP(D39,'Rent Roll - RPM'!$B$3:$B$60,'Rent Roll - RPM'!$S$3:$S$60,"") | S39: 2450 | T39: =S39/L39 -> 1.7192982
A40: 1 | B40: 11 | C40: 101 | D40: =IF(ISNUMBER(SEARCH("Bobby Meadow",F40)),LEFT(F40,FIND(" ",F40)-1)&"M",LEFT(F40,FIND(" ",F40)-1)&MID(F40,FIND(" ",F40)+1,1)) -> 7327H | E40: =IFERROR(IF(_xlfn.XMATCH(D40,'Rent Roll - RPM'!$B$3:$B$60,0,1)>0,"Match","No Match"),"No Match") -> No Match | F40: 7327 Hadley Meadow Lane | G40: =_xlfn.XLOOKUP(D40,'Rent Roll - RPM'!$B$3:$B$60,'Rent Roll - RPM'!$D$3:$D$60,0) -> 0 | H40: 1 | I40: F2 | J40: Raven | K40: 3 Bed | L40: 1852 | M40: 6 | N40: 46006 | O40: Turned | P40: =_xlfn.XLOOKUP(D40,'Rent Roll - RPM'!$B$3:$B$60,'Rent Roll - RPM'!$Q$3:$Q$60,"") | Q40: =_xlfn.XLOOKUP($D40,'Rent Roll - RPM'!$B$3:$B$60,'Rent Roll - RPM'!$R$3:$R$60,"") | R40: =_xlfn.XLOOKUP(D40,'Rent Roll - RPM'!$B$3:$B$60,'Rent Roll - RPM'!$S$3:$S$60,"") | S40: 2950 | T40: =S40/L40 -> 1.5928726
A41: 2 | B41: 24 | C41: 114 | D41: =IF(ISNUMBER(SEARCH("Bobby Meadow",F41)),LEFT(F41,FIND(" ",F41)-1)&"M",LEFT(F41,FIND(" ",F41)-1)&MID(F41,FIND(" ",F41)+1,1)) -> 7330H | E41: =IFERROR(IF(_xlfn.XMATCH(D41,'Rent Roll - RPM'!$B$3:$B$60,0,1)>0,"Match","No Match"),"No Match") -> No Match | F41: 7330 Hadley Meadow Lane | G41: =_xlfn.XLOOKUP(D41,'Rent Roll - RPM'!$B$3:$B$60,'Rent Roll - RPM'!$D$3:$D$60,0) -> 0 | H41: 1 | I41: A2 | J41: Canary | K41: 2 Bed | L41: 1425 | M41: 6 | N41: 46006 | O41: Turned | P41: =_xlfn.XLOOKUP(D41,'Rent Roll - RPM'!$B$3:$B$60,'Rent Roll - RPM'!$Q$3:$Q$60,"") | Q41: =_xlfn.XLOOKUP($D41,'Rent Roll - RPM'!$B$3:$B$60,'Rent Roll - RPM'!$R$3:$R$60,"") | R41: =_xlfn.XLOOKUP(D41,'Rent Roll - RPM'!$B$3:$B$60,'Rent Roll - RPM'!$S$3:$S$60,"") | S41: 2450 | T41: =S41/L41 -> 1.7192982
A42: 1 | B42: 12 | C42: 100 | D42: =IF(ISNUMBER(SEARCH("Bobby Meadow",F42)),LEFT(F42,FIND(" ",F42)-1)&"M",LEFT(F42,FIND(" ",F42)-1)&MID(F42,FIND(" ",F42)+1,1)) -> 7331H | E42: =IFERROR(IF(_xlfn.XMATCH(D42,'Rent Roll - RPM'!$B$3:$B$60,0,1)>0,"Match","No Match"),"No Match") -> No Match | F42: 7331 Hadley Meadow Lane | G42: =_xlfn.XLOOKUP(D42,'Rent Roll - RPM'!$B$3:$B$60,'Rent Roll - RPM'!$D$3:$D$60,0) -> 0 | H42: 1 | I42: C1 | J42: Falcon | K42: 3 Bed | L42: 1909 | M42: 6 | N42: 46006 | O42: Turned | P42: =_xlfn.XLOOKUP(D42,'Rent Roll - RPM'!$B$3:$B$60,'Rent Roll - RPM'!$Q$3:$Q$60,"") | Q42: =_xlfn.XLOOKUP($D42,'Rent Roll - RPM'!$B$3:$B$60,'Rent Roll - RPM'!$R$3:$R$60,"") | R42: =_xlfn.XLOOKUP(D42,'Rent Roll - RPM'!$B$3:$B$60,'Rent Roll - RPM'!$S$3:$S$60,"") | S42: 3150 | T42: =S42/L42 -> 1.6500786
A43: 2 | B43: 23 | C43: 113 | D43: =IF(ISNUMBER(SEARCH("Bobby Meadow",F43)),LEFT(F43,FIND(" ",F43)-1)&"M",LEFT(F43,FIND(" ",F43)-1)&MID(F43,FIND(" ",F43)+1,1)) -> 7334H | E43: =IFERROR(IF(_xlfn.XMATCH(D43,'Rent Roll - RPM'!$B$3:$B$60,0,1)>0,"Match","No Match"),"No Match") -> No Match | F43: 7334 Hadley Meadow Lane | G43: =_xlfn.XLOOKUP(D43,'Rent Roll - RPM'!$B$3:$B$60,'Rent Roll - RPM'!$D$3:$D$60,0) -> 0 | H43: 1 | I43: B3 | J43: Mallard | K43: 3 Bed | L43: 1685 | M43: 6 | N43: 46006 | O43: Turned | P43: =_xlfn.XLOOKUP(D43,'Rent Roll - RPM'!$B$3:$B$60,'Rent Roll - RPM'!$Q$3:$Q$60,"") | Q43: =_xlfn.XLOOKUP($D43,'Rent Roll - RPM'!$B$3:$B$60,'Rent Roll - RPM'!$R$3:$R$60,"") | R43: =_xlfn.XLOOKUP(D43,'Rent Roll - RPM'!$B$3:$B$60,'Rent Roll - RPM'!$S$3:$S$60,"") | S43: 2750 | T43: =S43/L43 -> 1.6320475
... A54: 2 | B54: 18 | C54: 94 | D54: =IF(ISNUMBER(SEARCH("Bobby Meadow",F54)),LEFT(F54,FIND(" ",F54)-1)&"M",LEFT(F54,FIND(" ",F54)-1)&MID(F54,FIND(" ",F54)+1,1)) -> 7414H | E54: =IFERROR(IF(_xlfn.XMATCH(D54,'Rent Roll - RPM'!$B$3:$B$60,0,1)>0,"Match","No Match"),"No Match") -> No Match | F54: 7414 Hadley Meadow Lane | G54: =_xlfn.XLOOKUP(D54,'Rent Roll - RPM'!$B$3:$B$60,'Rent Roll - RPM'!$D$3:$D$60,0) -> 0 | H54: 1 | I54: A2 | J54: Canary | K54: 2 Bed | L54: 1425 | M54: 5 | N54: 45991 | O54: Turned | P54: =_xlfn.XLOOKUP(D54,'Rent Roll - RPM'!$B$3:$B$60,'Rent Roll - RPM'!$Q$3:$Q$60,"") | Q54: =_xlfn.XLOOKUP($D54,'Rent Roll - RPM'!$B$3:$B$60,'Rent Roll - RPM'!$R$3:$R$60,"") | R54: =_xlfn.XLOOKUP(D54,'Rent Roll - RPM'!$B$3:$B$60,'Rent Roll - RPM'!$S$3:$S$60,"") | S54: 2450 | T54: =S54/L54 -> 1.7192982
A55: 2 | B55: 1R | C55: 77 | D55: =IF(ISNUMBER(SEARCH("Bobby Meadow",F55)),LEFT(F55,FIND(" ",F55)-1)&"M",LEFT(F55,FIND(" ",F55)-1)&MID(F55,FIND(" ",F55)+1,1)) -> 7415L | E55: =IFERROR(IF(_xlfn.XMATCH(D55,'Rent Roll - RPM'!$B$3:$B$60,0,1)>0,"Match","No Match"),"No Match") -> No Match | F55: 7415 Leighton Meadow Lane | G55: =_xlfn.XLOOKUP(D55,'Rent Roll - RPM'!$B$3:$B$60,'Rent Roll - RPM'!$D$3:$D$60,0) -> 0 | H55: 1 | I55: C1 | J55: Falcon | K55: 3 Bed | L55: 1909 | M55: 4 | N55: 45961 | O55: Turned | P55: =_xlfn.XLOOKUP(D55,'Rent Roll - RPM'!$B$3:$B$60,'Rent Roll - RPM'!$Q$3:$Q$60,"") | Q55: =_xlfn.XLOOKUP($D55,'Rent Roll - RPM'!$B$3:$B$60,'Rent Roll - RPM'!$R$3:$R$60,"") | R55: =_xlfn.XLOOKUP(D55,'Rent Roll - RPM'!$B$3:$B$60,'Rent Roll - RPM'!$S$3:$S$60,"") | S55: 3150 | T55: =S55/L55 -> 1.6500786
A56: 2 | B56: 17 | C56: 93 | D56: =IF(ISNUMBER(SEARCH("Bobby Meadow",F56)),LEFT(F56,FIND(" ",F56)-1)&"M",LEFT(F56,FIND(" ",F56)-1)&MID(F56,FIND(" ",F56)+1,1)) -> 7418H | E56: =IFERROR(IF(_xlfn.XMATCH(D56,'Rent Roll - RPM'!$B$3:$B$60,0,1)>0,"Match","No Match"),"No Match") -> No Match | F56: 7418 Hadley Meadow Lane | G56: =_xlfn.XLOOKUP(D56,'Rent Roll - RPM'!$B$3:$B$60,'Rent Roll - RPM'!$D$3:$D$60,0) -> 0 | H56: 1 | I56: E3 | J56: Sparrow | K56: 2 Bed | L56: 1635 | M56: 5 | N56: 45991 | O56: Turned | P56: =_xlfn.XLOOKUP(D56,'Rent Roll - RPM'!$B$3:$B$60,'Rent Roll - RPM'!$Q$3:$Q$60,"") | Q56: =_xlfn.XLOOKUP($D56,'Rent Roll - RPM'!$B$3:$B$60,'Rent Roll - RPM'!$R$3:$R$60,"") | R56: =_xlfn.XLOOKUP(D56,'Rent Roll - RPM'!$B$3:$B$60,'Rent Roll - RPM'!$S$3:$S$60,"") | S56: 2650 | T56: =S56/L56 -> 1.6207951
A57: 1 | B57: 20 | C57: 84 | D57: =IF(ISNUMBER(SEARCH("Bobby Meadow",F57)),LEFT(F57,FIND(" ",F57)-1)&"M",LEFT(F57,FIND(" ",F57)-1)&MID(F57,FIND(" ",F57)+1,1)) -> 7423H | E57: =IFERROR(IF(_xlfn.XMATCH(D57,'Rent Roll - RPM'!$B$3:$B$60,0,1)>0,"Match","No Match"),"No Match") -> No Match | F57: 7423 Hadley Meadow Lane | G57: =_xlfn.XLOOKUP(D57,'Rent Roll - RPM'!$B$3:$B$60,'Rent Roll - RPM'!$D$3:$D$60,0) -> 0 | H57: 1 | I57: C2 | J57: Falcon | K57: 3 Bed | L57: 1909 | M57: 5 | N57: 45991 | O57: Turned | P57: =_xlfn.XLOOKUP(D57,'Rent Roll - RPM'!$B$3:$B$60,'Rent Roll - RPM'!$Q$3:$Q$60,"") | Q57: =_xlfn.XLOOKUP($D57,'Rent Roll - RPM'!$B$3:$B$60,'Rent Roll - RPM'!$R$3:$R$60,"") | R57: =_xlfn.XLOOKUP(D57,'Rent Roll - RPM'!$B$3:$B$60,'Rent Roll - RPM'!$S$3:$S$60,"") | S57: 3150 | T57: =S57/L57 -> 1.6500786
A58: 2 | B58: 11 | C58: 60 | D58: =IF(ISNUMBER(SEARCH("Bobby Meadow",F58)),LEFT(F58,FIND(" ",F58)-1)&"M",LEFT(F58,FIND(" ",F58)-1)&MID(F58,FIND(" ",F58)+1,1)) -> 7423L | E58: =IFERROR(IF(_xlfn.XMATCH(D58,'Rent Roll - RPM'!$B$3:$B$60,0,1)>0,"Match","No Match"),"No Match") -> No Match | F58: 7423 Leighton Meadow Lane | G58: =_xlfn.XLOOKUP(D58,'Rent Roll - RPM'!$B$3:$B$60,'Rent Roll - RPM'!$D$3:$D$60,0) -> 0 | H58: 1 | I58: F2 | J58: Raven | K58: 3 Bed | L58: 1852 | M58: 3 | N58: Complete | O58: Turned | P58: =_xlfn.XLOOKUP(D58,'Rent Roll - RPM'!$B$3:$B$60,'Rent Roll - RPM'!$Q$3:$Q$60,"") | Q58: =_xlfn.XLOOKUP($D58,'Rent Roll - RPM'!$B$3:$B$60,'Rent Roll - RPM'!$R$3:$R$60,"") | R58: =_xlfn.XLOOKUP(D58,'Rent Roll - RPM'!$B$3:$B$60,'Rent Roll - RPM'!$S$3:$S$60,"") | S58: 2950 | T58: =S58/L58 -> 1.5928726
A59: 1 | B59: 21 | C59: 83 | D59: =IF(ISNUMBER(SEARCH("Bobby Meadow",F59)),LEFT(F59,FIND(" ",F59)-1)&"M",LEFT(F59,FIND(" ",F59)-1)&MID(F59,FIND(" ",F59)+1,1)) -> 7427H | E59: =IFERROR(IF(_xlfn.XMATCH(D59,'Rent Roll - RPM'!$B$3:$B$60,0,1)>0,"Match","No Match"),"No Match") -> No Match | F59: 7427 Hadley Meadow Lane | G59: =_xlfn.XLOOKUP(D59,'Rent Roll - RPM'!$B$3:$B$60,'Rent Roll - RPM'!$D$3:$D$60,0) -> 0 | H59: 1 | I59: C3 | J59: Falcon | K59: 3 Bed | L59: 1909 | M59: 5 | N59: 45991 | O59: Turned | P59: =_xlfn.XLOOKUP(D59,'Rent Roll - RPM'!$B$3:$B$60,'Rent Roll - RPM'!$Q$3:$Q$60,"") | Q59: =_xlfn.XLOOKUP($D59,'Rent Roll - RPM'!$B$3:$B$60,'Rent Roll - RPM'!$R$3:$R$60,"") | R59: =_xlfn.XLOOKUP(D59,'Rent Roll - RPM'!$B$3:$B$60,'Rent Roll - RPM'!$S$3:$S$60,"") | S59: 3150 | T59: =S59/L59 -> 1.6500786
A60: 2 | B60: 12 | C60: 59 | D60: =IF(ISNUMBER(SEARCH("Bobby Meadow",F60)),LEFT(F60,FIND(" ",F60)-1)&"M",LEFT(F60,FIND(" ",F60)-1)&MID(F60,FIND(" ",F60)+1,1)) -> 7427L | E60: =IFERROR(IF(_xlfn.XMATCH(D60,'Rent Roll - RPM'!$B$3:$B$60,0,1)>0,"Match","No Match"),"No Match") -> No Match | F60: 7427 Leighton Meadow Lane | G60: =_xlfn.XLOOKUP(D60,'Rent Roll - RPM'!$B$3:$B$60,'Rent Roll - RPM'!$D$3:$D$60,0) -> 0 | H60: 1 | I60: E3 | J60: Sparrow | K60: 2 Bed | L60: 1635 | M60: 3 | N60: Complete | O60: Turned | P60: =_xlfn.XLOOKUP(D60,'Rent Roll - RPM'!$B$3:$B$60,'Rent Roll - RPM'!$Q$3:$Q$60,"") | Q60: =_xlfn.XLOOKUP($D60,'Rent Roll - RPM'!$B$3:$B$60,'Rent Roll - RPM'!$R$3:$R$60,"") | R60: =_xlfn.XLOOKUP(D60,'Rent Roll - RPM'!$B$3:$B$60,'Rent Roll - RPM'!$S$3:$S$60,"") | S60: 2650 | T60: =S60/L60 -> 1.6207951
A61: 2 | B61: 16 | C61: 92 | D61: =IF(ISNUMBER(SEARCH("Bobby Meadow",F61)),LEFT(F61,FIND(" ",F61)-1)&"M",LEFT(F61,FIND(" ",F61)-1)&MID(F61,FIND(" ",F61)+1,1)) -> 7422H | E61: =IFERROR(IF(_xlfn.XMATCH(D61,'Rent Roll - RPM'!$B$3:$B$60,0,1)>0,"Match","No Match"),"No Match") -> No Match | F61: 7422 Hadley Meadow Lane | G61: Ikenna Eseadum | H61: 1 | I61: E2 | J61: Sparrow | K61: 2 Bed | L61: 1635 | M61: 5 | N61: 45991 | O61: Tenant Occupied | P61: =Q61 -> 46127 | Q61: 46127 | R61: =_xlfn.XLOOKUP(D61,'Rent Roll - RPM'!$B$3:$B$60,'Rent Roll - RPM'!$S$3:$S$60,"") | S61: 2650 | T61: =S61/L61 -> 1.6207951
A62: 3 | B62: 16 | C62: 40 | D62: =IF(ISNUMBER(SEARCH("Bobby Meadow",F62)),LEFT(F62,FIND(" ",F62)-1)&"M",LEFT(F62,FIND(" ",F62)-1)&MID(F62,FIND(" ",F62)+1,1)) -> 7306C | E62: =IFERROR(IF(_xlfn.XMATCH(D62,'Rent Roll - RPM'!$B$3:$B$60,0,1)>0,"Match","No Match"),"No Match") -> Match | F62: 7306 Corey Rushing Lane | G62: =_xlfn.XLOOKUP(D62,'Rent Roll - RPM'!$B$3:$B$60,'Rent Roll - RPM'!$D$3:$D$60,0) -> Williams, Anthony | H62: 1 | I62: B3 | J62: Mallard | K62: 3 Bed | L62: 1685 | M62: 2 | N62: Complete | O62: Leased | P62: 46111 | Q62: 46143 | R62: =_xlfn.XLOOKUP(D62,'Rent Roll - RPM'!$B$3:$B$60,'Rent Roll - RPM'!$S$3:$S$60,"") -> 46568 | S62: 2750 | T62: =S62/L62 -> 1.6320475
A63: 1 | B63: 23 | C63: 82 | D63: =IF(ISNUMBER(SEARCH("Bobby Meadow",F63)),LEFT(F63,FIND(" ",F63)-1)&"M",LEFT(F63,FIND(" ",F63)-1)&MID(F63,FIND(" ",F63)+1,1)) -> 7435H | E63: =IFERROR(IF(_xlfn.XMATCH(D63,'Rent Roll - RPM'!$B$3:$B$60,0,1)>0,"Match","No Match"),"No Match") -> Match | F63: 7435 Hadley Meadow Lane | G63: =_xlfn.XLOOKUP(D63,'Rent Roll - RPM'!$B$3:$B$60,'Rent Roll - RPM'!$D$3:$D$60,0) -> Gonzalez, Ernesto | H63: 1 | I63: C3 | J63: Falcon | K63: 3 Bed | L63: 1909 | M63: 5 | N63: 45991 | O63: Tenant Occupied | P63: 46104 | Q63: 46108 | R63: =_xlfn.XLOOKUP(D63,'Rent Roll - RPM'!$B$3:$B$60,'Rent Roll - RPM'!$S$3:$S$60,"") -> 46564 | S63: 3150 | T63: =S63/L63 -> 1.6500786
A64: 2 | B64: 13 | C64: 58 | D64: =IF(ISNUMBER(SEARCH("Bobby Meadow",F64)),LEFT(F64,FIND(" ",F64)-1)&"M",LEFT(F64,FIND(" ",F64)-1)&MID(F64,FIND(" ",F64)+1,1)) -> 7431L | E64: =IFERROR(IF(_xlfn.XMATCH(D64,'Rent Roll - RPM'!$B$3:$B$60,0,1)>0,"Match","No Match"),"No Match") -> Match | F64: 7431 Leighton Meadow Lane | G64: =_xlfn.XLOOKUP(D64,'Rent Roll - RPM'!$B$3:$B$60,'Rent Roll - RPM'!$D$3:$D$60,0) -> Jones, Jillian | I64: E1 | J64: Sparrow | K64: 2 Bed | L64: 1635 | M64: 3 | N64: Complete | O64: Tenant Occupied | P64: 46097 | Q64: =_xlfn.XLOOKUP($D64,'Rent Roll - RPM'!$B$3:$B$60,'Rent Roll - RPM'!$R$3:$R$60,"") -> 46127 | R64: =_xlfn.XLOOKUP(D64,'Rent Roll - RPM'!$B$3:$B$60,'Rent Roll - RPM'!$S$3:$S$60,"") -> 46521 | S64: 2650 | T64: =S64/L64 -> 1.6207951
A65: 1 | B65: 47 | C65: 28 | D65: =IF(ISNUMBER(SEARCH("Bobby Meadow",F65)),LEFT(F65,FIND(" ",F65)-1)&"M",LEFT(F65,FIND(" ",F65)-1)&MID(F65,FIND(" ",F65)+1,1)) -> 22013L | E65: =IFERROR(IF(_xlfn.XMATCH(D65,'Rent Roll - RPM'!$B$3:$B$60,0,1)>0,"Match","No Match"),"No Match") -> Match | F65: 22013 Lesley Grove Lane | G65: =_xlfn.XLOOKUP(D65,'Rent Roll - RPM'!$B$3:$B$60,'Rent Roll - RPM'!$D$3:$D$60,0) -> Ajah, Grace | I65: F1 | J65: Raven | K65: 3 Bed | L65: 1852 | M65: 2 | N65: Complete | O65: Tenant Occupied | P65: 46097 | Q65: =_xlfn.XLOOKUP($D65,'Rent Roll - RPM'!$B$3:$B$60,'Rent Roll - RPM'!$R$3:$R$60,"") -> 46111 | R65: =_xlfn.XLOOKUP(D65,'Rent Roll - RPM'!$B$3:$B$60,'Rent Roll - RPM'!$S$3:$S$60,"") -> 46506 | S65: 2950 | T65: =S65/L65 -> 1.5928726
A66: 1 | B66: 4 | C66: 108 | D66: =IF(ISNUMBER(SEARCH("Bobby Meadow",F66)),LEFT(F66,FIND(" ",F66)-1)&"M",LEFT(F66,FIND(" ",F66)-1)&MID(F66,FIND(" ",F66)+1,1)) -> 21902F | E66: =IFERROR(IF(_xlfn.XMATCH(D66,'Rent Roll - RPM'!$B$3:$B$60,0,1)>0,"Match","No Match"),"No Match") -> Match | F66: 21902 Ferguson Meadow Lane | G66: =_xlfn.XLOOKUP(D66,'Rent Roll - RPM'!$B$3:$B$60,'Rent Roll - RPM'!$D$3:$D$60,0) -> Ogunjimi, Oladeji | I66: F1 | J66: Raven | K66: 3 Bed | L66: 1852 | M66: 6 | N66: 46006 | O66: Tenant Occupied | P66: =_xlfn.XLOOKUP(D66,'Rent Roll - RPM'!$B$3:$B$60,'Rent Roll - RPM'!$Q$3:$Q$60,"") -> 46084 | Q66: =_xlfn.XLOOKUP($D66,'Rent Roll - RPM'!$B$3:$B$60,'Rent Roll - RPM'!$R$3:$R$60,"") -> 46094 | R66: =_xlfn.XLOOKUP(D66,'Rent Roll - RPM'!$B$3:$B$60,'Rent Roll - RPM'!$S$3:$S$60,"") -> 46489 | S66: 2950 | T66: =S66/L66 -> 1.5928726
A67: 3 | B67: 12 | C67: 36 | D67: =IF(ISNUMBER(SEARCH("Bobby Meadow",F67)),LEFT(F67,FIND(" ",F67)-1)&"M",LEFT(F67,FIND(" ",F67)-1)&MID(F67,FIND(" ",F67)+1,1)) -> 7322C | E67: =IFERROR(IF(_xlfn.XMATCH(D67,'Rent Roll - RPM'!$B$3:$B$60,0,1)>0,"Match","No Match"),"No Match") -> Match | F67: 7322 Corey Rushing Lane | G67: =_xlfn.XLOOKUP(D67,'Rent Roll - RPM'!$B$3:$B$60,'Rent Roll - RPM'!$D$3:$D$60,0) -> Wilson, Nicholas | I67: D2 | J67: Phoenix | K67: 4 Bed | L67: 2431 | M67: 2 | N67: Complete | O67: Tenant Occupied | P67: =_xlfn.XLOOKUP(D67,'Rent Roll - RPM'!$B$3:$B$60,'Rent Roll - RPM'!$Q$3:$Q$60,"") -> 46082 | Q67: =_xlfn.XLOOKUP($D67,'Rent Roll - RPM'!$B$3:$B$60,'Rent Roll - RPM'!$R$3:$R$60,"") -> 46094 | R67: =_xlfn.XLOOKUP(D67,'Rent Roll - RPM'!$B$3:$B$60,'Rent Roll - RPM'!$S$3:$S$60,"") -> 46489 | S67: 3600 | T67: =S67/L67 -> 1.4808721
A68: 1 | B68: 17 | C68: 87 | D68: =IF(ISNUMBER(SEARCH("Bobby Meadow",F68)),LEFT(F68,FIND(" ",F68)-1)&"M",LEFT(F68,FIND(" ",F68)-1)&MID(F68,FIND(" ",F68)+1,1)) -> 7411H | E68: =IFERROR(IF(_xlfn.XMATCH(D68,'Rent Roll - RPM'!$B$3:$B$60,0,1)>0,"Match","No Match"),"No Match") -> Match | F68: 7411 Hadley Meadow Lane | G68: =_xlfn.XLOOKUP(D68,'Rent Roll - RPM'!$B$3:$B$60,'Rent Roll - RPM'!$D$3:$D$60,0) -> Contreras, Kristina | I68: F2 | J68: Raven | K68: 3 Bed | L68: 1852 | M68: 5 | N68: 45991 | O68: Tenant Occupied | P68: =_xlfn.XLOOKUP(D68,'Rent Roll - RPM'!$B$3:$B$60,'Rent Roll - RPM'!$Q$3:$Q$60,"") -> 46064 | Q68: =_xlfn.XLOOKUP($D68,'Rent Roll - RPM'!$B$3:$B$60,'Rent Roll - RPM'!$R$3:$R$60,"") -> 46073 | R68: =_xlfn.XLOOKUP(D68,'Rent Roll - RPM'!$B$3:$B$60,'Rent Roll - RPM'!$S$3:$S$60,"") -> 46526 | S68: 2950 | T68: =S68/L68 -> 1.5928726
A69: 2 | B69: 15 | C69: 91 | D69: =IF(ISNUMBER(SEARCH("Bobby Meadow",F69)),LEFT(F69,FIND(" ",F69)-1)&"M",LEFT(F69,FIND(" ",F69)-1)&MID(F69,FIND(" ",F69)+1,1)) -> 7426H | E69: =IFERROR(IF(_xlfn.XMATCH(D69,'Rent Roll - RPM'!$B$3:$B$60,0,1)>0,"Match","No Match"),"No Match") -> Match | F69: 7426 Hadley Meadow Lane | G69: =_xlfn.XLOOKUP(D69,'Rent Roll - RPM'!$B$3:$B$60,'Rent Roll - RPM'!$D$3:$D$60,0) -> Kotun, Fatimah | I69: B1 | J69: Mallard | K69: 3 Bed | L69: 1685 | M69: 5 | N69: 45991 | O69: Tenant Occupied | P69: =_xlfn.XLOOKUP(D69,'Rent Roll - RPM'!$B$3:$B$60,'Rent Roll - RPM'!$Q$3:$Q$60,"") -> 46062 | Q69: =_xlfn.XLOOKUP($D69,'Rent Roll - RPM'!$B$3:$B$60,'Rent Roll - RPM'!$R$3:$R$60,"") -> 46073 | R69: =_xlfn.XLOOKUP(D69,'Rent Roll - RPM'!$B$3:$B$60,'Rent Roll - RPM'!$S$3:$S$60,"") -> 46526 | S69: 2750 | T69: =S69/L69 -> 1.6320475
A70: 1 | B70: 10 | C70: 102 | D70: =IF(ISNUMBER(SEARCH("Bobby Meadow",F70)),LEFT(F70,FIND(" ",F70)-1)&"M",LEFT(F70,FIND(" ",F70)-1)&MID(F70,FIND(" ",F70)+1,1)) -> 7323H | E70: =IFERROR(IF(_xlfn.XMATCH(D70,'Rent Roll - RPM'!$B$3:$B$60,0,1)>0,"Match","No Match"),"No Match") -> Match | F70: 7323 Hadley Meadow Lane | G70: =_xlfn.XLOOKUP(D70,'Rent Roll - RPM'!$B$3:$B$60,'Rent Roll - RPM'!$D$3:$D$60,0) -> Onyedebelu, Chimdimma | I70: B1 | J70: Mallard | K70: 3 Bed | L70: 1685 | M70: 6 | N70: 46006 | O70: Tenant Occupied | P70: 46054 | Q70: =_xlfn.XLOOKUP($D70,'Rent Roll - RPM'!$B$3:$B$60,'Rent Roll - RPM'!$R$3:$R$60,"") -> 46108 | R70: =_xlfn.XLOOKUP(D70,'Rent Roll - RPM'!$B$3:$B$60,'Rent Roll - RPM'!$S$3:$S$60,"") -> 46564 | S70: 2750 | T70: =S70/L70 -> 1.6320475
A71: 3 | B71: 21 | C71: 65 | D71: =IF(ISNUMBER(SEARCH("Bobby Meadow",F71)),LEFT(F71,FIND(" ",F71)-1)&"M",LEFT(F71,FIND(" ",F71)-1)&MID(F71,FIND(" ",F71)+1,1)) -> 7326L | E71: =IFERROR(IF(_xlfn.XMATCH(D71,'Rent Roll - RPM'!$B$3:$B$60,0,1)>0,"Match","No Match"),"No Match") -> Match | F71: 7326 Leighton Meadow Lane | G71: =_xlfn.XLOOKUP(D71,'Rent Roll - RPM'!$B$3:$B$60,'Rent Roll - RPM'!$D$3:$D$60,0) -> Chukwujiwu, Henry | I71: B1 | J71: Mallard | K71: 3 Bed | L71: 1685 | M71: 4 | N71: 45961 | O71: Tenant Occupied | P71: =_xlfn.XLOOKUP(D71,'Rent Roll - RPM'!$B$3:$B$60,'Rent Roll - RPM'!$Q$3:$Q$60,"") -> 46052 | Q71: =_xlfn.XLOOKUP($D71,'Rent Roll - RPM'!$B$3:$B$60,'Rent Roll - RPM'!$R$3:$R$60,"") -> 46053 | R71: =_xlfn.XLOOKUP(D71,'Rent Roll - RPM'!$B$3:$B$60,'Rent Roll - RPM'!$S$3:$S$60,"") -> 46446 | S71: 2750 | T71: =S71/L71 -> 1.6320475
A72: 3 | B72: 3 | C72: 16 | D72: =IF(ISNUMBER(SEARCH("Bobby Meadow",F72)),LEFT(F72,FIND(" ",F72)-1)&"M",LEFT(F72,FIND(" ",F72)-1)&MID(F72,FIND(" ",F72)+1,1)) -> 22019F | E72: =IFERROR(IF(_xlfn.XMATCH(D72,'Rent Roll - RPM'!$B$3:$B$60,0,1)>0,"Match","No Match"),"No Match") -> Match | F72: 22019 Ferguson Meadow Lane | G72: =_xlfn.XLOOKUP(D72,'Rent Roll - RPM'!$B$3:$B$60,'Rent Roll - RPM'!$D$3:$D$60,0) -> Ramazani, Mahdi | I72: E3 | J72: Sparrow | K72: 2 Bed | L72: 1635 | M72: 1 | N72: Complete | O72: Tenant Occupied | P72: =_xlfn.XLOOKUP(D72,'Rent Roll - RPM'!$B$3:$B$60,'Rent Roll - RPM'!$Q$3:$Q$60,"") -> 46052 | Q72: =_xlfn.XLOOKUP($D72,'Rent Roll - RPM'!$B$3:$B$60,'Rent Roll - RPM'!$R$3:$R$60,"") -> 46063 | R72: =_xlfn.XLOOKUP(D72,'Rent Roll - RPM'!$B$3:$B$60,'Rent Roll - RPM'!$S$3:$S$60,"") -> 46516 | S72: 2650 | T72: =S72/L72 -> 1.6207951
A73: 1 | B73: 28 | C73: 57 | D73: =IF(ISNUMBER(SEARCH("Bobby Meadow",F73)),LEFT(F73,FIND(" ",F73)-1)&"M",LEFT(F73,FIND(" ",F73)-1)&MID(F73,FIND(" ",F73)+1,1)) -> 21923M | E73: =IFERROR(IF(_xlfn.XMATCH(D73,'Rent Roll - RPM'!$B$3:$B$60,0,1)>0,"Match","No Match"),"No Match") -> Match | F73: 21923 Bobby Meadow Lane | G73: =_xlfn.XLOOKUP(D73,'Rent Roll - RPM'!$B$3:$B$60,'Rent Roll - RPM'!$D$3:$D$60,0) -> Buchanan, Britany | I73: E1 | J73: Sparrow | K73: 2 Bed | L73: 1635 | M73: 3 | N73: Complete | O73: Tenant Occupied | P73: =_xlfn.XLOOKUP(D73,'Rent Roll - RPM'!$B$3:$B$60,'Rent Roll - RPM'!$Q$3:$Q$60,"") -> 46044 | Q73: =_xlfn.XLOOKUP($D73,'Rent Roll - RPM'!$B$3:$B$60,'Rent Roll - RPM'!$R$3:$R$60,"") -> 46080 | R73: =_xlfn.XLOOKUP(D73,'Rent Roll - RPM'!$B$3:$B$60,'Rent Roll - RPM'!$S$3:$S$60,"") -> 46472 | S73: 2650 | T73: =S73/L73 -> 1.6207951
A74: 1 | B74: 3 | C74: 109 | D74: =IF(ISNUMBER(SEARCH("Bobby Meadow",F74)),LEFT(F74,FIND(" ",F74)-1)&"M",LEFT(F74,FIND(" ",F74)-1)&MID(F74,FIND(" ",F74)+1,1)) -> 21906F | E74: =IFERROR(IF(_xlfn.XMATCH(D74,'Rent Roll - RPM'!$B$3:$B$60,0,1)>0,"Match","No Match"),"No Match") -> Match | F74: 21906 Ferguson Meadow Lane | G74: =_xlfn.XLOOKUP(D74,'Rent Roll - RPM'!$B$3:$B$60,'Rent Roll - RPM'!$D$3:$D$60,0) -> Ogembo, Samantha | I74: B3 | J74: Mallard | K74: 3 Bed | L74: 1685 | M74: 6 | N74: 46006 | O74: Tenant Occupied | P74: =_xlfn.XLOOKUP(D74,'Rent Roll - RPM'!$B$3:$B$60,'Rent Roll - RPM'!$Q$3:$Q$60,"") -> 46041 | Q74: =_xlfn.XLOOKUP($D74,'Rent Roll - RPM'!$B$3:$B$60,'Rent Roll - RPM'!$R$3:$R$60,"") -> 46085 | R74: =_xlfn.XLOOKUP(D74,'Rent Roll - RPM'!$B$3:$B$60,'Rent Roll - RPM'!$S$3:$S$60,"") -> 46541 | S74: 2750 | T74: =S74/L74 -> 1.6320475
A75: 2 | B75: 22 | C75: 112 | D75: =IF(ISNUMBER(SEARCH("Bobby Meadow",F75)),LEFT(F75,FIND(" ",F75)-1)&"M",LEFT(F75,FIND(" ",F75)-1)&MID(F75,FIND(" ",F75)+1,1)) -> 7338H | E75: =IFERROR(IF(_xlfn.XMATCH(D75,'Rent Roll - RPM'!$B$3:$B$60,0,1)>0,"Match","No Match"),"No Match") -> Match | F75: 7338 Hadley Meadow Lane | G75: =_xlfn.XLOOKUP(D75,'Rent Roll - RPM'!$B$3:$B$60,'Rent Roll - RPM'!$D$3:$D$60,0) -> Elborno, Lana | I75: B1 | J75: Mallard | K75: 3 Bed | L75: 1685 | M75: 6 | N75: 46006 | O75: Tenant Occupied | P75: =_xlfn.XLOOKUP(D75,'Rent Roll - RPM'!$B$3:$B$60,'Rent Roll - RPM'!$Q$3:$Q$60,"") -> 46039 | Q75: =_xlfn.XLOOKUP($D75,'Rent Roll - RPM'!$B$3:$B$60,'Rent Roll - RPM'!$R$3:$R$60,"") -> 46067 | R75: =_xlfn.XLOOKUP(D75,'Rent Roll - RPM'!$B$3:$B$60,'Rent Roll - RPM'!$S$3:$S$60,"") -> 46459 | S75: 2750 | T75: =S75/L75 -> 1.6320475
A76: 1 | B76: 57 | C76: 11 | D76: =IF(ISNUMBER(SEARCH("Bobby Meadow",F76)),LEFT(F76,FIND(" ",F76)-1)&"M",LEFT(F76,FIND(" ",F76)-1)&MID(F76,FIND(" ",F76)+1,1)) -> 22042F | E76: =IFERROR(IF(_xlfn.XMATCH(D76,'Rent Roll - RPM'!$B$3:$B$60,0,1)>0,"Match","No Match"),"No Match") -> Match | F76: 22042 Ferguson Meadow Lane | G76: =_xlfn.XLOOKUP(D76,'Rent Roll - RPM'!$B$3:$B$60,'Rent Roll - RPM'!$D$3:$D$60,0) -> Casiano Hernandez, Beatriz | I76: F2 | J76: Raven | K76: 3 Bed | L76: 1852 | M76: 1 | N76: Complete | O76: Tenant Occupied | P76: =_xlfn.XLOOKUP(D76,'Rent Roll - RPM'!$B$3:$B$60,'Rent Roll - RPM'!$Q$3:$Q$60,"") -> 46035 | Q76: =_xlfn.XLOOKUP($D76,'Rent Roll - RPM'!$B$3:$B$60,'Rent Roll - RPM'!$R$3:$R$60,"") -> 46037 | R76: =_xlfn.XLOOKUP(D76,'Rent Roll - RPM'!$B$3:$B$60,'Rent Roll - RPM'!$S$3:$S$60,"") -> 46432 | S76: 2950 | T76: =S76/L76 -> 1.5928726
A77: 1 | B77: 24 | C77: 81 | D77: =IF(ISNUMBER(SEARCH("Bobby Meadow",F77)),LEFT(F77,FIND(" ",F77)-1)&"M",LEFT(F77,FIND(" ",F77)-1)&MID(F77,FIND(" ",F77)+1,1)) -> 21903M | E77: =IFERROR(IF(_xlfn.XMATCH(D77,'Rent Roll - RPM'!$B$3:$B$60,0,1)>0,"Match","No Match"),"No Match") -> Match | F77: 21903 Bobby Meadow Lane | G77: =_xlfn.XLOOKUP(D77,'Rent Roll - RPM'!$B$3:$B$60,'Rent Roll - RPM'!$D$3:$D$60,0) -> Gutierrez, Erica | I77: F2 | J77: Raven | K77: 3 Bed | L77: 1852 | M77: 5 | N77: 45991 | O77: Tenant Occupied | P77: =_xlfn.XLOOKUP(D77,'Rent Roll - RPM'!$B$3:$B$60,'Rent Roll - RPM'!$Q$3:$Q$60,"") -> 46030 | Q77: =_xlfn.XLOOKUP($D77,'Rent Roll - RPM'!$B$3:$B$60,'Rent Roll - RPM'!$R$3:$R$60,"") -> 46076 | R77: =_xlfn.XLOOKUP(D77,'Rent Roll - RPM'!$B$3:$B$60,'Rent Roll - RPM'!$S$3:$S$60,"") -> 46468 | S77: 2950 | T77: =S77/L77 -> 1.5928726
A78: 1 | B78: 18 | C78: 86 | D78: =IF(ISNUMBER(SEARCH("Bobby Meadow",F78)),LEFT(F78,FIND(" ",F78)-1)&"M",LEFT(F78,FIND(" ",F78)-1)&MID(F78,FIND(" ",F78)+1,1)) -> 7415H | E78: =IFERROR(IF(_xlfn.XMATCH(D78,'Rent Roll - RPM'!$B$3:$B$60,0,1)>0,"Match","No Match"),"No Match") -> Match | F78: 7415 Hadley Meadow Lane | G78: =_xlfn.XLOOKUP(D78,'Rent Roll - RPM'!$B$3:$B$60,'Rent Roll - RPM'!$D$3:$D$60,0) -> King, Tristan | I78: B3 | J78: Mallard | K78: 3 Bed | L78: 1685 | M78: 5 | N78: 45991 | O78: Tenant Occupied | P78: =_xlfn.XLOOKUP(D78,'Rent Roll - RPM'!$B$3:$B$60,'Rent Roll - RPM'!$Q$3:$Q$60,"") -> 46025 | Q78: =_xlfn.XLOOKUP($D78,'Rent Roll - RPM'!$B$3:$B$60,'Rent Roll - RPM'!$R$3:$R$60,"") -> 46037 | R78: =_xlfn.XLOOKUP(D78,'Rent Roll - RPM'!$B$3:$B$60,'Rent Roll - RPM'!$S$3:$S$60,"") -> 46432 | S78: 2750 | T78: =S78/L78 -> 1.6320475
A79: 2 | B79: 2 | C79: 69 | D79: =IF(ISNUMBER(SEARCH("Bobby Meadow",F79)),LEFT(F79,FIND(" ",F79)-1)&"M",LEFT(F79,FIND(" ",F79)-1)&MID(F79,FIND(" ",F79)+1,1)) -> 7307L | E79: =IFERROR(IF(_xlfn.XMATCH(D79,'Rent Roll - RPM'!$B$3:$B$60,0,1)>0,"Match","No Match"),"No Match") -> Match | F79: 7307 Leighton Meadow Lane | G79: =_xlfn.XLOOKUP(D79,'Rent Roll - RPM'!$B$3:$B$60,'Rent Roll - RPM'!$D$3:$D$60,0) -> Scott, Jeaneen | I79: B2 | J79: Mallard | K79: 3 Bed | L79: 1685 | M79: 4 | N79: 45961 | O79: Tenant Occupied | P79: =_xlfn.XLOOKUP(D79,'Rent Roll - RPM'!$B$3:$B$60,'Rent Roll - RPM'!$Q$3:$Q$60,"") -> 46025 | Q79: =_xlfn.XLOOKUP($D79,'Rent Roll - RPM'!$B$3:$B$60,'Rent Roll - RPM'!$R$3:$R$60,"") -> 46032 | R79: =_xlfn.XLOOKUP(D79,'Rent Roll - RPM'!$B$3:$B$60,'Rent Roll - RPM'!$S$3:$S$60,"") -> 46486 | S79: 2750 | T79: =S79/L79 -> 1.6320475
A80: 1 | B80: 31 | C80: 54 | D80: =IF(ISNUMBER(SEARCH("Bobby Meadow",F80)),LEFT(F80,FIND(" ",F80)-1)&"M",LEFT(F80,FIND(" ",F80)-1)&MID(F80,FIND(" ",F80)+1,1)) -> 21935M | E80: =IFERROR(IF(_xlfn.XMATCH(D80,'Rent Roll - RPM'!$B$3:$B$60,0,1)>0,"Match","No Match"),"No Match") -> Match | F80: 21935 Bobby Meadow Lane | G80: =_xlfn.XLOOKUP(D80,'Rent Roll - RPM'!$B$3:$B$60,'Rent Roll - RPM'!$D$3:$D$60,0) -> Akamimo, Vivian | I80: B3 | J80: Mallard | K80: 3 Bed | L80: 1685 | M80: 3 | N80: Complete | O80: Tenant Occupied | P80: =_xlfn.XLOOKUP(D80,'Rent Roll - RPM'!$B$3:$B$60,'Rent Roll - RPM'!$Q$3:$Q$60,"") -> 46025 | Q80: =_xlfn.XLOOKUP($D80,'Rent Roll - RPM'!$B$3:$B$60,'Rent Roll - RPM'!$R$3:$R$60,"") -> 46028 | R80: =_xlfn.XLOOKUP(D80,'Rent Roll - RPM'!$B$3:$B$60,'Rent Roll - RPM'!$S$3:$S$60,"") -> 46482 | S80: 2750 | T80: =S80/L80 -> 1.6320475
A81: 2 | B81: 10 | C81: 61 | D81: =IF(ISNUMBER(SEARCH("Bobby Meadow",F81)),LEFT(F81,FIND(" ",F81)-1)&"M",LEFT(F81,FIND(" ",F81)-1)&MID(F81,FIND(" ",F81)+1,1)) -> 7419L | E81: =IFERROR(IF(_xlfn.XMATCH(D81,'Rent Roll - RPM'!$B$3:$B$60,0,1)>0,"Match","No Match"),"No Match") -> Match | F81: 7419 Leighton Meadow Lane | G81: =_xlfn.XLOOKUP(D81,'Rent Roll - RPM'!$B$3:$B$60,'Rent Roll - RPM'!$D$3:$D$60,0) -> Draper, Blake | I81: B1 | J81: Mallard | K81: 3 Bed | L81: 1685 | M81: 3 | N81: Complete | O81: Tenant Occupied | P81: =_xlfn.XLOOKUP(D81,'Rent Roll - RPM'!$B$3:$B$60,'Rent Roll - RPM'!$Q$3:$Q$60,"") -> 46013 | Q81: =_xlfn.XLOOKUP($D81,'Rent Roll - RPM'!$B$3:$B$60,'Rent Roll - RPM'!$R$3:$R$60,"") -> 46018 | R81: =_xlfn.XLOOKUP(D81,'Rent Roll - RPM'!$B$3:$B$60,'Rent Roll - RPM'!$S$3:$S$60,"") -> 46413 | S81: 2750 | T81: =S81/L81 -> 1.6320475
A82: 3 | B82: 6 | C82: 19 | D82: =IF(ISNUMBER(SEARCH("Bobby Meadow",F82)),LEFT(F82,FIND(" ",F82)-1)&"M",LEFT(F82,FIND(" ",F82)-1)&MID(F82,FIND(" ",F82)+1,1)) -> 22031F | E82: =IFERROR(IF(_xlfn.XMATCH(D82,'Rent Roll - RPM'!$B$3:$B$60,0,1)>0,"Match","No Match"),"No Match") -> Match | F82: 22031 Ferguson Meadow Lane | G82: =_xlfn.XLOOKUP(D82,'Rent Roll - RPM'!$B$3:$B$60,'Rent Roll - RPM'!$D$3:$D$60,0) -> Adegbuyi, Taiwo | I82: B3 | J82: Mallard | K82: 3 Bed | L82: 1685 | M82: 1 | N82: Complete | O82: Tenant Occupied | P82: =_xlfn.XLOOKUP(D82,'Rent Roll - RPM'!$B$3:$B$60,'Rent Roll - RPM'!$Q$3:$Q$60,"") -> 46013 | Q82: =_xlfn.XLOOKUP($D82,'Rent Roll - RPM'!$B$3:$B$60,'Rent Roll - RPM'!$R$3:$R$60,"") -> 46014 | R82: =_xlfn.XLOOKUP(D82,'Rent Roll - RPM'!$B$3:$B$60,'Rent Roll - RPM'!$S$3:$S$60,"") -> 46409 | S82: 2750 | T82: =S82/L82 -> 1.6320475
A83: 3 | B83: 7 | C83: 20 | D83: =IF(ISNUMBER(SEARCH("Bobby Meadow",F83)),LEFT(F83,FIND(" ",F83)-1)&"M",LEFT(F83,FIND(" ",F83)-1)&MID(F83,FIND(" ",F83)+1,1)) -> 22035F | E83: =IFERROR(IF(_xlfn.XMATCH(D83,'Rent Roll - RPM'!$B$3:$B$60,0,1)>0,"Match","No Match"),"No Match") -> Match | F83: 22035 Ferguson Meadow Lane | G83: =_xlfn.XLOOKUP(D83,'Rent Roll - RPM'!$B$3:$B$60,'Rent Roll - RPM'!$D$3:$D$60,0) -> Isikwe, Sheela | I83: B1 | J83: Mallard | K83: 3 Bed | L83: 1685 | M83: 1 | N83: Complete | O83: Tenant Occupied | P83: =_xlfn.XLOOKUP(D83,'Rent Roll - RPM'!$B$3:$B$60,'Rent Roll - RPM'!$Q$3:$Q$60,"") -> 45994 | Q83: =_xlfn.XLOOKUP($D83,'Rent Roll - RPM'!$B$3:$B$60,'Rent Roll - RPM'!$R$3:$R$60,"") -> 46003 | R83: =_xlfn.XLOOKUP(D83,'Rent Roll - RPM'!$B$3:$B$60,'Rent Roll - RPM'!$S$3:$S$60,"") -> 46398 | S83: 2750 | T83: =S83/L83 -> 1.6320475
A84: 3 | B84: 22 | C84: 66 | D84: =IF(ISNUMBER(SEARCH("Bobby Meadow",F84)),LEFT(F84,FIND(" ",F84)-1)&"M",LEFT(F84,FIND(" ",F84)-1)&MID(F84,FIND(" ",F84)+1,1)) -> 7330L | E84: =IFERROR(IF(_xlfn.XMATCH(D84,'Rent Roll - RPM'!$B$3:$B$60,0,1)>0,"Match","No Match"),"No Match") -> Match | F84: 7330 Leighton Meadow Lane | G84: =_xlfn.XLOOKUP(D84,'Rent Roll - RPM'!$B$3:$B$60,'Rent Roll - RPM'!$D$3:$D$60,0) -> Nwagbosoma, Ikechukwu | I84: A3 | J84: Canary | K84: 2 Bed | L84: 1425 | M84: 4 | N84: 45961 | O84: Tenant Occupied | P84: =_xlfn.XLOOKUP(D84,'Rent Roll - RPM'!$B$3:$B$60,'Rent Roll - RPM'!$Q$3:$Q$60,"") -> 45993 | Q84: =_xlfn.XLOOKUP($D84,'Rent Roll - RPM'!$B$3:$B$60,'Rent Roll - RPM'!$R$3:$R$60,"") -> 45997 | R84: =_xlfn.XLOOKUP(D84,'Rent Roll - RPM'!$B$3:$B$60,'Rent Roll - RPM'!$S$3:$S$60,"") -> 46392 | S84: 2450 | T84: =S84/L84 -> 1.7192982
A85: 1 | B85: 5 | C85: 107 | D85: =IF(ISNUMBER(SEARCH("Bobby Meadow",F85)),LEFT(F85,FIND(" ",F85)-1)&"M",LEFT(F85,FIND(" ",F85)-1)&MID(F85,FIND(" ",F85)+1,1)) -> 7303H | E85: =IFERROR(IF(_xlfn.XMATCH(D85,'Rent Roll - RPM'!$B$3:$B$60,0,1)>0,"Match","No Match"),"No Match") -> Match | F85: 7303 Hadley Meadow Lane | G85: =_xlfn.XLOOKUP(D85,'Rent Roll - RPM'!$B$3:$B$60,'Rent Roll - RPM'!$D$3:$D$60,0) -> Akoma, Ijeoma | I85: F3 | J85: Raven | K85: 3 Bed | L85: 1852 | M85: 6 | N85: 46006 | O85: Tenant Occupied | P85: =_xlfn.XLOOKUP(D85,'Rent Roll - RPM'!$B$3:$B$60,'Rent Roll - RPM'!$Q$3:$Q$60,"") -> 45992 | Q85: =_xlfn.XLOOKUP($D85,'Rent Roll - RPM'!$B$3:$B$60,'Rent Roll - RPM'!$R$3:$R$60,"") -> 46037 | R85: =_xlfn.XLOOKUP(D85,'Rent Roll - RPM'!$B$3:$B$60,'Rent Roll - RPM'!$S$3:$S$60,"") -> 46432 | S85: 2950 | T85: =S85/L85 -> 1.5928726
A86: 3 | B86: 17 | C86: 41 | D86: =IF(ISNUMBER(SEARCH("Bobby Meadow",F86)),LEFT(F86,FIND(" ",F86)-1)&"M",LEFT(F86,FIND(" ",F86)-1)&MID(F86,FIND(" ",F86)+1,1)) -> 7302C | E86: =IFERROR(IF(_xlfn.XMATCH(D86,'Rent Roll - RPM'!$B$3:$B$60,0,1)>0,"Match","No Match"),"No Match") -> Match | F86: 7302 Corey Rushing Lane | G86: =_xlfn.XLOOKUP(D86,'Rent Roll - RPM'!$B$3:$B$60,'Rent Roll - RPM'!$D$3:$D$60,0) -> Owens, Rachel | I86: B1 | J86: Mallard | K86: 3 Bed | L86: 1685 | M86: 2 | N86: Complete | O86: Tenant Occupied | P86: =_xlfn.XLOOKUP(D86,'Rent Roll - RPM'!$B$3:$B$60,'Rent Roll - RPM'!$Q$3:$Q$60,"") -> 45966 | Q86: =_xlfn.XLOOKUP($D86,'Rent Roll - RPM'!$B$3:$B$60,'Rent Roll - RPM'!$R$3:$R$60,"") -> 45983 | R86: =_xlfn.XLOOKUP(D86,'Rent Roll - RPM'!$B$3:$B$60,'Rent Roll - RPM'!$S$3:$S$60,"") -> 46377 | S86: 2750 | T86: =S86/L86 -> 1.6320475
A87: 1 | B87: 50 | C87: 25 | D87: =IF(ISNUMBER(SEARCH("Bobby Meadow",F87)),LEFT(F87,FIND(" ",F87)-1)&"M",LEFT(F87,FIND(" ",F87)-1)&MID(F87,FIND(" ",F87)+1,1)) -> 22025L | E87: =IFERROR(IF(_xlfn.XMATCH(D87,'Rent Roll - RPM'!$B$3:$B$60,0,1)>0,"Match","No Match"),"No Match") -> Match | F87: 22025 Lesley Grove Lane | G87: =_xlfn.XLOOKUP(D87,'Rent Roll - RPM'!$B$3:$B$60,'Rent Roll - RPM'!$D$3:$D$60,0) -> Rush, Cody | I87: C1 | J87: Falcon | K87: 3 Bed | L87: 1909 | M87: 2 | N87: Complete | O87: Tenant Occupied | P87: =_xlfn.XLOOKUP(D87,'Rent Roll - RPM'!$B$3:$B$60,'Rent Roll - RPM'!$Q$3:$Q$60,"") -> 45961 | Q87: =_xlfn.XLOOKUP($D87,'Rent Roll - RPM'!$B$3:$B$60,'Rent Roll - RPM'!$R$3:$R$60,"") -> 45962 | R87: =_xlfn.XLOOKUP(D87,'Rent Roll - RPM'!$B$3:$B$60,'Rent Roll - RPM'!$S$3:$S$60,"") -> 46418 | S87: 3150 | T87: =S87/L87 -> 1.6500786
A88: 1 | B88: 34 | C88: 51 | D88: =IF(ISNUMBER(SEARCH("Bobby Meadow",F88)),LEFT(F88,FIND(" ",F88)-1)&"M",LEFT(F88,FIND(" ",F88)-1)&MID(F88,FIND(" ",F88)+1,1)) -> 21950M | E88: =IFERROR(IF(_xlfn.XMATCH(D88,'Rent Roll - RPM'!$B$3:$B$60,0,1)>0,"Match","No Match"),"No Match") -> Match | F88: 21950 Bobby Meadow Lane | G88: =_xlfn.XLOOKUP(D88,'Rent Roll - RPM'!$B$3:$B$60,'Rent Roll - RPM'!$D$3:$D$60,0) -> Thomas, C Yvette | I88: A1 | J88: Canary | K88: 2 Bed | L88: 1425 | M88: 3 | N88: Complete | O88: Tenant Occupied | P88: =_xlfn.XLOOKUP(D88,'Rent Roll - RPM'!$B$3:$B$60,'Rent Roll - RPM'!$Q$3:$Q$60,"") -> 45961 | Q88: =_xlfn.XLOOKUP($D88,'Rent Roll - RPM'!$B$3:$B$60,'Rent Roll - RPM'!$R$3:$R$60,"") -> 45999 | R88: =_xlfn.XLOOKUP(D88,'Rent Roll - RPM'!$B$3:$B$60,'Rent Roll - RPM'!$S$3:$S$60,"") -> 46394 | S88: 2450 | T88: =S88/L88 -> 1.7192982
A89: 2 | B89: 14 | C89: 90 | D89: =IF(ISNUMBER(SEARCH("Bobby Meadow",F89)),LEFT(F89,FIND(" ",F89)-1)&"M",LEFT(F89,FIND(" ",F89)-1)&MID(F89,FIND(" ",F89)+1,1)) -> 7430H | E89: =IFERROR(IF(_xlfn.XMATCH(D89,'Rent Roll - RPM'!$B$3:$B$60,0,1)>0,"Match","No Match"),"No Match") -> Match | F89: 7430 Hadley Meadow Lane | G89: =_xlfn.XLOOKUP(D89,'Rent Roll - RPM'!$B$3:$B$60,'Rent Roll - RPM'!$D$3:$D$60,0) -> Patel, Smit | I89: B2 | J89: Mallard | K89: 3 Bed | L89: 1685 | M89: 5 | N89: 45991 | O89: Tenant Occupied | P89: =_xlfn.XLOOKUP(D89,'Rent Roll - RPM'!$B$3:$B$60,'Rent Roll - RPM'!$Q$3:$Q$60,"") -> 45950 | Q89: =_xlfn.XLOOKUP($D89,'Rent Roll - RPM'!$B$3:$B$60,'Rent Roll - RPM'!$R$3:$R$60,"") -> 46029 | R89: =_xlfn.XLOOKUP(D89,'Rent Roll - RPM'!$B$3:$B$60,'Rent Roll - RPM'!$S$3:$S$60,"") -> 46424 | S89: 2750 | T89: =S89/L89 -> 1.6320475
A90: 1 | B90: 19 | C90: 85 | D90: =IF(ISNUMBER(SEARCH("Bobby Meadow",F90)),LEFT(F90,FIND(" ",F90)-1)&"M",LEFT(F90,FIND(" ",F90)-1)&MID(F90,FIND(" ",F90)+1,1)) -> 7419H | E90: =IFERROR(IF(_xlfn.XMATCH(D90,'Rent Roll - RPM'!$B$3:$B$60,0,1)>0,"Match","No Match"),"No Match") -> Match | F90: 7419 Hadley Meadow Lane | G90: =_xlfn.XLOOKUP(D90,'Rent Roll - RPM'!$B$3:$B$60,'Rent Roll - RPM'!$D$3:$D$60,0) -> Anjum, Sami | I90: B2 | J90: Mallard | K90: 3 Bed | L90: 1685 | M90: 5 | N90: 45991 | O90: Tenant Occupied | P90: =_xlfn.XLOOKUP(D90,'Rent Roll - RPM'!$B$3:$B$60,'Rent Roll - RPM'!$Q$3:$Q$60,"") -> 45950 | Q90: =_xlfn.XLOOKUP($D90,'Rent Roll - RPM'!$B$3:$B$60,'Rent Roll - RPM'!$R$3:$R$60,"") -> 46029 | R90: =_xlfn.XLOOKUP(D90,'Rent Roll - RPM'!$B$3:$B$60,'Rent Roll - RPM'!$S$3:$S$60,"") -> 46483 | S90: 2750 | T90: =S90/L90 -> 1.6320475
A91: 1 | B91: 26 | C91: 79 | D91: =IF(ISNUMBER(SEARCH("Bobby Meadow",F91)),LEFT(F91,FIND(" ",F91)-1)&"M",LEFT(F91,FIND(" ",F91)-1)&MID(F91,FIND(" ",F91)+1,1)) -> 21915M | E91: =IFERROR(IF(_xlfn.XMATCH(D91,'Rent Roll - RPM'!$B$3:$B$60,0,1)>0,"Match","No Match"),"No Match") -> Match | F91: 21915 Bobby Meadow Lane | G91: =_xlfn.XLOOKUP(D91,'Rent Roll - RPM'!$B$3:$B$60,'Rent Roll - RPM'!$D$3:$D$60,0) -> Hockaday, Gordon | I91: A1 | J91: Canary | K91: 2 Bed | L91: 1425 | M91: 5 | N91: 45991 | O91: Tenant Occupied | P91: =_xlfn.XLOOKUP(D91,'Rent Roll - RPM'!$B$3:$B$60,'Rent Roll - RPM'!$Q$3:$Q$60,"") -> 45950 | Q91: =_xlfn.XLOOKUP($D91,'Rent Roll - RPM'!$B$3:$B$60,'Rent Roll - RPM'!$R$3:$R$60,"") -> 45993 | R91: =_xlfn.XLOOKUP(D91,'Rent Roll - RPM'!$B$3:$B$60,'Rent Roll - RPM'!$S$3:$S$60,"") -> 46447 | S91: 2450 | T91: =S91/L91 -> 1.7192982
A92: 1 | B92: 56 | C92: 12 | D92: =IF(ISNUMBER(SEARCH("Bobby Meadow",F92)),LEFT(F92,FIND(" ",F92)-1)&"M",LEFT(F92,FIND(" ",F92)-1)&MID(F92,FIND(" ",F92)+1,1)) -> 22046F | E92: =IFERROR(IF(_xlfn.XMATCH(D92,'Rent Roll - RPM'!$B$3:$B$60,0,1)>0,"Match","No Match"),"No Match") -> Match | F92: 22046 Ferguson Meadow Lane | G92: =_xlfn.XLOOKUP(D92,'Rent Roll - RPM'!$B$3:$B$60,'Rent Roll - RPM'!$D$3:$D$60,0) -> Rivera, Jasmine | I92: B3 | J92: Mallard | K92: 3 Bed | L92: 1685 | M92: 1 | N92: Complete | O92: Tenant Occupied | P92: =_xlfn.XLOOKUP(D92,'Rent Roll - RPM'!$B$3:$B$60,'Rent Roll - RPM'!$Q$3:$Q$60,"") -> 45948 | Q92: =_xlfn.XLOOKUP($D92,'Rent Roll - RPM'!$B$3:$B$60,'Rent Roll - RPM'!$R$3:$R$60,"") -> 45985 | R92: =_xlfn.XLOOKUP(D92,'Rent Roll - RPM'!$B$3:$B$60,'Rent Roll - RPM'!$S$3:$S$60,"") -> 46379 | S92: 2750 | T92: =S92/L92 -> 1.6320475
A93: 1 | B93: 33 | C93: 52 | D93: =IF(ISNUMBER(SEARCH("Bobby Meadow",F93)),LEFT(F93,FIND(" ",F93)-1)&"M",LEFT(F93,FIND(" ",F93)-1)&MID(F93,FIND(" ",F93)+1,1)) -> 21954M | E93: =IFERROR(IF(_xlfn.XMATCH(D93,'Rent Roll - RPM'!$B$3:$B$60,0,1)>0,"Match","No Match"),"No Match") -> Match | F93: 21954 Bobby Meadow Lane | G93: =_xlfn.XLOOKUP(D93,'Rent Roll - RPM'!$B$3:$B$60,'Rent Roll - RPM'!$D$3:$D$60,0) -> Nwabuko, Nnenna | I93: B2 | J93: Mallard | K93: 3 Bed | L93: 1685 | M93: 3 | N93: Complete | O93: Tenant Occupied | P93: =_xlfn.XLOOKUP(D93,'Rent Roll - RPM'!$B$3:$B$60,'Rent Roll - RPM'!$Q$3:$Q$60,"") -> 45943 | Q93: =_xlfn.XLOOKUP($D93,'Rent Roll - RPM'!$B$3:$B$60,'Rent Roll - RPM'!$R$3:$R$60,"") -> 45965 | R93: =_xlfn.XLOOKUP(D93,'Rent Roll - RPM'!$B$3:$B$60,'Rent Roll - RPM'!$S$3:$S$60,"") -> 46359 | S93: 2750 | T93: =S93/L93 -> 1.6320475
A94: 1 | B94: 1 | C94: 111 | D94: =IF(ISNUMBER(SEARCH("Bobby Meadow",F94)),LEFT(F94,FIND(" ",F94)-1)&"M",LEFT(F94,FIND(" ",F94)-1)&MID(F94,FIND(" ",F94)+1,1)) -> 21914F | E94: =IFERROR(IF(_xlfn.XMATCH(D94,'Rent Roll - RPM'!$B$3:$B$60,0,1)>0,"Match","No Match"),"No Match") -> Match | F94: 21914 Ferguson Meadow Lane | G94: =_xlfn.XLOOKUP(D94,'Rent Roll - RPM'!$B$3:$B$60,'Rent Roll - RPM'!$D$3:$D$60,0) -> Smith, Audrey | I94: A1 | J94: Canary | K94: 2 Bed | L94: 1425 | M94: 6 | N94: 46006 | O94: Tenant Occupied | P94: =_xlfn.XLOOKUP(D94,'Rent Roll - RPM'!$B$3:$B$60,'Rent Roll - RPM'!$Q$3:$Q$60,"") -> 45943 | Q94: =_xlfn.XLOOKUP($D94,'Rent Roll - RPM'!$B$3:$B$60,'Rent Roll - RPM'!$R$3:$R$60,"") -> 46066 | R94: =_xlfn.XLOOKUP(D94,'Rent Roll - RPM'!$B$3:$B$60,'Rent Roll - RPM'!$S$3:$S$60,"") -> 46458 | S94: 2450 | T94: =S94/L94 -> 1.7192982
A95: 1 | B95: 35 | C95: 50 | D95: =IF(ISNUMBER(SEARCH("Bobby Meadow",F95)),LEFT(F95,FIND(" ",F95)-1)&"M",LEFT(F95,FIND(" ",F95)-1)&MID(F95,FIND(" ",F95)+1,1)) -> 21946M | E95: =IFERROR(IF(_xlfn.XMATCH(D95,'Rent Roll - RPM'!$B$3:$B$60,0,1)>0,"Match","No Match"),"No Match") -> Match | F95: 21946 Bobby Meadow Lane | G95: =_xlfn.XLOOKUP(D95,'Rent Roll - RPM'!$B$3:$B$60,'Rent Roll - RPM'!$D$3:$D$60,0) -> Odom, Clayton | I95: A2 | J95: Canary | K95: 2 Bed | L95: 1425 | M95: 3 | N95: Complete | O95: Tenant Occupied | P95: =_xlfn.XLOOKUP(D95,'Rent Roll - RPM'!$B$3:$B$60,'Rent Roll - RPM'!$Q$3:$Q$60,"") -> 45916 | Q95: =_xlfn.XLOOKUP($D95,'Rent Roll - RPM'!$B$3:$B$60,'Rent Roll - RPM'!$R$3:$R$60,"") -> 45916 | R95: =_xlfn.XLOOKUP(D95,'Rent Roll - RPM'!$B$3:$B$60,'Rent Roll - RPM'!$S$3:$S$60,"") -> 46371 | S95: 2450 | T95: =S95/L95 -> 1.7192982
A96: 1 | B96: 2 | C96: 110 | D96: =IF(ISNUMBER(SEARCH("Bobby Meadow",F96)),LEFT(F96,FIND(" ",F96)-1)&"M",LEFT(F96,FIND(" ",F96)-1)&MID(F96,FIND(" ",F96)+1,1)) -> 21910F | E96: =IFERROR(IF(_xlfn.XMATCH(D96,'Rent Roll - RPM'!$B$3:$B$60,0,1)>0,"Match","No Match"),"No Match") -> Match | F96: 21910 Ferguson Meadow Lane | G96: =_xlfn.XLOOKUP(D96,'Rent Roll - RPM'!$B$3:$B$60,'Rent Roll - RPM'!$D$3:$D$60,0) -> Calle, Natalia | I96: E2 | J96: Sparrow | K96: 2 Bed | L96: 1635 | M96: 6 | N96: 46006 | O96: Tenant Occupied | P96: =_xlfn.XLOOKUP(D96,'Rent Roll - RPM'!$B$3:$B$60,'Rent Roll - RPM'!$Q$3:$Q$60,"") -> 45884 | Q96: =_xlfn.XLOOKUP($D96,'Rent Roll - RPM'!$B$3:$B$60,'Rent Roll - RPM'!$R$3:$R$60,"") -> 45987 | R96: =_xlfn.XLOOKUP(D96,'Rent Roll - RPM'!$B$3:$B$60,'Rent Roll - RPM'!$S$3:$S$60,"") -> 46443 | S96: 2650 | T96: =S96/L96 -> 1.6207951
A97: 3 | B97: 4 | C97: 17 | D97: =IF(ISNUMBER(SEARCH("Bobby Meadow",F97)),LEFT(F97,FIND(" ",F97)-1)&"M",LEFT(F97,FIND(" ",F97)-1)&MID(F97,FIND(" ",F97)+1,1)) -> 22023F | E97: =IFERROR(IF(_xlfn.XMATCH(D97,'Rent Roll - RPM'!$B$3:$B$60,0,1)>0,"Match","No Match"),"No Match") -> Match | F97: 22023 Ferguson Meadow Lane | G97: =_xlfn.XLOOKUP(D97,'Rent Roll - RPM'!$B$3:$B$60,'Rent Roll - RPM'!$D$3:$D$60,0) -> Adewumi, Omolara | I97: F1 | J97: Raven | K97: 3 Bed | L97: 1852 | M97: 1 | N97: Complete | O97: Tenant Occupied | P97: =_xlfn.XLOOKUP(D97,'Rent Roll - RPM'!$B$3:$B$60,'Rent Roll - RPM'!$Q$3:$Q$60,"") -> 45862 | Q97: =_xlfn.XLOOKUP($D97,'Rent Roll - RPM'!$B$3:$B$60,'Rent Roll - RPM'!$R$3:$R$60,"") -> 45863 | R97: =_xlfn.XLOOKUP(D97,'Rent Roll - RPM'!$B$3:$B$60,'Rent Roll - RPM'!$S$3:$S$60,"") -> 46258 | S97: 2950 | T97: =S97/L97 -> 1.5928726
A98: 1 | B98: 52 | C98: 23 | D98: =IF(ISNUMBER(SEARCH("Bobby Meadow",F98)),LEFT(F98,FIND(" ",F98)-1)&"M",LEFT(F98,FIND(" ",F98)-1)&MID(F98,FIND(" ",F98)+1,1)) -> 22033L | E98: =IFERROR(IF(_xlfn.XMATCH(D98,'Rent Roll - RPM'!$B$3:$B$60,0,1)>0,"Match","No Match"),"No Match") -> Match | F98: 22033 Lesley Grove Lane | G98: =_xlfn.XLOOKUP(D98,'Rent Roll - RPM'!$B$3:$B$60,'Rent Roll - RPM'!$D$3:$D$60,0) -> Ciftci, Irmak | I98: A1 | J98: Canary | K98: 2 Bed | L98: 1425 | M98: 2 | N98: Complete | O98: Tenant Occupied | P98: =_xlfn.XLOOKUP(D98,'Rent Roll - RPM'!$B$3:$B$60,'Rent Roll - RPM'!$Q$3:$Q$60,"") -> 45856 | Q98: =_xlfn.XLOOKUP($D98,'Rent Roll - RPM'!$B$3:$B$60,'Rent Roll - RPM'!$R$3:$R$60,"") -> 45870 | R98: =_xlfn.XLOOKUP(D98,'Rent Roll - RPM'!$B$3:$B$60,'Rent Roll - RPM'!$S$3:$S$60,"") -> 46265 | S98: 2450 | T98: =S98/L98 -> 1.7192982
A99: 1 | B99: 45 | C99: 30 | D99: =IF(ISNUMBER(SEARCH("Bobby Meadow",F99)),LEFT(F99,FIND(" ",F99)-1)&"M",LEFT(F99,FIND(" ",F99)-1)&MID(F99,FIND(" ",F99)+1,1)) -> 22005L | E99: =IFERROR(IF(_xlfn.XMATCH(D99,'Rent Roll - RPM'!$B$3:$B$60,0,1)>0,"Match","No Match"),"No Match") -> Match | F99: 22005 Lesley Grove Lane | G99: =_xlfn.XLOOKUP(D99,'Rent Roll - RPM'!$B$3:$B$60,'Rent Roll - RPM'!$D$3:$D$60,0) -> Martinez, Melinda | I99: C3 | J99: Falcon | K99: 3 Bed | L99: 1909 | M99: 2 | N99: Complete | O99: Tenant Occupied | P99: =_xlfn.XLOOKUP(D99,'Rent Roll - RPM'!$B$3:$B$60,'Rent Roll - RPM'!$Q$3:$Q$60,"") -> 45856 | Q99: =_xlfn.XLOOKUP($D99,'Rent Roll - RPM'!$B$3:$B$60,'Rent Roll - RPM'!$R$3:$R$60,"") -> 45874 | R99: =_xlfn.XLOOKUP(D99,'Rent Roll - RPM'!$B$3:$B$60,'Rent Roll - RPM'!$S$3:$S$60,"") -> 46269 | S99: 3150 | T99: =S99/L99 -> 1.6500786
A100: 1 | B100: 32 | C100: 53 | D100: =IF(ISNUMBER(SEARCH("Bobby Meadow",F100)),LEFT(F100,FIND(" ",F100)-1)&"M",LEFT(F100,FIND(" ",F100)-1)&MID(F100,FIND(" ",F100)+1,1)) -> 21939M | E100: =IFERROR(IF(_xlfn.XMATCH(D100,'Rent Roll - RPM'!$B$3:$B$60,0,1)>0,"Match","No Match"),"No Match") -> Match | F100: 21939 Bobby Meadow Lane | G100: =_xlfn.XLOOKUP(D100,'Rent Roll - RPM'!$B$3:$B$60,'Rent Roll - RPM'!$D$3:$D$60,0) -> Cheeks, Sharonda | I100: B1 | J100: Mallard | K100: 3 Bed | L100: 1685 | M100: 3 | N100: Complete | O100: Tenant Occupied | P100: =_xlfn.XLOOKUP(D100,'Rent Roll - RPM'!$B$3:$B$60,'Rent Roll - RPM'!$Q$3:$Q$60,"") -> 45856 | Q100: =_xlfn.XLOOKUP($D100,'Rent Roll - RPM'!$B$3:$B$60,'Rent Roll - RPM'!$R$3:$R$60,"") -> 45941 | R100: =_xlfn.XLOOKUP(D100,'Rent Roll - RPM'!$B$3:$B$60,'Rent Roll - RPM'!$S$3:$S$60,"") -> 46366 | S100: 2750 | T100: =S100/L100 -> 1.6320475
A101: 1 | B101: 58 | C101: 10 | D101: =IF(ISNUMBER(SEARCH("Bobby Meadow",F101)),LEFT(F101,FIND(" ",F101)-1)&"M",LEFT(F101,FIND(" ",F101)-1)&MID(F101,FIND(" ",F101)+1,1)) -> 22038F | E101: =IFERROR(IF(_xlfn.XMATCH(D101,'Rent Roll - RPM'!$B$3:$B$60,0,1)>0,"Match","No Match"),"No Match") -> Match | F101: 22038 Ferguson Meadow Lane | G101: =_xlfn.XLOOKUP(D101,'Rent Roll - RPM'!$B$3:$B$60,'Rent Roll - RPM'!$D$3:$D$60,0) -> Ojediran, Olunife | I101: A1 | J101: Canary | K101: 2 Bed | L101: 1425 | M101: 1 | N101: Complete | O101: Tenant Occupied | P101: =_xlfn.XLOOKUP(D101,'Rent Roll - RPM'!$B$3:$B$60,'Rent Roll - RPM'!$Q$3:$Q$60,"") -> 45854 | Q101: =_xlfn.XLOOKUP($D101,'Rent Roll - RPM'!$B$3:$B$60,'Rent Roll - RPM'!$R$3:$R$60,"") -> 45856 | R101: =_xlfn.XLOOKUP(D101,'Rent Roll - RPM'!$B$3:$B$60,'Rent Roll - RPM'!$S$3:$S$60,"") -> 46312 | S101: 2450 | T101: =S101/L101 -> 1.7192982
A102: 3 | B102: 5 | C102: 18 | D102: =IF(ISNUMBER(SEARCH("Bobby Meadow",F102)),LEFT(F102,FIND(" ",F102)-1)&"M",LEFT(F102,FIND(" ",F102)-1)&MID(F102,FIND(" ",F102)+1,1)) -> 22027F | E102: =IFERROR(IF(_xlfn.XMATCH(D102,'Rent Roll - RPM'!$B$3:$B$60,0,1)>0,"Match","No Match"),"No Match") -> Match | F102: 22027 Ferguson Meadow Lane | G102: =_xlfn.XLOOKUP(D102,'Rent Roll - RPM'!$B$3:$B$60,'Rent Roll - RPM'!$D$3:$D$60,0) -> Egunjobi, Ransome | I102: B2 | J102: Mallard | K102: 3 Bed | L102: 1685 | M102: 1 | N102: Complete | O102: Tenant Occupied | P102: =_xlfn.XLOOKUP(D102,'Rent Roll - RPM'!$B$3:$B$60,'Rent Roll - RPM'!$Q$3:$Q$60,"") -> 45838 | Q102: =_xlfn.XLOOKUP($D102,'Rent Roll - RPM'!$B$3:$B$60,'Rent Roll - RPM'!$R$3:$R$60,"") -> 45839 | R102: =_xlfn.XLOOKUP(D102,'Rent Roll - RPM'!$B$3:$B$60,'Rent Roll - RPM'!$S$3:$S$60,"") -> 46234 | S102: 2750 | T102: =S102/L102 -> 1.6320475
A103: 1 | B103: 59 | C103: 9 | D103: =IF(ISNUMBER(SEARCH("Bobby Meadow",F103)),LEFT(F103,FIND(" ",F103)-1)&"M",LEFT(F103,FIND(" ",F103)-1)&MID(F103,FIND(" ",F103)+1,1)) -> 22034F | E103: =IFERROR(IF(_xlfn.XMATCH(D103,'Rent Roll - RPM'!$B$3:$B$60,0,1)>0,"Match","No Match"),"No Match") -> Match | F103: 22034 Ferguson Meadow Lane | G103: =_xlfn.XLOOKUP(D103,'Rent Roll - RPM'!$B$3:$B$60,'Rent Roll - RPM'!$D$3:$D$60,0) -> Maynard, Joseph | I103: A2 | J103: Canary | K103: 2 Bed | L103: 1425 | M103: 1 | N103: Complete | O103: Tenant Occupied | P103: =_xlfn.XLOOKUP(D103,'Rent Roll - RPM'!$B$3:$B$60,'Rent Roll - RPM'!$Q$3:$Q$60,"") -> 45834 | Q103: =_xlfn.XLOOKUP($D103,'Rent Roll - RPM'!$B$3:$B$60,'Rent Roll - RPM'!$R$3:$R$60,"") -> 45836 | R103: =_xlfn.XLOOKUP(D103,'Rent Roll - RPM'!$B$3:$B$60,'Rent Roll - RPM'!$S$3:$S$60,"") -> 46230 | S103: 2450 | T103: =S103/L103 -> 1.7192982
A104: 3 | B104: 8 | C104: 32 | D104: =IF(ISNUMBER(SEARCH("Bobby Meadow",F104)),LEFT(F104,FIND(" ",F104)-1)&"M",LEFT(F104,FIND(" ",F104)-1)&MID(F104,FIND(" ",F104)+1,1)) -> 22026L | E104: =IFERROR(IF(_xlfn.XMATCH(D104,'Rent Roll - RPM'!$B$3:$B$60,0,1)>0,"Match","No Match"),"No Match") -> Match | F104: 22026 Lesley Grove Lane | G104: =_xlfn.XLOOKUP(D104,'Rent Roll - RPM'!$B$3:$B$60,'Rent Roll - RPM'!$D$3:$D$60,0) -> Pipkin, Raquel | I104: D1 | J104: Phoenix | K104: 4 Bed | L104: 2431 | M104: 2 | N104: Complete | O104: Tenant Occupied | P104: =_xlfn.XLOOKUP(D104,'Rent Roll - RPM'!$B$3:$B$60,'Rent Roll - RPM'!$Q$3:$Q$60,"") -> 45832 | Q104: =_xlfn.XLOOKUP($D104,'Rent Roll - RPM'!$B$3:$B$60,'Rent Roll - RPM'!$R$3:$R$60,"") -> 45835 | R104: =_xlfn.XLOOKUP(D104,'Rent Roll - RPM'!$B$3:$B$60,'Rent Roll - RPM'!$S$3:$S$60,"") -> 46229 | S104: 3600 | T104: =S104/L104 -> 1.4808721
A105: 1 | B105: 67 | C105: 1 | D105: =IF(ISNUMBER(SEARCH("Bobby Meadow",F105)),LEFT(F105,FIND(" ",F105)-1)&"M",LEFT(F105,FIND(" ",F105)-1)&MID(F105,FIND(" ",F105)+1,1)) -> 22002F | E105: =IFERROR(IF(_xlfn.XMATCH(D105,'Rent Roll - RPM'!$B$3:$B$60,0,1)>0,"Match","No Match"),"No Match") -> Match | F105: 22002 Ferguson Meadow Lane | G105: =_xlfn.XLOOKUP(D105,'Rent Roll - RPM'!$B$3:$B$60,'Rent Roll - RPM'!$D$3:$D$60,0) -> Agbo, Chinwe | I105: A2 | J105: Canary | K105: 2 Bed | L105: 1425 | M105: 1 | N105: Complete | O105: Tenant Occupied | P105: =_xlfn.XLOOKUP(D105,'Rent Roll - RPM'!$B$3:$B$60,'Rent Roll - RPM'!$Q$3:$Q$60,"") -> 45821 | Q105: =_xlfn.XLOOKUP($D105,'Rent Roll - RPM'!$B$3:$B$60,'Rent Roll - RPM'!$R$3:$R$60,"") -> 45829 | R105: =_xlfn.XLOOKUP(D105,'Rent Roll - RPM'!$B$3:$B$60,'Rent Roll - RPM'!$S$3:$S$60,"") -> 46223 | S105: 2450 | T105: =S105/L105 -> 1.7192982
A106: 1 | B106: 55 | C106: 13 | D106: =IF(ISNUMBER(SEARCH("Bobby Meadow",F106)),LEFT(F106,FIND(" ",F106)-1)&"M",LEFT(F106,FIND(" ",F106)-1)&MID(F106,FIND(" ",F106)+1,1)) -> 22045L | E106: =IFERROR(IF(_xlfn.XMATCH(D106,'Rent Roll - RPM'!$B$3:$B$60,0,1)>0,"Match","No Match"),"No Match") -> Match | F106: 22045 Lesley Grove Lane | G106: =_xlfn.XLOOKUP(D106,'Rent Roll - RPM'!$B$3:$B$60,'Rent Roll - RPM'!$D$3:$D$60,0) -> Adaranijo, Idris | I106: A1 | J106: Canary | K106: 2 Bed | L106: 1425 | M106: 1 | N106: Complete | O106: Tenant Occupied | P106: =_xlfn.XLOOKUP(D106,'Rent Roll - RPM'!$B$3:$B$60,'Rent Roll - RPM'!$Q$3:$Q$60,"") -> 45812 | Q106: =_xlfn.XLOOKUP($D106,'Rent Roll - RPM'!$B$3:$B$60,'Rent Roll - RPM'!$R$3:$R$60,"") -> 45819 | R106: =_xlfn.XLOOKUP(D106,'Rent Roll - RPM'!$B$3:$B$60,'Rent Roll - RPM'!$S$3:$S$60,"") -> 46213 | S106: 2450 | T106: =S106/L106 -> 1.7192982
A107: 1 | B107: 63 | C107: 5 | D107: =IF(ISNUMBER(SEARCH("Bobby Meadow",F107)),LEFT(F107,FIND(" ",F107)-1)&"M",LEFT(F107,FIND(" ",F107)-1)&MID(F107,FIND(" ",F107)+1,1)) -> 22018F | E107: =IFERROR(IF(_xlfn.XMATCH(D107,'Rent Roll - RPM'!$B$3:$B$60,0,1)>0,"Match","No Match"),"No Match") -> Match | F107: 22018 Ferguson Meadow Lane | G107: =_xlfn.XLOOKUP(D107,'Rent Roll - RPM'!$B$3:$B$60,'Rent Roll - RPM'!$D$3:$D$60,0) -> Aro, Opeyemi | I107: B2 | J107: Mallard | K107: 3 Bed | L107: 1685 | M107: 1 | N107: Complete | O107: Tenant Occupied | P107: =_xlfn.XLOOKUP(D107,'Rent Roll - RPM'!$B$3:$B$60,'Rent Roll - RPM'!$Q$3:$Q$60,"") -> 45804 | Q107: =_xlfn.XLOOKUP($D107,'Rent Roll - RPM'!$B$3:$B$60,'Rent Roll - RPM'!$R$3:$R$60,"") -> 45809 | R107: =_xlfn.XLOOKUP(D107,'Rent Roll - RPM'!$B$3:$B$60,'Rent Roll - RPM'!$S$3:$S$60,"") -> 46568 | S107: 2750 | T107: =S107/L107 -> 1.6320475
A108: 1 | B108: 60 | C108: 8 | D108: =IF(ISNUMBER(SEARCH("Bobby Meadow",F108)),LEFT(F108,FIND(" ",F108)-1)&"M",LEFT(F108,FIND(" ",F108)-1)&MID(F108,FIND(" ",F108)+1,1)) -> 22030F | E108: =IFERROR(IF(_xlfn.XMATCH(D108,'Rent Roll - RPM'!$B$3:$B$60,0,1)>0,"Match","No Match"),"No Match") -> Match | F108: 22030 Ferguson Meadow Lane | G108: =_xlfn.XLOOKUP(D108,'Rent Roll - RPM'!$B$3:$B$60,'Rent Roll - RPM'!$D$3:$D$60,0) -> Roberts, Melissa | I108: A3 | J108: Canary | K108: 2 Bed | L108: 1425 | M108: 1 | N108: Complete | O108: Tenant Occupied | P108: =_xlfn.XLOOKUP(D108,'Rent Roll - RPM'!$B$3:$B$60,'Rent Roll - RPM'!$Q$3:$Q$60,"") -> 45797 | Q108: =_xlfn.XLOOKUP($D108,'Rent Roll - RPM'!$B$3:$B$60,'Rent Roll - RPM'!$R$3:$R$60,"") -> 45800 | R108: =_xlfn.XLOOKUP(D108,'Rent Roll - RPM'!$B$3:$B$60,'Rent Roll - RPM'!$S$3:$S$60,"") -> 46195 | S108: 2450 | T108: =S108/L108 -> 1.7192982
... A110: 1 | B110: 61 | C110: 7 | D110: =IF(ISNUMBER(SEARCH("Bobby Meadow",F110)),LEFT(F110,FIND(" ",F110)-1)&"M",LEFT(F110,FIND(" ",F110)-1)&MID(F110,FIND(" ",F110)+1,1)) -> 22026F | E110: =IFERROR(IF(_xlfn.XMATCH(D110,'Rent Roll - RPM'!$B$3:$B$60,0,1)>0,"Match","No Match"),"No Match") -> Match | F110: 22026 Ferguson Meadow Lane | G110: =_xlfn.XLOOKUP(D110,'Rent Roll - RPM'!$B$3:$B$60,'Rent Roll - RPM'!$D$3:$D$60,0) -> Maxwell, Felicia | I110: E1 | J110: Sparrow | K110: 2 Bed | L110: 1635 | M110: 1 | N110: Complete | O110: Tenant Occupied | P110: =_xlfn.XLOOKUP(D110,'Rent Roll - RPM'!$B$3:$B$60,'Rent Roll - RPM'!$Q$3:$Q$60,"") -> 45776 | Q110: =_xlfn.XLOOKUP($D110,'Rent Roll - RPM'!$B$3:$B$60,'Rent Roll - RPM'!$R$3:$R$60,"") -> 45778 | R110: =_xlfn.XLOOKUP(D110,'Rent Roll - RPM'!$B$3:$B$60,'Rent Roll - RPM'!$S$3:$S$60,"") -> 46173 | S110: 2650 | T110: =S110/L110 -> 1.6207951
A111: 1 | B111: 42 | C111: 43 | D111: =IF(ISNUMBER(SEARCH("Bobby Meadow",F111)),LEFT(F111,FIND(" ",F111)-1)&"M",IF(ISNUMBER(SEARCH("Bruce Rushing",F111)),LEFT(F111,FIND(" ",F111)-1)&"R",LEFT(F111,FIND(" ",F111)-1)&MID(F111,FIND(" ",F111)+1,1))) -> 21917R | E111: =IFERROR(IF(_xlfn.XMATCH(D111,'Rent Roll - RPM'!$B$3:$B$60,0,1)>0,"Match","No Match"),"No Match") -> Match | F111: 21917 Bruce Rushing Lane | G111: =_xlfn.XLOOKUP(D111,'Rent Roll - RPM'!$B$3:$B$60,'Rent Roll - RPM'!$D$3:$D$60,0) -> Jeffery, Laura | I111: B1 | J111: Mallard | K111: 3 Bed | L111: 1685 | M111: 3 | N111: Complete | O111: Tenant Occupied | P111: =_xlfn.XLOOKUP(D111,'Rent Roll - RPM'!$B$3:$B$60,'Rent Roll - RPM'!$Q$3:$Q$60,"") -> 45770 | Q111: =_xlfn.XLOOKUP($D111,'Rent Roll - RPM'!$B$3:$B$60,'Rent Roll - RPM'!$R$3:$R$60,"") -> 45856 | R111: =_xlfn.XLOOKUP(D111,'Rent Roll - RPM'!$B$3:$B$60,'Rent Roll - RPM'!$S$3:$S$60,"") -> 46251 | S111: 2750 | T111: =S111/L111 -> 1.6320475
...

Sheet Rent Roll - RPM
B1: Unit | C1: Resident | D1: Name | E1: Resident | F1: Unit | G1: Resident | H1: Unit | I1: Status | J1: Days | K1: Make | L1: Move | M1: Hold | N1: Hold | O1: Notice | P1: Move | Q1: Lease | R1: Lease | S1: Lease
E2: Rent | F2: Rent | G2: Deposit | H2: Deposit | J2: Vacant | K2: Ready | L2: In | N2: Until | P2: Out | Q2: Sign | R2: From | S2: To
B3: 22026F | C3: t0908304 | D3: Maxwell, Felicia | E3: 2650 | F3: 2650 | G3: 1000 | H3: 0 | I3: Notice | K3: 45772 | L3: 45778 | M3: No | O3: 46099 | P3: 46173 | Q3: 45776 | R3: 45778 | S3: 46173 | T3: Paste here leased not moved in
B4: 7306C | C4: t0913318 | D4: Williams, Anthony | E4: 2750 | F4: 2750 | G4: 0 | H4: 0 | I4: Applicant | J4: 475 | K4: 45891 | L4: 46150 | M4: No | R4: 46113 | S4: 46568
B5: 22029L | C5: t0751889 | D5: Maxwell, Felicia | E5: 3600 | F5: 3600 | G5: 0 | H5: 0 | I5: Future | J5: 219 | K5: 45891 | L5: 46174 | M5: No | Q5: 46099 | R5: 46174 | S5: 46568
B6: 7431L | C6: t0902211 | D6: Jones, Jillian | E6: 2650 | F6: 2650 | G6: 0 | H6: 0 | I6: Future | J6: 440 | K6: 45987 | L6: 46127 | M6: No | R6: 46127 | S6: 46521
B7: 22013L | C7: t0903492 | D7: Ajah, Grace | E7: 2950 | F7: 2950 | G7: 0 | H7: 0 | I7: Future | J7: 475 | K7: 45891 | L7: 46111 | M7: No | R7: 46111 | S7: 46506
T9: Paste here moved in units
B10: 21914F | C10: t0836706 | D10: Smith, Audrey | E10: 2450 | F10: 2450 | G10: 2450 | H10: 0 | I10: Current | K10: 46047 | L10: 46066 | M10: No | Q10: 45943 | R10: 46066 | S10: 46458
B11: 21915M | C11: t0840997 | D11: Hockaday, Gordon | E11: 2450 | F11: 2450 | G11: 2450 | H11: 0 | I11: Current | K11: 45993 | L11: 45993 | M11: No | Q11: 45950 | R11: 45993 | S11: 46447
B12: 21938M | C12: t0748186 | D12: Posadas, Yolanda | E12: 2450 | F12: 2450 | G12: 2450 | H12: 0 | I12: Current | K12: 45863 | L12: 45865 | M12: No | Q12: 45778 | R12: 45865 | S12: 46321
B13: 21946M | C13: t0810731 | D13: Odom, Clayton | E13: 2450 | F13: 2450 | G13: 2450 | H13: 0 | I13: Current | K13: 45911 | L13: 45916 | M13: No | Q13: 45916 | R13: 45916 | S13: 46371
B14: 21950M | C14: t0845369 | D14: Thomas, C Yvette | E14: 2450 | F14: 2450 | G14: 500 | H14: 0 | I14: Current | K14: 45923 | L14: 45999 | M14: No | Q14: 45961 | R14: 45999 | S14: 46394
B15: 22002F | C15: t0773895 | D15: Agbo, Chinwe | E15: 2450 | F15: 2450 | G15: 500 | H15: 0 | I15: Current | K15: 45754 | L15: 45829 | M15: No | Q15: 45821 | R15: 45829 | S15: 46223
B16: 22011F | C16: t0737373 | D16: Smith, Gabrielle | E16: 2450 | F16: 2450 | G16: 1000 | H16: 0 | I16: Current | K16: 45754 | L16: 45878 | M16: No | Q16: 45744 | R16: 45878 | S16: 46334
B17: 22014F | C17: t0743361 | D17: Green, Dominique | E17: 2450 | F17: 2450 | G17: 2450 | H17: 0 | I17: Current | K17: 45754 | L17: 45782 | M17: No | Q17: 45757 | R17: 45782 | S17: 46177
B18: 22015F | C18: t0742291 | D18: Olmsted, Deborah | E18: 2450 | F18: 2450 | G18: 1000 | H18: 0 | I18: Current | K18: 45754 | L18: 45777 | M18: No | Q18: 45758 | R18: 45777 | S18: 46232
B19: 22030F | C19: t0759978 | D19: Roberts, Melissa | E19: 2450 | F19: 2450 | G19: 2450 | H19: 0 | I19: Current | K19: 45772 | L19: 45800 | M19: No | Q19: 45797 | R19: 45800 | S19: 46195
B20: 22033L | C20: t0788773 | D20: Ciftci, Irmak | E20: 2450 | F20: 2450 | G20: 500 | H20: 0 | I20: Current | K20: 45859 | L20: 45870 | M20: No | Q20: 45856 | R20: 45870 | S20: 46265
B21: 22034F | C21: t0781667 | D21: Maynard, Joseph | E21: 2450 | F21: 2450 | G21: 500 | H21: 0 | I21: Current | K21: 45804 | L21: 45836 | M21: No | Q21: 45834 | R21: 45836 | S21: 46230
... B60: 7411H | C60: t0890574 | D60: Contreras, Kristina | E60: 2950 | F60: 2950 | G60: 500 | H60: 0 | I60: Current | K60: 46014 | L60: 46073 | M60: No | Q60: 46064 | R60: 46073 | S60: 46526

Sheet Lease Tracker
A1: LIGHTHAVEN | I1: A | J1: Canary
A2: LEASING STATUS | I2: B | J2: Mallard
B4: LEASED - NOT MOVED IN | C4: RESIDENT NAME | D4: MOVE IN DATE: | E4: PLAN TYPE
A5: 1
A6: =A5+1 -> 2 | B6: 7303 Leighton Meadow | C6: Phoebo Akloyo | D6: 45776 | E6: Raven | H6: Actual | I6: 45955 | J6: 45986 | K6: 46016 | L6: 46023 | M6: 46054 | N6: 46082 | O6: 46113 | P6: 46143 | Q6: 46174 | R6: 46204 | S6: 46235 | T6: 46266 | U6: 46296 | V6: 46327 | W6: 46357
A7: =A6+1 -> 3 | B7: 22029 Lesley Grove Lane | C7: Felicia Maxwell (onsite Transfer) | D7: 46174 | E7: Phoenix | H7: Beg Occ | I7: 21 | J7: =I8 -> 23 | K7: =J8 -> 27 | L7: =K8 -> 33 | M7: =L8 -> 41 | N7: =M8 -> 47 | O7: =N8 -> 53 | P7: =O8 -> 56 | Q7: =P8 -> 57 | ... W7: =V8 -> 57
A8: =A7+1 -> 4 | H8: Ending Occ | I8: 23 | J8: 27 | K8: 33 | L8: =K8+8 -> 41 | M8: =L8+M15+M14 -> 47 | N8: =M8+N15+N14 -> 53 | O8: =N8+O15+O14 -> 56 | P8: =O8+P15+P14 -> 57 | Q8: =P8+Q15+Q14 -> 57 | R8: =Q8+R15+R14 -> 57 | S8: =R8+S15+S14 -> 57 | T8: =S8+T15+T14 -> 57 | ... W8: =V8+W15+W14 -> 57
A9: =A8+1 -> 5 | H9: OCC % | I9: =I8/117 -> 0.1965812 | J9: =J8/117 -> 0.23076923 | K9: =K8/117 -> 0.28205128 | L9: =L8/117 -> 0.35042735 | M9: =M8/117 -> 0.4017094 | N9: =N8/117 -> 0.45299145 | O9: =O8/117 -> 0.47863248 | P9: =P8/117 -> 0.48717949 | ... W9: =W8/117 -> 0.48717949
A10: =A9+1 -> 6
A11: =A10+1 -> 7 | H11: Cumulative Leased | I11: =J11-J13 -> 29 | J11: 33 | K11: 39 | L11: 47 | M11: =L11+M13 -> 52 | N11: =M11+N13 -> 55 | O11: =N11+O13 -> 58 | P11: =O11+P13 -> 58 | Q11: =P11+Q13 -> 58 | R11: =Q11+R13 -> 58 | S11: =R11+S13 -> 58 | T11: =S11+T13 -> 58 | ... W11: =V11+W13 -> 58
A12: =A11+1 -> 8 | F12: % OCC | H12: % Leased | I12: =I11/117 -> 0.24786325 | J12: =J11/117 -> 0.28205128 | K12: =K11/117 -> 0.33333333 | L12: =L11/117 -> 0.4017094 | M12: =M11/117 -> 0.44444444 | N12: =N11/117 -> 0.47008547 | O12: =O11/117 -> 0.4957265 | P12: =P11/117 -> 0.4957265 | ... W12: =W11/117 -> 0.4957265
A13: =A12+1 -> 9 | H13: # of leases signed | I13: 8 | J13: 4 | K13: =K11-J11 -> 6 | L13: =L11-K11 -> 8 | M13: 5 | N13: 3 | O13: 3
A14: =A13+1 -> 10 | H14: # of Move-ins | I14: 1 | J14: =J8-J7 -> 4 | K14: =K8-K7 -> 6 | L14: =L8-L7 -> 8 | M14: 7 | N14: 6 | O14: 3 | P14: 1 | Q14: 1
H15: # of Move-outs / transfers | I15: 0 | J15: 0 | K15: 0 | L15: 0 | M15: -1 | Q15: -1
B16: LEASED - MOVED IN | D16: MOVE IN DATE: | E16: PLAN TYPE
A17: 1 | B17: 22015 Ferguson Meadow Lane | D17: 45777 | E17: A.2 | H17: 2026 Budget
A18: =A17+1 -> 2 | B18: 22026 Ferguson Meadow Lane | C18: Felicia Maxwell (onsite Transfer) | D18: 45778 | E18: E.1 | F18: Onsite Transfer 05/31/26 | H18: Beginning Occ | L18: 33 | M18: 40 | N18: 47 | O18: 52 | P18: 58 | Q18: 68 | R18: 77 | S18: 85 | T18: 91 | U18: 96 | V18: 100 | W18: 104
A19: =A18+1 -> 3 | B19: 22037 Lesley Grove Lane | D19: 45778 | E19: E.2 | H19: Ending Occ | L19: =L18+L20 -> 38 | M19: =M18+M20 -> 45 | N19: =N18+N20 -> 52 | O19: =O18+O20 -> 58 | P19: =P18+P20 -> 68 | Q19: =Q18+Q20 -> 77 | R19: =R18+R20 -> 85 | S19: =S18+S20 -> 91 | ... W19: =W18+W20 -> 107
A20: =A19+1 -> 4 | B20: 22014 Ferguson Meadow Lane | D20: 45782 | E20: B.1 | H20: # of Leases / month | L20: 5 | M20: 5 | N20: 5 | O20: 6 | P20: 10 | Q20: 9 | R20: 8 | S20: 6 | T20: 5 | U20: 4 | V20: 4 | W20: 3
A21: =A20+1 -> 5 | B21: 22030 Ferguson Meadow Lane | D21: 45800 | E21: A
A22: =A21+1 -> 6 | B22: 22018 Ferguson Meadow Lane | D22: 45809 | E22: B | H22: Projected Occ, Actual to Budget | M22: =(M11/117)*100 -> 44.444444
A23: =A22+1 -> 7 | B23: 22045 Lesley Grove Lane | D23: 45819 | E23: A
A24: =A23+1 -> 8 | B24: 22002 Ferguson Meadow Lane | D24: 45829 | E24: A | H24: Gross Absorption = Total number of units leased | N24: =K11-L11 -> -8
A25: =A24+1 -> 9 | B25: 22034 Ferguson Meadow Lane | D25: 45835 | E25: A | H25: Net Absorption = Total number of units leased minus the number of units vacated.
A26: =A25+1 -> 10 | B26: 22026 Lesley Grove Lane | D26: 45836 | E26: D
A27: =A26+1 -> 11 | B27: 22027 Ferguson Meadow Lane | D27: 45839 | E27: B
A28: =A27+1 -> 12 | B28: 21917 Bruce Rushing Lane | C28: L. Jeffrey | D28: 7/18/205 | E28: B.1
A29: =A28+1 -> 13 | B29: 22038 Ferguson Meadow Lane | D29: 45856 | E29: A
A30: =A29+1 -> 14 | B30: 21938 Bobby Meadow Lane | C30: Y Posadas | D30: 45865 | E30: A.2 | O30: =18/3 -> 6
A31: =A30+1 -> 15 | B31: 22023 Ferguson Meadow Lane | D31: 45863 | E31: F
A32: =A31+1 -> 16 | B32: 22041 Lesley Grove | D32: 46228 | E32: F
A33: =A32+1 -> 17 | B33: 22033 Lesley Grove | D33: 45870 | E33: A
A34: =A33+1 -> 18 | B34: 22005 Lesley Grove | D34: 45874 | E34: C
A35: =A34+1 -> 19 | B35: 21909 Bruce Rushing Lane | C35: H. Kim | D35: 45875 | E35: A | F35: Early Term - Relocating out of state - paying early term fee on 1/1 with rent. Move-out 2/14
A36: =A34+1 -> 19 | B36: 22011 Ferguson Meadow | D36: 45878 | E36: A.1
A37: =A36+1 -> 20 | B37: 21946 Bruce Rushing Lane | C37: C Odom | D37: 45898 | E37: A
A38: =A37+1 -> 21 | B38: 21939 Bobby Meadow Lane | C38: S Cheeks | D38: 45941 | E38: B
A39: =A38+1 -> 22 | B39: 7302 Corey Rushing Lane | D39: 45975 | E39: B
A40: =A39+1 -> 23 | B40: 22025 Lesley Grove Lane | D40: 45962 | E40: C1
A41: =A40+1 -> 24 | B41: 21954 Bobby meadow | D41: 45965 | E41: B
A42: =A41+1 -> 25 | B42: 22046 Ferguson Meadow Lane | C42: Rivera | D42: 45985 | E42: B
A43: =A42+1 -> 26 | B43: 21910 Ferguson Meadow Lane | C43: Calle | D43: 45987 | E43: E
A44: =A43+1 -> 27 | B44: 21915 Bobby Meadow Lane | C44: Hockaday | D44: 45993 | E44: A | H44: =31/117 -> 0.26495726 | J44: =48-15 -> 33
A45: =A44+1 -> 28 | B45: 7330 Leighton Meadow Ln | C45: Ikechukwu Nwagbosoma | D45: 45997 | E45: A | F45: =A46/117 -> 0.24786325
A46: =A45+1 -> 29 | B46: 21950 Bobby Meadow Lane | C46: Y Thomas | D46: 45999 | E46: A
A47: =A46+1 -> 30 | B47: 21913 Bruce Rushing | C47: Ibukunoluwa Oyeleke | D47: 46002 | E47: A | G47: =30/117 -> 0.25641026
A48: =A47+1 -> 31 | B48: 22035 Ferguson Meadow | C48: Sheela Isikwe | D48: 46003 | E48: B
A49: =A48+1 -> 32 | B49: 7419 Leighton Meadow Lane | C49: Blake Draper | D49: 46018 | E49: B
A50: =A49+1 -> 33 | B50: 21935 Bobby Meadow | C50: Vivian Akamimo | D50: 46028 | E50: B, Mallard
A51: =A50+1 -> 34 | B51: 7430 Hadley Meadow Lane | C51: Smit Patel | D51: 46029 | E51: A
A52: =A51+1 -> 35 | B52: 7419 Leighton Meadow Lane | C52: Sami Anjum | D52: 46029 | E52: B
A53: =A52+1 -> 36 | B53: 7307 Leighton Meadow | C53: Jeaneen Scott | D53: 46032 | E53: B
A54: =A53+1 -> 37 | B54: 7415 Hadley Meadow | C54: Tristan King | D54: 46037 | E54: B
A55: =A54+1 -> 38 | B55: 21927 Bobby Meadow Lane | C55: Ljeoma Akoma | D55: 46037 | E55: B
A56: =A55+1 -> 39 | B56: 22042 Ferguson Meadow Ln | C56: Beatriz Casiano | D56: 46037 | E56: Raven
A57: =A56+1 -> 40 | B57: 7326 Leighton Meadow | C57: Henry Chukwujiwu | D57: 46053 | E57: Mallard
A58: =A57+1 -> 41 | B58: 22019 Ferguson Meadow Ln | C58: Mahdi Ramazani | D58: 46063 | E58: A- Sparrow | F58: x
A59: =A58+1 -> 42 | B59: 21914 Ferguson Meadow Lane | C59: Audrey Smith | D59: 46066 | E59: A | F59: x
A60: =A59+1 -> 43 | B60: 7338 Hadley Meadow | C60: Elborno, Lana | D60: 46067 | E60: Mallard
A61: =A60+1 -> 44 | B61: 7411 Hadley Meadow | C61: Kristina Contreras | D61: 46073 | E61: Raven | F61: x
A62: =A61+1 -> 45 | B62: 7426 Hadley Meadow | C62: Fatimah Kotun | D62: 46073 | F62: x
A63: =A62+1 -> 46 | B63: 21903 Bobby Meadow Lane | C63: Erica Gutierrez | D63: 46076 | E63: Raven | F63: x
A64: =A63+1 -> 47 | B64: 21923 Bobby Meadow | C64: Britany Buchanan | D64: 46080 | E64: A
A65: =A64+1 -> 48 | B65: 21906 Ferguson Meadow | C65: Samantha Ogembo | D65: 46085 | E65: Mallard
A66: =A65+1 -> 49 | B66: 21902 Ferguson Meadow | C66: Oladeji Ogunjimi | D66: 46094 | E66: Raven
A67: =A66+1 -> 50 | B67: 7322 Corey Rushing | C67: N Wilson | D67: 46094 | E67: Phoenix
A68: =A67+1 -> 51 | B68: 7323 Hadley Meadow | C68: Chidimma Onyedebelu | D68: 46108 | E68: Mallard
A69: =A68+1 -> 52 | B69: 7435 Hadley Meadow | C69: Earnesto Gonzalez | D69: 46108 | E69: Raven
A70: =A69+1 -> 53 | B70: 22013 Leslie Grove | C70: Grace Ajah | D70: 46111 | E70: Raven
A71: =A70+1 -> 54 | B71: 22006 Ferguson Meadow Lane | C71: Jillian Jones | D71: 46127 | E71: Sparrow
A72: =A71+1 -> 55 | B72: 7422 Hadley Meadow | C72: Ikenna Eseadum | D72: 46127 | E72: Sparrow
A73: =A72+1 -> 56
A74: =A73+1 -> 57
B77: PENDING APPROVAL | D77: MOVE IN DATE: | E77: PLAN TYPE

Sheet Weekly Traffic
A1: 2026 Traffic Tracking Sheet
A2: January 2026
C3: Prospect | D3: Tours | E3: Apps | F3: Leases | G3: Cancels | H3: Denials | J3: Website | K3: Google Paid Search | L3: Zillow | M3: RentCafe | N3: Drive By | O3: Apt list | P3: Locaters | Q3: Direct mailer | R3: Google Biz | S3: Banners/Signage | T3: Knock | U3: Total
A4: Week 1 | B4: 12/29 -1/4 | C4: 28 | D4: 14 | E4: 5 | F4: =E4-G4-H4 -> 4 | G4: 1 | H4: 0 | J4: 11 | K4: 3 | L4: 2 | M4: 2 | N4: 6 | O4: 1 | P4: 2 | Q4: 1 | U4: =SUM(J4:R4) -> 28
A5: Week 2 | B5: 1/5 - 1/11 | C5: 22 | D5: 10 | E5: 3 | F5: =E5-G5-H5 -> 1 | G5: 0 | H5: 2 | J5: 6 | K5: 1 | L5: 2 | N5: 4 | P5: 4 | R5: 3 | S5: 1 | T5: 1 | U5: =SUM(J5:T5) -> 22
A6: Week 3 | B6: 1/12-1/18 | C6: 23 | D6: 8 | E6: 3 | F6: =E6-G6-H6 -> 2 | G6: 1 | H6: 0 | J6: 8 | K6: 4 | L6: 0 | M6: 2 | N6: 3 | O6: 0 | P6: 2 | Q6: 0 | R6: 3 | S6: 0 | T6: 1 | U6: =SUM(J6:T6) -> 23
A7: Week 4 | B7: 1/19-1/25 | C7: 25 | D7: 7 | E7: 2 | F7: =E7-G7-H7 -> 1 | G7: 0 | H7: 1 | U7: =SUM(J7:R7) -> 0
A8: Week 5 | B8: 1/26-2/1 | C8: 24 | D8: 8 | E8: 2 | F8: 0 | G8: 0 | H8: 1
A9: TOTALS - January | C9: =SUM(C4:C8) -> 122 | D9: =SUM(D4:D8) -> 47 | E9: =SUM(E4:E8) -> 15 | F9: =SUM(F4:F8) -> 8 | G9: =SUM(G4:G8) -> 2 | H9: =SUM(H4:H8) -> 4 | J9: =SUM(J4:J7) -> 25 | K9: =SUM(K4:K7) -> 8 | L9: =SUM(L4:L7) -> 4 | M9: =SUM(M4:M7) -> 4 | N9: =SUM(N4:N7) -> 13 | O9: =SUM(O4:O7) -> 1 | P9: =SUM(P4:P7) -> 8 | Q9: =SUM(Q4:Q7) -> 1 | ... U9: =SUM(U4:U7) -> 73
A10: conversions | D10: =D9/C9 -> 0.3852459 | E10: =E9/D9 -> 0.31914894 | F10: =F9/E9 -> 0.53333333 | J10: =J9/$U$28 -> 0.34246575 | K10: =K9/$U$28 -> 0.10958904 | L10: =L9/$U$28 -> 0.054794521 | M10: =M9/$U$28 -> 0.054794521 | N10: =N9/$U$28 -> 0.17808219 | O10: =O9/$U$28 -> 0.01369863 | P10: =P9/$U$28 -> 0.10958904 | Q10: =Q9/$U$28 -> 0.01369863 | ... U10: =U9/$U$28 -> 1
A11: 46054
C12: Prospect | D12: Tours | E12: Apps | F12: Leases | G12: Cancels | H12: Denials
A13: Week 6 | B13: 2/2-2/8 | C13: 17 | D13: 9 | E13: 2 | F13: 2 | G13: 0 | H13: 0 | U13: =SUM(J13:R13) -> 0
A14: Week 7 | B14: 2/9-2/15 | C14: 16 | D14: 3 | E14: 1 | F14: =E14-G14-H14 -> 1 | G14: 0 | H14: 0 | K14: 5 | M14: 4 | N14: 2 | S14: 2 | U14: =SUM(J14:R14) -> 11
A15: Week 8 | B15: 2/16-2/22 | C15: 19 | D15: 3 | E15: 2 | F15: =E15-G15-H15 -> 1 | G15: 1 | H15: 0 | J15: 3 | K15: 5 | L15: 1 | N15: 3 | P15: 4 | R15: 1 | S15: 1
A16: Week 9 | B16: 2/23-03/01 | C16: 13 | D16: 3 | E16: 2 | F16: =E16-G16-H16 -> 1 | G16: 0 | H16: 1 | J16: 6 | K16: 4 | L16: 1 | N16: 1
A17: TOTALS - February | C17: =SUM(C13:C16) -> 65 | D17: =SUM(D13:D16) -> 18 | E17: =SUM(E13:E16) -> 7 | F17: =SUM(F13:F16) -> 5 | G17: =SUM(G13:G16) -> 1 | H17: =SUM(H13:H16) -> 1 | J17: =SUM(J13:J16) -> 9 | K17: =SUM(K13:K16) -> 14 | L17: =SUM(L13:L16) -> 2 | M17: =SUM(M13:M16) -> 4 | N17: =SUM(N13:N16) -> 6 | O17: =SUM(O13:O16) -> 0 | P17: =SUM(P13:P16) -> 4 | Q17: =SUM(Q13:Q16) -> 0 | ... U17: =SUM(U13:U16) -> 11
A19: Week 10 | B19: 3/2-3/8 | C19: 6 | F19: =E19-G19-H19 -> 0
A20: Week 11
A21: Week 12
A22: Week 13
A23: Week 14
A24: Week 15
A25: Week 16
A26: Week 17
A28: TOTALS | B28: =SUM(B4:B27) -> 0 | C28: =C9+C17 -> 187 | D28: =D9 -> 47 | E28: =E9 -> 15 | F28: =F9 -> 8 | G28: =G9 -> 2 | H28: =H9 -> 4 | J28: =J9 -> 25 | K28: =K9 -> 8 | L28: =L9 -> 4 | M28: =M9 -> 4 | N28: =N9 -> 13 | O28: =O9 -> 1 | P28: =P9 -> 8 | Q28: =Q9 -> 1 | ... U28: =U9 -> 73
A29: conversions | D29: =D28/C28 -> 0.2513369 | E29: =E28/D28 -> 0.31914894 | F29: =F28/E28 -> 0.53333333 | J29: =J28/$U$28 -> 0.34246575 | K29: =K28/$U$28 -> 0.10958904 | L29: =L28/$U$28 -> 0.054794521 | M29: =M28/$U$28 -> 0.054794521 | N29: =N28/$U$28 -> 0.17808219 | O29: =O28/$U$28 -> 0.01369863 | P29: =P28/$U$28 -> 0.10958904 | Q29: =Q28/$U$28 -> 0.01369863 | ... U29: =U28/$U$28 -> 1

Sheet Leasing Pace
B1: Annual Projection - to- Budget Occupancy
B3: Occupancy | C3: 46023 | D3: 46054 | E3: 46082 | F3: 46113 | G3: 46143 | H3: 46174 | I3: 46204 | J3: 46235 | K3: 46266 | L3: 46296 | M3: 46327 | N3: 46357
B4: Beginning Occupied Units | C4: 33 | D4: =C6 -> 40 | E4: =D6 -> 45 | F4: =E6 -> 50 | G4: =F6 -> 56 | H4: =G6 -> 66 | I4: =H6 -> 75 | J4: =I6 -> 83 | K4: =J6 -> 89 | ... N4: =M6 -> 102
B5: Net change in Occupied units | C5: =C6-C4 -> 7 | D5: 5 | E5: 5 | F5: 6 | G5: 10 | H5: 9 | I5: 8 | J5: 6 | K5: 5 | L5: 4 | M5: 4 | N5: 3
B6: Ending Occupied Units | C6: 40 | D6: =D5+D4 -> 45 | E6: =E5+E4 -> 50 | F6: =F5+F4 -> 56 | G6: =G5+G4 -> 66 | H6: =H5+H4 -> 75 | I6: =I5+I4 -> 83 | J6: =J5+J4 -> 89 | K6: =K5+K4 -> 94 | ... N6: =N5+N4 -> 105
B7: Ending OCC % | C7: =C6/117 -> 0.34188034 | D7: =D6/117 -> 0.38461538 | E7: =E6/117 -> 0.42735043 | F7: =F6/117 -> 0.47863248 | G7: =G6/117 -> 0.56410256 | H7: =H6/117 -> 0.64102564 | I7: =I6/117 -> 0.70940171 | J7: =J6/117 -> 0.76068376 | ... N7: =N6/117 -> 0.8974359
B10: 2026 Budget | C10: 46023 | D10: 46054 | E10: 46082 | F10: 46113 | G10: 46143 | H10: 46174 | I10: 46204 | J10: 46235 | K10: 46266 | L10: 46296 | M10: 46327 | N10: 46357
B11: Beginning Occ | C11: 32 | D11: =C11+C14 -> 37 | E11: =D11+D14 -> 42 | F11: =E11+E14 -> 47 | G11: =F11+F14 -> 53 | H11: =G11+G14 -> 63 | I11: =H11+H14 -> 72 | J11: =I11+I14 -> 80 | K11: =J11+J14 -> 86 | ... N11: =M11+M14 -> 99
B12: Ending Occ | C12: =C11+C14 -> 37 | D12: =D11+D14 -> 42 | E12: =E11+E14 -> 47 | F12: =F11+F14 -> 53 | G12: =G11+G14 -> 63 | H12: =H11+H14 -> 72 | I12: =I11+I14 -> 80 | J12: =J11+J14 -> 86 | ... N12: =N11+N14 -> 102
B13: Ending OCC % | C13: =C12/117 -> 0.31623932 | D13: =D12/117 -> 0.35897436 | E13: =E12/117 -> 0.4017094 | F13: =F12/117 -> 0.45299145 | G13: =G12/117 -> 0.53846154 | H13: =H12/117 -> 0.61538462 | I13: =I12/117 -> 0.68376068 | J13: =J12/117 -> 0.73504274 | ... N13: =N12/117 -> 0.87179487
B14: # of Leases / month | C14: 5 | D14: 5 | E14: 5 | F14: 6 | G14: 10 | H14: 9 | I14: 8 | J14: 6 | K14: 5 | L14: 4 | M14: 4 | N14: 3
B16: Leasing Activity | C16: 46023 | D16: 46054 | E16: 46082 | F16: 46113 | G16: 46143 | H16: 46174 | I16: 46204 | J16: 46235 | K16: 46266 | L16: 46296 | M16: 46327 | N16: 46357
B17: # Lease - Beg of Month | C17: 39
B18: # of Leases Signed in the month | C18: =C19-C17 -> 7
B19: # of Leases - To Date | C19: 46 | D19: =C19+D22 -> 45 | E19: =D19 -> 45 | F19: =E19 -> 45 | G19: =F19 -> 45 | H19: =G19 -> 45 | I19: =H19 -> 45 | J19: =I19 -> 45 | K19: =J19 -> 45 | L19: =K19 -> 45 | ... N19: =M19 -> 45
B20: % Leased | C20: =C19/117 -> 0.39316239 | D20: =D19/117 -> 0.38461538 | E20: =E19/117 -> 0.38461538 | F20: =F19/117 -> 0.38461538 | G20: =G19/117 -> 0.38461538 | H20: =H19/117 -> 0.38461538 | I20: =I19/117 -> 0.38461538 | J20: =J19/117 -> 0.38461538 | ... N20: =N19/117 -> 0.38461538
B21: # of Leases / Month | D21: =D19-C19 -> -1 | E21: =E19-D19 -> 0 | F21: =F19-E19 -> 0 | G21: =G19-F19 -> 0 | H21: =H19-G19 -> 0 | I21: =I19-H19 -> 0 | J21: =J19-I19 -> 0 | K21: =K19-J19 -> 0 | ... N21: =N19-M19 -> 0
B22: # of Move-outs | D22: -1
C23: 46023
C24: Actual | D24: Budget

Sheet Rents 
G2: Original Proforma | J2: April 2025 | M2: July 2025 | P2: Market Rents | S2: Bridge Loan Proforma 2026 | V2: Effective Rents (Market Rents + Concessions) | Z2: 2025 RPM Budget | AC2: as of 10/2025
A4: Floorplan | B4: Floorplan ID # | C4: SF | D4: Bdrms | E4: # Units | F4: # Leased | G4: Original Rents | H4: Original Rents PSF | I4: Proforma Rents Annualized | J4: Updated* Rents | K4: Updated* Rents PSF | L4: Updated* Rents Annualized | M4: August '25 Avg Mkt Rents | N4: August '25 Mkt Rents PSF | O4: August '25 Mkt Rents Annualized | P4: Market Rents | Q4: Market Rents PSF | R4: Market Rents Annualized | S4: BL Market Rents | T4: BL - Rents PSF | U4: BL - Rents Annualized | V4: Current Effective Rents | W4: Current Effective Rents PSF | X4: Effective Rents Annualized | Y4: Market -Effective Rent Delta | Z4: Market Rents | AA4: Market Rents PSF | AB4: Market Rents Annualized | AC4: Avg Eff Rent | AD4: Eff Rent PSF | AE4: Eff Rents Annualized | AG4: Bridge Loan to Market Assumption Delta | AI4: Market -Effective Rent Delta | AK4: Eff Rent - Refi Rent Delta
A5: Canary | B5: THA / TH1 | C5: 1425 | D5: 2/2.5 | E5: 31 | F5: 16 | G5: 2600 | H5: =G5/C5 -> 1.8245614 | I5: =G5*E5*12 -> 967200 | J5: 2450 | K5: =J5/C5 -> 1.7192982 | L5: =J5*12*$E$5 -> 911400 | M5: 2450 | N5: =M5/$C$5 -> 1.7192982 | O5: =M5*12*$E$5 -> 911400 | P5: 2450 | Q5: =P5/$C5 -> 1.7192982 | R5: =P5*12*$E5 -> 911400 | S5: 2468 | T5: =S5/C5 -> 1.7319298 | U5: =S5*E5*12 -> 918096 | V5: 2238 | W5: =V5/$C5 -> 1.5705263 | X5: =V5*12*$E5 -> 832536 | Y5: =V5/P5-1 -> -0.086530612 | Z5: 2450 | AA5: =Z5/$C5 -> 1.7192982 | AB5: =Z5*12*$E5 -> 911400 | AC5: 2315 | AD5: =AC5/$C5 -> 1.6245614 | AE5: =AC5*12*$E5 -> 861180 | AG5: =S5/P5-1 -> 0.0073469388 | AI5: =V5/P5-1 -> -0.086530612 | AK5: =X5/U5-1 -> -0.093192869
A6: Sparrow | B6: THE / TH2 | C6: 1635 | D6: 2/2.5 | E6: 18 | F6: 3 | G6: 2900 | H6: =G6/C6 -> 1.7737003 | I6: =G6*E6*12 -> 626400 | J6: 2650 | K6: =J6/C6 -> 1.6207951 | L6: =J6*12*E6 -> 572400 | M6: 2650 | N6: =M6/C6 -> 1.6207951 | O6: =M6*12*E6 -> 572400 | P6: 2650 | Q6: =P6/$C6 -> 1.6207951 | R6: =P6*12*$E6 -> 572400 | S6: 2678 | T6: =S6/C6 -> 1.6379205 | U6: =S6*E6*12 -> 578448 | V6: 2356 | W6: =V6/$C6 -> 1.4409786 | X6: =V6*12*$E6 -> 508896 | Y6: =V6/P6-1 -> -0.1109434 | Z6: 2650 | AA6: =Z6/$C6 -> 1.6207951 | AB6: =Z6*12*$E6 -> 572400 | AC6: 2344 | AD6: =AC6/C6 -> 1.4336391 | AE6: =AC6*12*$E6 -> 506304 | AG6: =S6/P6-1 -> 0.010566038 | AI6: =V6/P6-1 -> -0.1109434 | AK6: =X6/U6-1 -> -0.12023898
A7: Mallard | B7: THB / TH3 | C7: 1685 | D7: 3/2.5 | E7: 25 | F7: 8 | G7: 3200 | H7: =G7/C7 -> 1.8991098 | I7: =G7*E7*12 -> 960000 | J7: 2950 | K7: =J7/C7 -> 1.7507418 | L7: =J7*12*E7 -> 885000 | M7: 2750 | N7: =M7/C7 -> 1.6320475 | O7: =M7*12*E7 -> 825000 | P7: 2750 | Q7: =P7/$C7 -> 1.6320475 | R7: =P7*12*$E7 -> 825000 | S7: 2788 | T7: =S7/C7 -> 1.6545994 | U7: =S7*E7*12 -> 836400 | V7: 2637 | W7: =V7/$C7 -> 1.5649852 | X7: =V7*12*$E7 -> 791100 | Y7: =V7/P7-1 -> -0.041090909 | Z7: 2750 | AA7: =Z7/$C7 -> 1.6320475 | AB7: =Z7*12*$E7 -> 825000 | AC7: 2433 | AD7: =AC7/C7 -> 1.4439169 | AE7: =AC7*12*$E7 -> 729900 | AG7: =S7/P7-1 -> 0.013818182 | AI7: =V7/P7-1 -> -0.041090909 | AK7: =X7/U7-1 -> -0.054160689
A8: Raven | B8: THF / TH4 | C8: 1852 | D8: 3/2.5 | E8: 21 | F8: 1 | G8: 3400 | H8: =G8/C8 -> 1.8358531 | I8: =G8*E8*12 -> 856800 | J8: 3150 | K8: =J8/C8 -> 1.7008639 | L8: =J8*12*E8 -> 793800 | M8: 2950 | N8: =M8/C8 -> 1.5928726 | O8: =M8*12*E8 -> 743400 | P8: 2950 | Q8: =P8/$C8 -> 1.5928726 | R8: =P8*12*$E8 -> 743400 | S8: 2971 | T8: =S8/C8 -> 1.6042117 | U8: =S8*E8*12 -> 748692 | V8: 2497 | W8: =V8/$C8 -> 1.3482721 | X8: =V8*12*$E8 -> 629244 | Y8: =V8/P8-1 -> -0.15355932 | Z8: 2950 | AA8: =Z8/$C8 -> 1.5928726 | AB8: =Z8*12*$E8 -> 743400 | AC8: 2610 | AD8: =AC8/C8 -> 1.4092873 | AE8: =AC8*12*$E8 -> 657720 | AG8: =S8/P8-1 -> 0.0071186441 | AI8: =V8/P8-1 -> -0.15355932 | AK8: =X8/U8-1 -> -0.15954224
A9: Falcon | B9: THC / TH5 | C9: 1909 | D9: 3/2.5 | E9: 16 | F9: 1 | G9: 3600 | H9: =G9/C9 -> 1.8858041 | I9: =G9*E9*12 -> 691200 | J9: 3250 | K9: =J9/C9 -> 1.702462 | L9: =J9*12*E9 -> 624000 | M9: 3150 | N9: =M9/C9 -> 1.6500786 | O9: =M9*12*E9 -> 604800 | P9: 3150 | Q9: =P9/$C9 -> 1.6500786 | R9: =P9*12*$E9 -> 604800 | S9: 3150 | T9: =S9/C9 -> 1.6500786 | U9: =S9*E9*12 -> 604800 | V9: 2815 | W9: =V9/$C9 -> 1.474594 | X9: =V9*12*$E9 -> 540480 | Y9: =V9/P9-1 -> -0.10634921 | Z9: 3150 | AA9: =Z9/$C9 -> 1.6500786 | AB9: =Z9*12*$E9 -> 604800 | AC9: 2787 | AD9: =AC9/C9 -> 1.4599267 | AE9: =AC9*12*$E9 -> 535104 | AG9: =S9/P9-1 -> 0 | AI9: =V9/P9-1 -> -0.10634921 | AK9: =X9/U9-1 -> -0.10634921
A10: Phoenix | B10: THD / TH6 | C10: 2431 | D10: 4/2.5 | E10: 6 | F10: 1 | G10: 4000 | H10: =G10/C10 -> 1.6454134 | I10: =G10*E10*12 -> 288000 | J10: 3600 | K10: =J10/C10 -> 1.4808721 | L10: =J10*12*E10 -> 259200 | M10: 3600 | N10: =M10/C10 -> 1.4808721 | O10: =M10*12*E10 -> 259200 | P10: 3600 | Q10: =P10/$C10 -> 1.4808721 | R10: =P10*12*$E10 -> 259200 | S10: 3600 | T10: =S10/C10 -> 1.4808721 | U10: =S10*E10*12 -> 259200 | V10: 3216.62 | W10: =V10/$C10 -> 1.3231674 | X10: =V10*12*$E10 -> 231596.64 | Y10: =V10/P10-1 -> -0.10649444 | Z10: 3600 | AA10: =Z10/$C10 -> 1.4808721 | AB10: =Z10*12*$E10 -> 259200 | AC10: 3208 | AD10: =AC10/C10 -> 1.3196216 | AE10: =AC10*12*$E10 -> 230976 | AG10: =S10/P10-1 -> 0 | AI10: =V10/P10-1 -> -0.10649444 | AK10: =X10/U10-1 -> -0.10649444
A11: TOTAL | C11: =((C5*E5)+(C6*E6)+(C7*E7)+(C8*E8)+(C9*E9)+(C10*E10))/E11 -> 1707.2821 | E11: =SUM(E5:E10) -> 117 | F11: =SUM(F5:F10) -> 30 | G11: =SUMPRODUCT(G5:G10,$E$5:$E$10)/E11 -> 3126.4957 | H11: =(I11/$C$11/12)/E11 -> 1.8312708 | I11: =SUM(I5:I10) -> 4389600 | J11: =SUMPRODUCT(J5:J10,$E$5:$E$10)/$E$11 -> 2881.6239 | K11: =L11/$C$11/12 -> 197.47762 | L11: =SUM(L5:L10) -> 4045800 | M11: =SUMPRODUCT(M5:M10,$E$5:$E$10)/$E$11 -> 2789.3162 | N11: =O11/$C$11/12 -> 191.15178 | O11: =SUM(O5:O10) -> 3916200 | P11: =SUMPRODUCT(P5:P10,$E$5:$E$10)/$E$11 -> 2789.3162 | Q11: =(R11/$C$11/12)/E11 -> 1.6337759 | R11: =SUM(R5:R10) -> 3916200 | S11: =SUMPRODUCT(S5:S10,$E$5:$E$10)/$E$11 -> 2810.2821 | T11: =SUMPRODUCT(T5:T10,$E$5:$E$10)/$E$11 -> 1.6539514 | U11: =SUM(U5:U10) -> 3945636 | V11: =SUMPRODUCT(V5:V10,$F$5:$F$10)/$F$11 -> 2416.6873 | W11: =SUMPRODUCT(W5:W10,$F$5:$F$10)/$F$11 -> 1.5372424 | X11: =SUM(X5:X10) -> 3533852.6 | Y11: =V11/P11-1 -> -0.13359149 | Z11: =SUMPRODUCT(Z5:Z10,$E$5:$E$10)/$E$11 -> 2789.3162 | AA11: =Z11/C11 -> 1.6337759 | AB11: =SUM(AB5:AB10) -> 3916200 | AC11: =SUMPRODUCT(AC5:AC10,$E$5:$E$10)/$E$11 -> 2507.9658 | AD11: =AC11/C11 -> 1.4689815 | AE11: =SUM(AE5:AE10) -> 3521184 | AG11: =S11/P11-1 -> 0.00751647 | AI11: =V11/P11-1 -> -0.13359149
N13: % Chg July / April | O13: =O11/L11-1 -> -0.03203322 | R13: Annualized Effective Rents | S13: With Proj. Concessions: | U13: 3635309 | X13: =SUM(X5:X10) -> 3533852.6 | AD13: % Chg July / Eff Rent | AE13: =AE11/O11-1 -> -0.10086717 | AK13: =X13/U13-1 -> -0.027908593
K14: % Chg - Orig | L14: =$L$11/$I$11-1 -> -0.078321487 | N14: % Chg - Orig | O14: =O11/I11-1 -> -0.10784582 | AD14: % Chg - Orig | AE14: =AE11/I11-1 -> -0.19783488
A21: * Per April 2025 Monthly Report

Sheet LeaseUp Template
A1: Lease-Up / Inventory Template
A2: LightHaven District West
A3: # of Units | B3: 117 | S3: 117
B4: 49 | E4: 41 | H4: =B4-E4+C23 -> 7 | K4: =B3-E4-H4 -> 69
B6: Executed Leases To Date | E6: Occupancy | H6: Future Occupancy | K6: Remaining Inventory
B7: =B4/B3 -> 0.41880342 | E7: =E4/B3 -> 0.35042735 | H7: =H4/B3 -> 0.05982906 | K7: =K4/B3 -> 0.58974359
A9: OCCUPANCY BY MONTH
B10: 46023 | C10: 46054 | D10: 46082 | E10: 46113 | F10: 46143 | G10: 46174 | H10: 46204 | I10: 46235 | J10: 46266 | K10: 46296 | L10: 46327 | M10: 46357 | N10: Total / Avg
A11: 2026 Budget
A12: Beginning | B12: 33 | C12: =B13 -> 40 | D12: =C13 -> 47 | E12: =D13 -> 52 | F12: =E13 -> 58 | G12: =F13 -> 68 | H12: =G13 -> 77 | I12: =H13 -> 85 | J12: =I13 -> 91 | ... M12: =L13 -> 104
A13: Ending OCC | B13: 40 | C13: 47 | D13: 52 | E13: 58 | F13: 68 | G13: 77 | H13: 85 | I13: 91 | J13: 96 | K13: 100 | L13: 104 | M13: 107 | N13: =M13 -> 107
A14: OCC % | B14: =B13/117 -> 0.34188034 | C14: =C13/117 -> 0.4017094 | D14: =D13/117 -> 0.44444444 | E14: =E13/117 -> 0.4957265 | F14: =F13/117 -> 0.58119658 | G14: =G13/117 -> 0.65811966 | H14: =H13/117 -> 0.72649573 | I14: =I13/117 -> 0.77777778 | ... N14: =N13/117 -> 0.91452991
A17: Actual + Projected
A18: Beginning | B18: 33 | C18: =B19 -> 41 | D18: =C19 -> 47 | E18: =D19 -> 53 | F18: =E19 -> 56 | G18: =F19 -> 57 | H18: =G19 -> 57 | I18: =H19 -> 57 | J18: =I19 -> 57 | ... N18: =M19 -> 57
A19: Ending OCC | B19: 41 | C19: =B19+C22+C23 -> 47 | D19: =D18+SUM(D22:D23) -> 53 | E19: =E18+SUM(E22:E23) -> 56 | F19: =F18+SUM(F22:F23) -> 57 | G19: =G18+SUM(G22:G23) -> 57 | H19: =H18+SUM(H22:H23) -> 57 | I19: =I18+SUM(I22:I23) -> 57 | J19: =J18+SUM(J22:J23) -> 57 | K19: =K18+SUM(K22:K23) -> 57 | ... M19: =M18+SUM(M22:M23) -> 57 | N19: =M19 -> 57
A20: OCC % | B20: =B18/117 -> 0.28205128 | C20: =C19/$B$3 -> 0.4017094 | D20: =D19/$B$3 -> 0.45299145 | E20: =E19/$B$3 -> 0.47863248 | F20: =F19/$B$3 -> 0.48717949 | G20: =G19/$B$3 -> 0.48717949 | H20: =H19/$B$3 -> 0.48717949 | I20: =I19/$B$3 -> 0.48717949 | J20: =J19/$B$3 -> 0.48717949 | ... N20: =N19/$B$3 -> 0.48717949
A22: Move-ins | B22: =B19-B18 -> 8 | C22: ='Lease Tracker'!M14 -> 7 | D22: ='Lease Tracker'!N14 -> 6 | E22: ='Lease Tracker'!O14 -> 3 | F22: ='Lease Tracker'!P14 -> 1 | G22: ='Lease Tracker'!Q14 -> 1 | H22: ='Lease Tracker'!R14 -> 0 | I22: ='Lease Tracker'!S14 -> 0 | J22: ='Lease Tracker'!T14 -> 0 | ... M22: ='Lease Tracker'!W14 -> 0 | N22: =SUM(B22:M22) -> 26
A23: Move-Outs | C23: ='Lease Tracker'!M15 -> -1 | D23: ='Lease Tracker'!N15 -> 0 | E23: ='Lease Tracker'!O15 -> 0 | F23: ='Lease Tracker'!P15 -> 0 | G23: ='Lease Tracker'!Q15 -> -1 | H23: ='Lease Tracker'!R15 -> 0 | I23: ='Lease Tracker'!S15 -> 0 | J23: ='Lease Tracker'!T15 -> 0 | ... M23: ='Lease Tracker'!W15 -> 0 | N23: =SUM(B23:M23) -> -2
A25: # Units Leased, Actual | B25: ='Lease Tracker'!L13 -> 8 | C25: ='Lease Tracker'!M13 -> 5 | D25: ='Lease Tracker'!N13 -> 3 | E25: ='Lease Tracker'!O13 -> 3 | F25: ='Lease Tracker'!P13 -> 0 | G25: ='Lease Tracker'!Q13 -> 0 | H25: ='Lease Tracker'!R13 -> 0 | I25: ='Lease Tracker'!S13 -> 0 | ... M25: ='Lease Tracker'!W13 -> 0 | N25: =SUM(B25:M25) -> 19
A26: Cumulative Leases | B26: 47 | C26: =B26+C25 -> 52 | D26: =C26+D25 -> 55 | E26: =D26+E25 -> 58 | F26: =E26+F25 -> 58 | G26: =F26+G25 -> 58 | H26: =G26+H25 -> 58 | I26: =H26+I25 -> 58 | J26: =I26+J25 -> 58 | ... M26: =L26+M25 -> 58 | N26: =M26 -> 58
A28: Internal Proforma | B28: 44 | C28: 52 | D28: 60 | E28: 68 | F28: 76 | G28: 84 | H28: 92 | I28: 100 | J28: 108 | K28: 116 | L28: 116 | M28: 116 | N28: 116
A29: Ending OCC % | B29: =B28/117 -> 0.37606838 | C29: =C28/117 -> 0.44444444 | D29: =D28/117 -> 0.51282051 | E29: =E28/117 -> 0.58119658 | F29: =F28/117 -> 0.64957265 | G29: =G28/117 -> 0.71794872 | H29: =H28/117 -> 0.78632479 | I29: =I28/117 -> 0.85470085 | ... N29: =N28/117 -> 0.99145299
A31: LEASING PACE
B32: 46023 | C32: 46054 | D32: 46082 | E32: 46113 | F32: 46143 | G32: 46174 | H32: 46204 | I32: 46235 | J32: 46266 | K32: 46296 | L32: 46327 | M32: 46357 | N32: Average
A33: Actual, monthly | B33: 8 | C33: =C25 -> 5 | O33: <---replace with chart in Power BI
A34: Budget, monthly | B34: =B13-B12 -> 7 | C34: =C13-C12 -> 7 | D34: =D13-D12 -> 5 | E34: =E13-E12 -> 6 | F34: =F13-F12 -> 10 | G34: =G13-G12 -> 9 | H34: =H13-H12 -> 8 | I34: =I13-I12 -> 6 | ... N34: =N13-N12 -> 107
A35: Favorable/(Unfav) | B35: =B33-B34 -> 1 | C35: =C33-C34 -> -2 | D35: =D33-D34 -> -5 | E35: =E33-E34 -> -6 | F35: =F33-F34 -> -10 | G35: =G33-G34 -> -9 | H35: =H33-H34 -> -8 | I35: =I33-I34 -> -6 | ... N35: =N33-N34 -> -107
A37: LEASING SUMMARY
B38: Total Visits | C38: Leases | D38: Cancels | E38: Denials | F38: Net Leases | G38: Avg. Rent / Unit | I38: Proforma Rent per Unit
A39: For the Month
A40: Year to Date
E42: Total Leads | F42: Prospects | G42: Tours | H42: Applications | I42: Leases
D43: Qty | E43: 31 | F43: 25 | G43: 18 | H43: 6 | I43: 5
D44: Conversion % | F44: =F43/E43 -> 0.80645161 | G44: =G43/F43 -> 0.72 | H44: =H43/G43 -> 0.33333333 | I44: =I43/H43 -> 0.83333333
A45: KPIs | B45: Lead>Prosp. | C45: 60% or higher | E45: Prospects>Tours | F45: 25% or higher | H45: Tour >App | I45: 35% or higher
A46: Comments:
A47: Pace has kept strong from Q4 2025 into the new year. Although traffic has slowed down, our conversions have increased with an 83% conversion from Apps to Leases
A48: for the month. We netted 7 new move-ins adding in January and signed 7 new leases, bring total leases to 4 (39.3%).
A50: LEASING BY PHASE
B51: Phase 1 | C51: Phase 2 | D51: Phase 3 | E51: Phase 4 | F51: Phase 5 | G51: Phase 6 | H51: Total | J51: Commentary
A52: Floorplan | B52: Complete | C52: T/O Date | D52: T/O Date | E52: T/O Date | F52: T/O Date | G52: T/O Date | H52: Units / Plan
A53: Canary | B53: 8/8 | C53: 2/2 | D53: 0.83333333 | E53: 0.2 | F53: 0.16666667 | G53: 0.25 | H53: 0.58064516
A54: Sparrow
A55: Mallard | B55: 8/8 | C55: 0.5 | D55: 0.75
A56: Raven
A57: Falcon
A58: Phoenix
A59: Total Units / Phase | B59: 16/16 | C59: 0.75 | D59: 0.8 | E59: 0.2 | F59: 0.16666667 | G59: 0.25
A60: SUMMARY BY FLOORPLAN
A61: Floorplan | B61: Bedrooms | C61: Unit Count | D61: Unit SF | E61: # Leased | F61: % Leased | G61: Units Occupied | H61: % Occupied | I61: # Avail | J61: Market Rent | K61: Market $/ SF | L61: Effective Rent | M61: Effective $/ SF
A62: Canary
A63: Sparrow
A64: Mallard
A65: Raven
A66: Falcon
A67: Phoenix
A68: TOTAL / AVERAGE
A69: RENT REVIEW
B70: 46023 | C70: 46054 | D70: 46082 | E70: 46113 | F70: 46143 | G70: 46174 | H70: 46204 | I70: 46235 | J70: 46266 | K70: 46296 | L70: 46327 | M70: 46357 | N70: 46357
A71: Proforma
A72: Budget
A73: Market
A74: Effective (Actual)
A76: MARKETING PERFORMANCE
A77: TOP LEAD SOURCES
B78: 46023 | C78: 46054 | D78: 46082 | E78: 46113 | F78: 46143 | G78: 46174 | H78: 46204 | I78: 46235 | J78: 46266 | K78: 46296 | L78: 46327 | M78: 46357
A79: Property Website | B79: =11+6 -> 17
A80: Locator/Realtor | B80: =2+4 -> 6
A81: Drive By | B81: =6+4 -> 10
A82: Google Business | B82: 3
A83: Zillow | B83: =2+2 -> 4
A84: Google Paid Search | B84: =3+1 -> 4
A86: Our current marketing monthly spend is $10,920 with a strong continued focus on our digital platorform. In Q4, most leases were driven by Google channels, include GBP, Google Search and the property website, reinforcing the importance of maintaining a strong presence across Google's channels. We continue to see this trend continue into 2026 with the website being the top lead generator. When looking into the website sources/mediums, Google organic search, paid search and direct traffic were the strongest.
A90: CURRENT INCENTIVES
A92: Current Leasing Incentives: | F92: Proposed leasing specials below were approved:
A93: 4 Weeks Free – Canary (Must move in by 2/28) | F93: o 4 Weeks Free – Canary (Must move in by 3/15); 2 Weeks Free if move-in is after 3/15
A94: 6 Weeks Free – Sparrow (Must move in by 2/28) | F94: o 8 Weeks Free – Sparrow (Must move in by 3/15); 4 Weeks Free if move-in is after 3/15
A95: 8 Weeks Free – All 3- and 4-bedroom floor plans (Must move in by 2/28) | F95: o 4 Weeks Free – Mallard (Must move in by 3/15); 2 Weeks Free if move-in is after 3/15
F96: o 8 Weeks Free – Raven, Falcon, and Phoenix (Must move in by 3/15 ); 4 Weeks Free if move-in after 3/15
